Workbook
Name Gen_Ind: 'Main Data'!$AE:$AE
Name Latestmonth: Transpose!$DW:$DW
Name May: Transpose!$DW:$DW
Name Month: 'Main Data'!$C:$C
Name Name: Transpose!$DW:$DW
Name Sector: 'Main Data'!$A:$A
Name Year: 'Main Data'!$B:$B

Sheet Backup
A1: Sector | B1: Year | C1: Month | D1: Cereals and products | E1: Meat and fish | F1: Egg | G1: Milk and products | H1: Oils and fats | I1: Fruits | J1: Vegetables | K1: Pulses and products | L1: Sugar and Confectionery | M1: Spices | N1: Non-alcoholic beverages | O1: Prepared meals, snacks, sweets etc. | P1: Food and beverages | Q1: Pan, tobacco and intoxicants | R1: Clothing | S1: Footwear | T1: Clothing and footwear | U1: Housing | V1: Fuel and light | W1: Household goods and services | X1: Health | Y1: Transport and communication | Z1: Recreation and amusement | AA1: Education | AB1: Personal care and effects | AC1: Miscellaneous | AD1: General index
A2: Rural | B2: 2013 | C2: January | D2: 107.5 | E2: 106.3 | F2: 108.1 | G2: 104.9 | H2: 106.1 | I2: 103.9 | J2: 101.9 | K2: 106.1 | L2: 106.8 | M2: 103.1 | N2: 104.8 | O2: 106.7 | P2: 105.5 | Q2: 105.1 | R2: 106.5 | S2: 105.8 | T2: 106.4 | U2: NA | V2: 105.5 | W2: 104.8 | X2: 104 | Y2: 103.3 | Z2: 103.4 | AA2: 103.8 | AB2: 104.7 | AC2: 104 | AD2: 105.1
A3: Urban | B3: 2013 | C3: January | D3: 110.5 | E3: 109.1 | F3: 113 | G3: 103.6 | H3: 103.4 | I3: 102.3 | J3: 102.9 | K3: 105.8 | L3: 105.1 | M3: 101.8 | N3: 105.1 | O3: 107.9 | P3: 105.9 | Q3: 105.2 | R3: 105.9 | S3: 105 | T3: 105.8 | U3: 100.3 | V3: 105.4 | W3: 104.8 | X3: 104.1 | Y3: 103.2 | Z3: 102.9 | AA3: 103.5 | AB3: 104.3 | AC3: 103.7 | AD3: 104
A4: Rural+Urban | B4: 2013 | C4: January | D4: 108.4 | E4: 107.3 | F4: 110 | G4: 104.4 | H4: 105.1 | I4: 103.2 | J4: 102.2 | K4: 106 | L4: 106.2 | M4: 102.7 | N4: 104.9 | O4: 107.3 | P4: 105.6 | Q4: 105.1 | R4: 106.3 | S4: 105.5 | T4: 106.2 | U4: 100.3 | V4: 105.5 | W4: 104.8 | X4: 104 | Y4: 103.2 | Z4: 103.1 | AA4: 103.6 | AB4: 104.5 | AC4: 103.9 | AD4: 104.6
A5: Rural | B5: 2013 | C5: February | D5: 109.2 | E5: 108.7 | F5: 110.2 | G5: 105.4 | H5: 106.7 | I5: 104 | J5: 102.4 | K5: 105.9 | L5: 105.7 | M5: 103.1 | N5: 105.1 | O5: 107.7 | P5: 106.3 | Q5: 105.6 | R5: 107.1 | S5: 106.3 | T5: 107 | U5: NA | V5: 106.2 | W5: 105.2 | X5: 104.4 | Y5: 103.9 | Z5: 104 | AA5: 104.1 | AB5: 104.6 | AC5: 104.4 | AD5: 105.8
A6: Urban | B6: 2013 | C6: February | D6: 112.9 | E6: 112.9 | F6: 116.9 | G6: 104 | H6: 103.5 | I6: 103.1 | J6: 104.9 | K6: 104.1 | L6: 103.8 | M6: 102.3 | N6: 106 | O6: 109 | P6: 107.2 | Q6: 106 | R6: 106.6 | S6: 105.5 | T6: 106.4 | U6: 100.4 | V6: 105.7 | W6: 105.2 | X6: 104.7 | Y6: 104.4 | Z6: 103.3 | AA6: 103.7 | AB6: 104.3 | AC6: 104.3 | AD6: 104.7
A7: Rural+Urban | B7: 2013 | C7: February | D7: 110.4 | E7: 110.2 | F7: 112.8 | G7: 104.9 | H7: 105.5 | I7: 103.6 | J7: 103.2 | K7: 105.3 | L7: 105.1 | M7: 102.8 | N7: 105.5 | O7: 108.3 | P7: 106.6 | Q7: 105.7 | R7: 106.9 | S7: 106 | T7: 106.8 | U7: 100.4 | V7: 106 | W7: 105.2 | X7: 104.5 | Y7: 104.2 | Z7: 103.6 | AA7: 103.9 | AB7: 104.5 | AC7: 104.4 | AD7: 105.3
A8: Rural | B8: 2013 | C8: March | D8: 110.2 | E8: 108.8 | F8: 109.9 | G8: 105.6 | H8: 106.2 | I8: 105.7 | J8: 101.4 | K8: 105.7 | L8: 105 | M8: 103.3 | N8: 105.6 | O8: 108.2 | P8: 106.6 | Q8: 106.5 | R8: 107.6 | S8: 106.8 | T8: 107.5 | U8: NA | V8: 106.1 | W8: 105.6 | X8: 104.7 | Y8: 104.6 | Z8: 104 | AA8: 104.3 | AB8: 104.3 | AC8: 104.6 | AD8: 106
A9: Urban | B9: 2013 | C9: March | D9: 113.9 | E9: 111.4 | F9: 113.2 | G9: 104.3 | H9: 102.7 | I9: 104.9 | J9: 103.8 | K9: 103.5 | L9: 102.6 | M9: 102.4 | N9: 107 | O9: 109.8 | P9: 107.3 | Q9: 106.8 | R9: 107.2 | S9: 106 | T9: 107 | U9: 100.4 | V9: 106 | W9: 105.7 | X9: 105.2 | Y9: 105.5 | Z9: 103.5 | AA9: 103.8 | AB9: 104.2 | AC9: 104.9 | AD9: 105
A10: Rural+Urban | B10: 2013 | C10: March | D10: 111.4 | E10: 109.7 | F10: 111.2 | G10: 105.1 | H10: 104.9 | I10: 105.3 | J10: 102.2 | K10: 105 | L10: 104.2 | M10: 103 | N10: 106.2 | O10: 108.9 | P10: 106.9 | Q10: 106.6 | R10: 107.4 | S10: 106.5 | T10: 107.3 | U10: 100.4 | V10: 106.1 | W10: 105.6 | X10: 104.9 | Y10: 105.1 | Z10: 103.7 | AA10: 104 | AB10: 104.3 | AC10: 104.7 | AD10: 105.5
A11: Rural | B11: 2013 | C11: April | D11: 110.2 | E11: 109.5 | F11: 106.9 | G11: 106.3 | H11: 105.7 | I11: 108.3 | J11: 103.4 | K11: 105.7 | L11: 104.2 | M11: 103.2 | N11: 106.5 | O11: 108.8 | P11: 107.1 | Q11: 107.1 | R11: 108.1 | S11: 107.4 | T11: 108 | U11: NA | V11: 106.5 | W11: 106.1 | X11: 105.1 | Y11: 104.4 | Z11: 104.5 | AA11: 104.8 | AB11: 102.7 | AC11: 104.6 | AD11: 106.4
A12: Urban | B12: 2013 | C12: April | D12: 114.6 | E12: 113.4 | F12: 106 | G12: 104.7 | H12: 102.1 | I12: 109.5 | J12: 109.7 | K12: 104.6 | L12: 102 | M12: 103.5 | N12: 108.2 | O12: 110.6 | P12: 108.8 | Q12: 108.5 | R12: 107.9 | S12: 106.4 | T12: 107.7 | U12: 100.5 | V12: 106.4 | W12: 106.5 | X12: 105.7 | Y12: 105 | Z12: 104 | AA12: 105.2 | AB12: 103.2 | AC12: 105.1 | AD12: 105.7
A13: Rural+Urban | B13: 2013 | C13: April | D13: 111.6 | E13: 110.9 | F13: 106.6 | G13: 105.7 | H13: 104.4 | I13: 108.9 | J13: 105.5 | K13: 105.3 | L13: 103.5 | M13: 103.3 | N13: 107.2 | O13: 109.6 | P13: 107.7 | Q13: 107.5 | R13: 108 | S13: 107 | T13: 107.9 | U13: 100.5 | V13: 106.5 | W13: 106.3 | X13: 105.3 | Y13: 104.7 | Z13: 104.2 | AA13: 105 | AB13: 102.9 | AC13: 104.8 | AD13: 106.1
A14: Rural | B14: 2013 | C14: May | D14: 110.9 | E14: 109.8 | F14: 105.9 | G14: 107.5 | H14: 105.3 | I14: 108.1 | J14: 107.3 | K14: 106.1 | L14: 103.7 | M14: 104 | N14: 107.4 | O14: 109.9 | P14: 108.1 | Q14: 108.1 | R14: 108.8 | S14: 107.9 | T14: 108.6 | U14: NA | V14: 107.5 | W14: 106.8 | X14: 105.7 | Y14: 104.1 | Z14: 105 | AA14: 105.5 | AB14: 102.1 | AC14: 104.8 | AD14: 107.2
A15: Urban | B15: 2013 | C15: May | D15: 115.4 | E15: 114.2 | F15: 102.7 | G15: 105.5 | H15: 101.5 | I15: 110.6 | J15: 123.7 | K15: 105.2 | L15: 101.9 | M15: 105 | N15: 109.1 | O15: 111.3 | P15: 111.1 | Q15: 109.8 | R15: 108.5 | S15: 106.7 | T15: 108.3 | U15: 100.5 | V15: 107.2 | W15: 107.1 | X15: 106.2 | Y15: 103.9 | Z15: 104.6 | AA15: 105.7 | AB15: 102.6 | AC15: 104.9 | AD15: 106.6
A16: Rural+Urban | B16: 2013 | C16: May | D16: 112.3 | E16: 111.3 | F16: 104.7 | G16: 106.8 | H16: 103.9 | I16: 109.3 | J16: 112.9 | K16: 105.8 | L16: 103.1 | M16: 104.3 | N16: 108.1 | O16: 110.5 | P16: 109.2 | Q16: 108.6 | R16: 108.7 | S16: 107.4 | T16: 108.5 | U16: 100.5 | V16: 107.4 | W16: 106.9 | X16: 105.9 | Y16: 104 | Z16: 104.8 | AA16: 105.6 | AB16: 102.3 | AC16: 104.8 | AD16: 106.9
A17: Rural | B17: 2013 | C17: June | D17: 112.3 | E17: 112.1 | F17: 108.1 | G17: 108.3 | H17: 105.9 | I17: 109.2 | J17: 118 | K17: 106.8 | L17: 104.1 | M17: 105.4 | N17: 108.2 | O17: 111 | P17: 110.6 | Q17: 109 | R17: 109.7 | S17: 108.8 | T17: 109.5 | U17: NA | V17: 108.5 | W17: 107.5 | X17: 106.3 | Y17: 105 | Z17: 105.6 | AA17: 106.5 | AB17: 102.5 | AC17: 105.5 | AD17: 108.9
A18: Urban | B18: 2013 | C18: June | D18: 117 | E18: 120.1 | F18: 112.5 | G18: 107.3 | H18: 101.3 | I18: 112.4 | J18: 143.6 | K18: 105.4 | L18: 101.4 | M18: 106.4 | N18: 110 | O18: 112.2 | P18: 115 | Q18: 110.9 | R18: 109.2 | S18: 107.2 | T18: 108.9 | U18: 106.6 | V18: 108 | W18: 107.7 | X18: 106.5 | Y18: 105.2 | Z18: 105.2 | AA18: 108.1 | AB18: 103.3 | AC18: 106.1 | AD18: 109.7
A19: Rural+Urban | B19: 2013 | C19: June | D19: 113.8 | E19: 114.9 | F19: 109.8 | G19: 107.9 | H19: 104.2 | I19: 110.7 | J19: 126.7 | K19: 106.3 | L19: 103.2 | M19: 105.7 | N19: 109 | O19: 111.6 | P19: 112.2 | Q19: 109.5 | R19: 109.5 | S19: 108.1 | T19: 109.3 | U19: 106.6 | V19: 108.3 | W19: 107.6 | X19: 106.4 | Y19: 105.1 | Z19: 105.4 | AA19: 107.4 | AB19: 102.8 | AC19: 105.8 | AD19: 109.3
A20: Rural | B20: 2013 | C20: July | D20: 113.4 | E20: 114.9 | F20: 110.5 | G20: 109.3 | H20: 106.2 | I20: 110.3 | J20: 129.2 | K20: 107.1 | L20: 104.3 | M20: 106.4 | N20: 109.1 | O20: 112.1 | P20: 113.1 | Q20: 109.8 | R20: 110.5 | S20: 109.5 | T20: 110.3 | U20: NA | V20: 109.5 | W20: 108.3 | X20: 106.9 | Y20: 106.8 | Z20: 106.4 | AA20: 107.8 | AB20: 102.5 | AC20: 106.5 | AD20: 110.7
A21: Urban | B21: 2013 | C21: July | D21: 117.8 | E21: 119.2 | F21: 114 | G21: 108.3 | H21: 101.1 | I21: 113.2 | J21: 160.9 | K21: 105.1 | L21: 101.3 | M21: 107.5 | N21: 110.4 | O21: 113.1 | P21: 117.5 | Q21: 111.7 | R21: 109.8 | S21: 107.8 | T21: 109.5 | U21: 107.7 | V21: 108.6 | W21: 108.1 | X21: 107.1 | Y21: 107.3 | Z21: 105.9 | AA21: 110.1 | AB21: 103.2 | AC21: 107.3 | AD21: 111.4
A22: Rural+Urban | B22: 2013 | C22: July | D22: 114.8 | E22: 116.4 | F22: 111.9 | G22: 108.9 | H22: 104.3 | I22: 111.7 | J22: 140 | K22: 106.4 | L22: 103.3 | M22: 106.8 | N22: 109.6 | O22: 112.6 | P22: 114.7 | Q22: 110.3 | R22: 110.2 | S22: 108.8 | T22: 110 | U22: 107.7 | V22: 109.2 | W22: 108.2 | X22: 107 | Y22: 107.1 | Z22: 106.1 | AA22: 109.1 | AB22: 102.8 | AC22: 106.9 | AD22: 111
A23: Rural | B23: 2013 | C23: August | D23: 114.3 | E23: 115.4 | F23: 111.1 | G23: 110 | H23: 106.4 | I23: 110.8 | J23: 138.9 | K23: 107.4 | L23: 104.1 | M23: 106.9 | N23: 109.7 | O23: 112.6 | P23: 114.9 | Q23: 110.7 | R23: 111.3 | S23: 110.2 | T23: 111.1 | U23: NA | V23: 109.9 | W23: 108.7 | X23: 107.5 | Y23: 107.8 | Z23: 106.8 | AA23: 108.7 | AB23: 105 | AC23: 107.5 | AD23: 112.1
A24: Urban | B24: 2013 | C24: August | D24: 118.3 | E24: 120.4 | F24: 112.7 | G24: 108.9 | H24: 101.1 | I24: 108.7 | J24: 177 | K24: 104.7 | L24: 101 | M24: 108.5 | N24: 110.9 | O24: 114.3 | P24: 119.6 | Q24: 112.4 | R24: 110.6 | S24: 108.3 | T24: 110.2 | U24: 108.9 | V24: 109.3 | W24: 108.7 | X24: 107.6 | Y24: 108.1 | Z24: 106.5 | AA24: 110.8 | AB24: 106 | AC24: 108.3 | AD24: 112.7
A25: Rural+Urban | B25: 2013 | C25: August | D25: 115.6 | E25: 117.2 | F25: 111.7 | G25: 109.6 | H25: 104.5 | I25: 109.8 | J25: 151.8 | K25: 106.5 | L25: 103.1 | M25: 107.4 | N25: 110.2 | O25: 113.4 | P25: 116.6 | Q25: 111.2 | R25: 111 | S25: 109.4 | T25: 110.7 | U25: 108.9 | V25: 109.7 | W25: 108.7 | X25: 107.5 | Y25: 108 | Z25: 106.6 | AA25: 109.9 | AB25: 105.4 | AC25: 107.9 | AD25: 112.4
A26: Rural | B26: 2013 | C26: September | D26: 115.4 | E26: 115.7 | F26: 111.7 | G26: 111 | H26: 107.4 | I26: 110.9 | J26: 154 | K26: 108.1 | L26: 104.2 | M26: 107.9 | N26: 110.4 | O26: 114 | P26: 117.8 | Q26: 111.7 | R26: 112.7 | S26: 111.4 | T26: 112.5 | U26: NA | V26: 111.1 | W26: 109.6 | X26: 108.3 | Y26: 109.3 | Z26: 107.7 | AA26: 109.8 | AB26: 106.7 | AC26: 108.7 | AD26: 114.2
A27: Urban | B27: 2013 | C27: September | D27: 118.6 | E27: 119.1 | F27: 113.2 | G27: 109.6 | H27: 101.7 | I27: 103.2 | J27: 174.3 | K27: 105.1 | L27: 100.8 | M27: 109.1 | N27: 111.1 | O27: 115.4 | P27: 119.2 | Q27: 112.9 | R27: 111.4 | S27: 109 | T27: 111.1 | U27: 109.7 | V27: 109.5 | W27: 109.6 | X27: 107.9 | Y27: 110.4 | Z27: 107.4 | AA27: 111.2 | AB27: 106.9 | AC27: 109.4 | AD27: 113.2
A28: Rural+Urban | B28: 2013 | C28: September | D28: 116.4 | E28: 116.9 | F28: 112.3 | G28: 110.5 | H28: 105.3 | I28: 107.3 | J28: 160.9 | K28: 107.1 | L28: 103.1 | M28: 108.3 | N28: 110.7 | O28: 114.6 | P28: 118.3 | Q28: 112 | R28: 112.2 | S28: 110.4 | T28: 111.9 | U28: 109.7 | V28: 110.5 | W28: 109.6 | X28: 108.1 | Y28: 109.9 | Z28: 107.5 | AA28: 110.6 | AB28: 106.8 | AC28: 109 | AD28: 113.7
A29: Rural | B29: 2013 | C29: October | D29: 116.3 | E29: 115.4 | F29: 112.6 | G29: 111.7 | H29: 107.7 | I29: 113.2 | J29: 164.9 | K29: 108.3 | L29: 103.9 | M29: 108.2 | N29: 111.1 | O29: 114.9 | P29: 119.8 | Q29: 112.2 | R29: 113.6 | S29: 112.3 | T29: 113.4 | U29: NA | V29: 111.6 | W29: 110.4 | X29: 108.9 | Y29: 109.3 | Z29: 108.3 | AA29: 110.2 | AB29: 107.5 | AC29: 109.1 | AD29: 115.5
A30: Urban | B30: 2013 | C30: October | D30: 118.9 | E30: 118.1 | F30: 114.5 | G30: 110.4 | H30: 102.3 | I30: 106.2 | J30: 183.5 | K30: 105.3 | L30: 100.2 | M30: 109.6 | N30: 111.4 | O30: 116 | P30: 120.8 | Q30: 113.5 | R30: 112.5 | S30: 109.7 | T30: 112 | U30: 110.5 | V30: 109.7 | W30: 110.2 | X30: 108.2 | Y30: 109.7 | Z30: 108 | AA30: 111.3 | AB30: 107.3 | AC30: 109.4 | AD30: 114
A31: Rural+Urban | B31: 2013 | C31: October | D31: 117.1 | E31: 116.3 | F31: 113.3 | G31: 111.2 | H31: 105.7 | I31: 109.9 | J31: 171.2 | K31: 107.3 | L31: 102.7 | M31: 108.7 | N31: 111.2 | O31: 115.4 | P31: 120.2 | Q31: 112.5 | R31: 113.2 | S31: 111.2 | T31: 112.8 | U31: 110.5 | V31: 110.9 | W31: 110.3 | X31: 108.6 | Y31: 109.5 | Z31: 108.1 | AA31: 110.8 | AB31: 107.4 | AC31: 109.2 | AD31: 114.8
A32: Rural | B32: 2013 | C32: November | D32: 117.3 | E32: 114.9 | F32: 116.2 | G32: 112.8 | H32: 108.9 | I32: 116.6 | J32: 178.1 | K32: 109.1 | L32: 103.6 | M32: 109 | N32: 111.8 | O32: 116 | P32: 122.5 | Q32: 112.8 | R32: 114.6 | S32: 113.1 | T32: 114.4 | U32: NA | V32: 112.6 | W32: 111.3 | X32: 109.7 | Y32: 109.6 | Z32: 108.7 | AA32: 111 | AB32: 108.2 | AC32: 109.8 | AD32: 117.4
A33: Urban | B33: 2013 | C33: November | D33: 119.8 | E33: 116.3 | F33: 122.6 | G33: 112 | H33: 103.2 | I33: 110 | J33: 192.8 | K33: 106.3 | L33: 99.5 | M33: 110.3 | N33: 111.8 | O33: 117.1 | P33: 122.9 | Q33: 114.1 | R33: 113.5 | S33: 110.3 | T33: 113 | U33: 111.1 | V33: 110 | W33: 110.9 | X33: 108.6 | Y33: 109.5 | Z33: 108.5 | AA33: 111.3 | AB33: 107.9 | AC33: 109.6 | AD33: 115
A34: Rural+Urban | B34: 2013 | C34: November | D34: 118.1 | E34: 115.4 | F34: 118.7 | G34: 112.5 | H34: 106.8 | I34: 113.5 | J34: 183.1 | K34: 108.2 | L34: 102.2 | M34: 109.4 | N34: 111.8 | O34: 116.5 | P34: 122.6 | Q34: 113.1 | R34: 114.2 | S34: 111.9 | T34: 113.8 | U34: 111.1 | V34: 111.6 | W34: 111.1 | X34: 109.3 | Y34: 109.5 | Z34: 108.6 | AA34: 111.2 | AB34: 108.1 | AC34: 109.7 | AD34: 116.3
A35: Rural | B35: 2013 | C35: December | D35: 118.4 | E35: 115.9 | F35: 120.4 | G35: 113.8 | H35: 109.5 | I35: 115.5 | J35: 145.7 | K35: 109.5 | L35: 102.9 | M35: 109.8 | N35: 112.1 | O35: 116.8 | P35: 118.7 | Q35: 113.6 | R35: 115.8 | S35: 114 | T35: 115.5 | U35: NA | V35: 112.8 | W35: 112.1 | X35: 110.1 | Y35: 109.9 | Z35: 109.2 | AA35: 111.6 | AB35: 108.1 | AC35: 110.1 | AD35: 115.5
A36: Urban | B36: 2013 | C36: December | D36: 120.5 | E36: 118.1 | F36: 128.5 | G36: 112.8 | H36: 103.4 | I36: 110.7 | J36: 144.8 | K36: 107.1 | L36: 98.6 | M36: 111.9 | N36: 112.1 | O36: 118.1 | P36: 117.8 | Q36: 115 | R36: 114.2 | S36: 110.9 | T36: 113.7 | U36: 110.7 | V36: 110.4 | W36: 111.3 | X36: 109 | Y36: 109.7 | Z36: 108.9 | AA36: 111.4 | AB36: 107.7 | AC36: 109.8 | AD36: 113.3
A37: Rural+Urban | B37: 2013 | C37: December | D37: 119.1 | E37: 116.7 | F37: 123.5 | G37: 113.4 | H37: 107.3 | I37: 113.3 | J37: 145.4 | K37: 108.7 | L37: 101.5 | M37: 110.5 | N37: 112.1 | O37: 117.4 | P37: 118.4 | Q37: 114 | R37: 115.2 | S37: 112.7 | T37: 114.8 | U37: 110.7 | V37: 111.9 | W37: 111.7 | X37: 109.7 | Y37: 109.8 | Z37: 109 | AA37: 111.5 | AB37: 107.9 | AC37: 110 | AD37: 114.5
A38: Rural | B38: 2014 | C38: January | D38: 118.9 | E38: 117.1 | F38: 120.5 | G38: 114.4 | H38: 109 | I38: 115.5 | J38: 123.9 | K38: 109.6 | L38: 101.8 | M38: 110.2 | N38: 112.4 | O38: 117.3 | P38: 116 | Q38: 114 | R38: 116.5 | S38: 114.5 | T38: 116.2 | U38: NA | V38: 113 | W38: 112.6 | X38: 110.6 | Y38: 110.5 | Z38: 109.6 | AA38: 111.8 | AB38: 108.3 | AC38: 110.6 | AD38: 114.2
A39: Urban | B39: 2014 | C39: January | D39: 121.2 | E39: 122 | F39: 129.9 | G39: 113.6 | H39: 102.9 | I39: 112.1 | J39: 118.9 | K39: 107.5 | L39: 96.9 | M39: 112.7 | N39: 112.1 | O39: 119 | P39: 115.5 | Q39: 115.7 | R39: 114.8 | S39: 111.3 | T39: 114.3 | U39: 111.6 | V39: 111 | W39: 111.9 | X39: 109.7 | Y39: 110.8 | Z39: 109.8 | AA39: 111.5 | AB39: 108 | AC39: 110.5 | AD39: 112.9
A40: Rural+Urban | B40: 2014 | C40: January | D40: 119.6 | E40: 118.8 | F40: 124.1 | G40: 114.1 | H40: 106.8 | I40: 113.9 | J40: 122.2 | K40: 108.9 | L40: 100.2 | M40: 111 | N40: 112.3 | O40: 118.1 | P40: 115.8 | Q40: 114.5 | R40: 115.8 | S40: 113.2 | T40: 115.4 | U40: 111.6 | V40: 112.2 | W40: 112.3 | X40: 110.3 | Y40: 110.7 | Z40: 109.7 | AA40: 111.6 | AB40: 108.2 | AC40: 110.6 | AD40: 113.6
A41: Rural | B41: 2014 | C41: February | D41: 119.4 | E41: 117.7 | F41: 121.2 | G41: 115 | H41: 109 | I41: 116.6 | J41: 116 | K41: 109.8 | L41: 101.1 | M41: 110.4 | N41: 112.9 | O41: 117.8 | P41: 115.3 | Q41: 114.2 | R41: 117.1 | S41: 114.5 | T41: 116.7 | U41: NA | V41: 113.2 | W41: 112.9 | X41: 110.9 | Y41: 110.8 | Z41: 109.9 | AA41: 112 | AB41: 108.7 | AC41: 110.9 | AD41: 114
A42: Urban | B42: 2014 | C42: February | D42: 121.9 | E42: 122 | F42: 124.5 | G42: 115.2 | H42: 102.5 | I42: 114.1 | J42: 111.5 | K42: 108.2 | L42: 95.4 | M42: 113.5 | N42: 112.1 | O42: 119.9 | P42: 115.2 | Q42: 116.2 | R42: 115.3 | S42: 111.7 | T42: 114.7 | U42: 112.5 | V42: 111.1 | W42: 112.6 | X42: 110.4 | Y42: 111.3 | Z42: 110.3 | AA42: 111.6 | AB42: 108.7 | AC42: 111 | AD42: 113.1
A43: Rural+Urban | B43: 2014 | C43: February | D43: 120.2 | E43: 119.2 | F43: 122.5 | G43: 115.1 | H43: 106.6 | I43: 115.4 | J43: 114.5 | K43: 109.3 | L43: 99.2 | M43: 111.4 | N43: 112.6 | O43: 118.8 | P43: 115.3 | Q43: 114.7 | R43: 116.4 | S43: 113.3 | T43: 115.9 | U43: 112.5 | V43: 112.4 | W43: 112.8 | X43: 110.7 | Y43: 111.1 | Z43: 110.1 | AA43: 111.8 | AB43: 108.7 | AC43: 110.9 | AD43: 113.6
A44: Rural | B44: 2014 | C44: March | D44: 120.1 | E44: 118.1 | F44: 120.7 | G44: 116.1 | H44: 109.3 | I44: 119.6 | J44: 117.9 | K44: 110.2 | L44: 101.2 | M44: 110.7 | N44: 113 | O44: 118.3 | P44: 116.2 | Q44: 114.6 | R44: 117.5 | S44: 114.9 | T44: 117.2 | U44: NA | V44: 113.4 | W44: 113.4 | X44: 111.4 | Y44: 111.2 | Z44: 110.2 | AA44: 112.4 | AB44: 108.9 | AC44: 111.3 | AD44: 114.6
A45: Urban | B45: 2014 | C45: March | D45: 122.1 | E45: 121.4 | F45: 121.5 | G45: 116.2 | H45: 102.8 | I45: 117.7 | J45: 113.3 | K45: 108.9 | L45: 96.3 | M45: 114.1 | N45: 112.2 | O45: 120.5 | P45: 116 | Q45: 116.7 | R45: 115.8 | S45: 112.1 | T45: 115.2 | U45: 113.2 | V45: 110.9 | W45: 113 | X45: 110.8 | Y45: 111.6 | Z45: 110.9 | AA45: 111.8 | AB45: 109.2 | AC45: 111.4 | AD45: 113.7
A46: Rural+Urban | B46: 2014 | C46: Marcrh | D46: 120.7 | E46: 119.3 | F46: 121 | G46: 116.1 | H46: 106.9 | I46: 118.7 | J46: 116.3 | K46: 109.8 | L46: 99.6 | M46: 111.8 | N46: 112.7 | O46: 119.3 | P46: 116.1 | Q46: 115.2 | R46: 116.8 | S46: 113.7 | T46: 116.4 | U46: 113.2 | V46: 112.5 | W46: 113.2 | X46: 111.2 | Y46: 111.4 | Z46: 110.6 | AA46: 112 | AB46: 109 | AC46: 111.3 | AD46: 114.2
A47: Rural | B47: 2014 | C47: April | D47: 120.2 | E47: 118.9 | F47: 118.1 | G47: 117 | H47: 109.7 | I47: 125.5 | J47: 120.5 | K47: 111 | L47: 102.6 | M47: 111.2 | N47: 113.5 | O47: 118.7 | P47: 117.2 | Q47: 115.4 | R47: 118.1 | S47: 116.1 | T47: 117.8 | U47: NA | V47: 113.4 | W47: 113.7 | X47: 111.8 | Y47: 111.2 | Z47: 110.5 | AA47: 113 | AB47: 108.9 | AC47: 111.5 | AD47: 115.4
A48: Urban | B48: 2014 | C48: April | D48: 122.5 | E48: 121.7 | F48: 113.3 | G48: 117 | H48: 103.1 | I48: 126.7 | J48: 121.2 | K48: 111 | L48: 100.3 | M48: 115.3 | N48: 112.7 | O48: 121 | P48: 118.2 | Q48: 117.6 | R48: 116.3 | S48: 112.5 | T48: 115.7 | U48: 113.9 | V48: 110.9 | W48: 113.4 | X48: 111 | Y48: 111.2 | Z48: 111.2 | AA48: 112.5 | AB48: 109.1 | AC48: 111.4 | AD48: 114.7
A49: Rural+Urban | B49: 2014 | C49: April | D49: 120.9 | E49: 119.9 | F49: 116.2 | G49: 117 | H49: 107.3 | I49: 126.1 | J49: 120.7 | K49: 111 | L49: 101.8 | M49: 112.6 | N49: 113.2 | O49: 119.8 | P49: 117.6 | Q49: 116 | R49: 117.4 | S49: 114.6 | T49: 117 | U49: 113.9 | V49: 112.5 | W49: 113.6 | X49: 111.5 | Y49: 111.2 | Z49: 110.9 | AA49: 112.7 | AB49: 109 | AC49: 111.5 | AD49: 115.1
A50: Rural | B50: 2014 | C50: May | D50: 120.3 | E50: 120.2 | F50: 116.9 | G50: 118 | H50: 110.1 | I50: 126.3 | J50: 123.9 | K50: 111.5 | L50: 103.5 | M50: 111.6 | N50: 114.2 | O50: 119.2 | P50: 118.2 | Q50: 116.3 | R50: 118.7 | S50: 116.8 | T50: 118.5 | U50: NA | V50: 113.4 | W50: 114.1 | X50: 112.1 | Y50: 111.4 | Z50: 110.9 | AA50: 113.1 | AB50: 108.9 | AC50: 111.8 | AD50: 116
A51: Urban | B51: 2014 | C51: May | D51: 122.7 | E51: 124.1 | F51: 114.2 | G51: 119.1 | H51: 103.5 | I51: 129.2 | J51: 127 | K51: 112.6 | L51: 101.3 | M51: 117 | N51: 112.9 | O51: 121.7 | P51: 120 | Q51: 118.3 | R51: 116.8 | S51: 112.9 | T51: 116.2 | U51: 114.3 | V51: 111.1 | W51: 114.1 | X51: 111.2 | Y51: 111.3 | Z51: 111.5 | AA51: 112.9 | AB51: 109.3 | AC51: 111.7 | AD51: 115.6
A52: Rural+Urban | B52: 2014 | C52: May | D52: 121.1 | E52: 121.6 | F52: 115.9 | G52: 118.4 | H52: 107.7 | I52: 127.7 | J52: 125 | K52: 111.9 | L52: 102.8 | M52: 113.4 | N52: 113.7 | O52: 120.4 | P52: 118.9 | Q52: 116.8 | R52: 118 | S52: 115.2 | T52: 117.6 | U52: 114.3 | V52: 112.5 | W52: 114.1 | X52: 111.8 | Y52: 111.3 | Z52: 111.2 | AA52: 113 | AB52: 109.1 | AC52: 111.8 | AD52: 115.8
A53: Rural | B53: 2014 | C53: June | D53: 120.7 | E53: 121.6 | F53: 116.1 | G53: 119.3 | H53: 110.3 | I53: 125.8 | J53: 129.3 | K53: 112.2 | L53: 103.6 | M53: 112.3 | N53: 114.9 | O53: 120.1 | P53: 119.5 | Q53: 117.3 | R53: 119.7 | S53: 117.3 | T53: 119.3 | U53: NA | V53: 114.4 | W53: 114.9 | X53: 112.8 | Y53: 112.2 | Z53: 111.4 | AA53: 114.3 | AB53: 108 | AC53: 112.3 | AD53: 117
A54: Urban | B54: 2014 | C54: June | D54: 123.1 | E54: 125.9 | F54: 115.4 | G54: 120.4 | H54: 103.4 | I54: 131.2 | J54: 137.5 | K54: 112.8 | L54: 101.4 | M54: 118.3 | N54: 113.2 | O54: 122.4 | P54: 122 | Q54: 119 | R54: 117.4 | S54: 113.2 | T54: 116.7 | U54: 113.9 | V54: 111.2 | W54: 114.3 | X54: 111.4 | Y54: 111.5 | Z54: 111.8 | AA54: 115.1 | AB54: 108.7 | AC54: 112.2 | AD54: 116.4
A55: Rural+Urban | B55: 2014 | C55: June | D55: 121.5 | E55: 123.1 | F55: 115.8 | G55: 119.7 | H55: 107.8 | I55: 128.3 | J55: 132.1 | K55: 112.4 | L55: 102.9 | M55: 114.3 | N55: 114.2 | O55: 121.2 | P55: 120.4 | Q55: 117.8 | R55: 118.8 | S55: 115.6 | T55: 118.3 | U55: 113.9 | V55: 113.2 | W55: 114.6 | X55: 112.3 | Y55: 111.8 | Z55: 111.6 | AA55: 114.8 | AB55: 108.3 | AC55: 112.3 | AD55: 116.7
A56: Rural | B56: 2014 | C56: July | D56: 121.7 | E56: 122.5 | F56: 117.7 | G56: 120.6 | H56: 110.4 | I56: 129.1 | J56: 150.1 | K56: 113.2 | L56: 104.8 | M56: 113.3 | N56: 115.6 | O56: 120.9 | P56: 123.3 | Q56: 118 | R56: 120.7 | S56: 118.3 | T56: 120.3 | U56: NA | V56: 115.3 | W56: 115.4 | X56: 113.4 | Y56: 113.2 | Z56: 111.8 | AA56: 115.5 | AB56: 108.8 | AC56: 113.1 | AD56: 119.5
A57: Urban | B57: 2014 | C57: July | D57: 123.8 | E57: 126.4 | F57: 118 | G57: 121.6 | H57: 103.5 | I57: 133.7 | J57: 172.4 | K57: 113.1 | L57: 102.7 | M57: 120 | N57: 113.8 | O57: 123.4 | P57: 127.1 | Q57: 121 | R57: 118 | S57: 113.6 | T57: 117.4 | U57: 114.8 | V57: 111.6 | W57: 114.9 | X57: 111.5 | Y57: 113 | Z57: 112.4 | AA57: 117.8 | AB57: 109.7 | AC57: 113.5 | AD57: 118.9
A58: Rural+Urban | B58: 2014 | C58: July | D58: 122.4 | E58: 123.9 | F58: 117.8 | G58: 121 | H58: 107.9 | I58: 131.2 | J58: 157.7 | K58: 113.2 | L58: 104.1 | M58: 115.5 | N58: 114.8 | O58: 122.1 | P58: 124.7 | Q58: 118.8 | R58: 119.6 | S58: 116.3 | T58: 119.1 | U58: 114.8 | V58: 113.9 | W58: 115.2 | X58: 112.7 | Y58: 113.1 | Z58: 112.1 | AA58: 116.8 | AB58: 109.2 | AC58: 113.3 | AD58: 119.2
A59: Rural | B59: 2014 | C59: August | D59: 121.8 | E59: 122.8 | F59: 117.8 | G59: 121.9 | H59: 110.6 | I59: 129.7 | J59: 161.1 | K59: 114.1 | L59: 105.1 | M59: 114.6 | N59: 115.8 | O59: 121.7 | P59: 125.3 | Q59: 118.8 | R59: 120.9 | S59: 118.8 | T59: 120.7 | U59: NA | V59: 115.4 | W59: 115.9 | X59: 114 | Y59: 113.2 | Z59: 112.2 | AA59: 116.2 | AB59: 109.4 | AC59: 113.5 | AD59: 120.7
A60: Urban | B60: 2014 | C60: August | D60: 124.8 | E60: 127.3 | F60: 116.5 | G60: 122.2 | H60: 103.6 | I60: 132.7 | J60: 181.9 | K60: 115.2 | L60: 102.7 | M60: 122.1 | N60: 114.4 | O60: 124.7 | P60: 128.9 | Q60: 123 | R60: 118.6 | S60: 114.1 | T60: 117.9 | U60: 115.5 | V60: 111.8 | W60: 115.3 | X60: 112.2 | Y60: 112.5 | Z60: 112.9 | AA60: 119.2 | AB60: 110.5 | AC60: 113.9 | AD60: 119.9
A61: Rural+Urban | B61: 2014 | C61: August | D61: 122.7 | E61: 124.4 | F61: 117.3 | G61: 122 | H61: 108 | I61: 131.1 | J61: 168.2 | K61: 114.5 | L61: 104.3 | M61: 117.1 | N61: 115.2 | O61: 123.1 | P61: 126.6 | Q61: 119.9 | R61: 120 | S61: 116.8 | T61: 119.6 | U61: 115.5 | V61: 114 | W61: 115.6 | X61: 113.3 | Y61: 112.8 | Z61: 112.6 | AA61: 118 | AB61: 109.9 | AC61: 113.7 | AD61: 120.3
A62: Rural | B62: 2014 | C62: September | D62: 122.3 | E62: 122.4 | F62: 117.8 | G62: 122.7 | H62: 110.4 | I62: 129.8 | J62: 158.8 | K62: 115 | L62: 104.7 | M62: 114.9 | N62: 116.5 | O62: 122.6 | P62: 125.3 | Q62: 119.5 | R62: 121.7 | S62: 119.2 | T62: 121.3 | U62: NA | V62: 115.8 | W62: 116.7 | X62: 114.5 | Y62: 112.8 | Z62: 112.6 | AA62: 116.6 | AB62: 109.1 | AC62: 113.7 | AD62: 120.9
A63: Urban | B63: 2014 | C63: September | D63: 124.2 | E63: 125.4 | F63: 116.4 | G63: 122.7 | H63: 103.5 | I63: 124.5 | J63: 168.6 | K63: 116.9 | L63: 101.9 | M63: 122.9 | N63: 114.8 | O63: 125.2 | P63: 126.7 | Q63: 124.3 | R63: 119.2 | S63: 114.5 | T63: 118.4 | U63: 116.1 | V63: 111.8 | W63: 115.5 | X63: 112.3 | Y63: 111.2 | Z63: 113.4 | AA63: 120 | AB63: 110 | AC63: 113.6 | AD63: 119.2
A64: Rural+Urban | B64: 2014 | C64: September | D64: 122.9 | E64: 123.5 | F64: 117.3 | G64: 122.7 | H64: 107.9 | I64: 127.3 | J64: 162.1 | K64: 115.6 | L64: 103.8 | M64: 117.6 | N64: 115.8 | O64: 123.8 | P64: 125.8 | Q64: 120.8 | R64: 120.7 | S64: 117.2 | T64: 120.1 | U64: 116.1 | V64: 114.3 | W64: 116.1 | X64: 113.7 | Y64: 112 | Z64: 113.1 | AA64: 118.6 | AB64: 109.5 | AC64: 113.7 | AD64: 120.1
A65: Rural | B65: 2014 | C65: October | D65: 122.6 | E65: 122.5 | F65: 118.3 | G65: 123.2 | H65: 110.5 | I65: 128.9 | J65: 155.3 | K65: 115.5 | L65: 104 | M65: 115.3 | N65: 116.8 | O65: 123.2 | P65: 125.1 | Q65: 120 | R65: 122.7 | S65: 120.3 | T65: 122.3 | U65: NA | V65: 116.4 | W65: 117.5 | X65: 115.3 | Y65: 112.6 | Z65: 113 | AA65: 116.9 | AB65: 109.3 | AC65: 114 | AD65: 121
A66: Urban | B66: 2014 | C66: October | D66: 124.6 | E66: 126.1 | F66: 117.8 | G66: 123.1 | H66: 103.5 | I66: 123.5 | J66: 159.6 | K66: 117.4 | L66: 101.2 | M66: 123.8 | N66: 115.2 | O66: 125.9 | P66: 125.8 | Q66: 124.3 | R66: 119.6 | S66: 114.9 | T66: 118.9 | U66: 116.7 | V66: 112 | W66: 115.8 | X66: 112.6 | Y66: 111 | Z66: 113.6 | AA66: 120.2 | AB66: 110.1 | AC66: 113.7 | AD66: 119.1
A67: Rural+Urban | B67: 2014 | C67: October | D67: 123.2 | E67: 123.8 | F67: 118.1 | G67: 123.2 | H67: 107.9 | I67: 126.4 | J67: 156.8 | K67: 116.1 | L67: 103.1 | M67: 118.1 | N67: 116.1 | O67: 124.5 | P67: 125.4 | Q67: 121.1 | R67: 121.5 | S67: 118.1 | T67: 121 | U67: 116.7 | V67: 114.7 | W67: 116.7 | X67: 114.3 | Y67: 111.8 | Z67: 113.3 | AA67: 118.8 | AB67: 109.6 | AC67: 113.9 | AD67: 120.1
A68: Rural | B68: 2014 | C68: November | D68: 122.7 | E68: 122.6 | F68: 119.9 | G68: 124 | H68: 110.5 | I68: 128.8 | J68: 152 | K68: 116.2 | L68: 103.3 | M68: 115.8 | N68: 116.8 | O68: 124.5 | P68: 124.9 | Q68: 120.8 | R68: 123.3 | S68: 120.5 | T68: 122.9 | U68: NA | V68: 117.3 | W68: 118.1 | X68: 115.9 | Y68: 112 | Z68: 113.3 | AA68: 117.2 | AB68: 108.8 | AC68: 114.1 | AD68: 121.1
A69: Urban | B69: 2014 | C69: November | D69: 124.5 | E69: 125.6 | F69: 122.7 | G69: 124.6 | H69: 103.2 | I69: 122.2 | J69: 153.2 | K69: 119.3 | L69: 99.8 | M69: 124.6 | N69: 115.8 | O69: 126.9 | P69: 125.4 | Q69: 125.8 | R69: 120.3 | S69: 115.4 | T69: 119.5 | U69: 117.1 | V69: 112.6 | W69: 116.4 | X69: 113 | Y69: 109.7 | Z69: 114 | AA69: 120.3 | AB69: 109.6 | AC69: 113.4 | AD69: 119
A70: Rural+Urban | B70: 2014 | C70: November | D70: 123.3 | E70: 123.7 | F70: 121 | G70: 124.2 | H70: 107.8 | I70: 125.7 | J70: 152.4 | K70: 117.2 | L70: 102.1 | M70: 118.7 | N70: 116.4 | O70: 125.6 | P70: 125.1 | Q70: 122.1 | R70: 122.1 | S70: 118.4 | T70: 121.6 | U70: 117.1 | V70: 115.5 | W70: 117.3 | X70: 114.8 | Y70: 110.8 | Z70: 113.7 | AA70: 119 | AB70: 109.1 | AC70: 113.8 | AD70: 120.1
A71: Rural | B71: 2014 | C71: December | D71: 122.4 | E71: 122.4 | F71: 121.8 | G71: 124.2 | H71: 110.2 | I71: 128.6 | J71: 140.3 | K71: 116.3 | L71: 102 | M71: 116 | N71: 117.3 | O71: 124.8 | P71: 123.3 | Q71: 121.7 | R71: 123.8 | S71: 120.6 | T71: 123.3 | U71: NA | V71: 117.4 | W71: 118.2 | X71: 116.2 | Y71: 111.5 | Z71: 113.3 | AA71: 117.7 | AB71: 109.4 | AC71: 114.2 | AD71: 120.3
A72: Urban | B72: 2014 | C72: December | D72: 124 | E72: 124.7 | F72: 126.3 | G72: 124.9 | H72: 103 | I72: 122.3 | J72: 141 | K72: 120.1 | L72: 97.8 | M72: 125.4 | N72: 116.1 | O72: 127.6 | P72: 124 | Q72: 126.4 | R72: 120.7 | S72: 115.8 | T72: 120 | U72: 116.5 | V72: 113 | W72: 116.8 | X72: 113.2 | Y72: 108.8 | Z72: 114.3 | AA72: 120.7 | AB72: 110.4 | AC72: 113.4 | AD72: 118.4
A73: Rural+Urban | B73: 2014 | C73: December | D73: 122.9 | E73: 123.2 | F73: 123.5 | G73: 124.5 | H73: 107.6 | I73: 125.7 | J73: 140.5 | K73: 117.6 | L73: 100.6 | M73: 119.1 | N73: 116.8 | O73: 126.1 | P73: 123.6 | Q73: 123 | R73: 122.6 | S73: 118.6 | T73: 122 | U73: 116.5 | V73: 115.7 | W73: 117.5 | X73: 115.1 | Y73: 110.1 | Z73: 113.9 | AA73: 119.5 | AB73: 109.8 | AC73: 113.8 | AD73: 119.4
A74: Rural | B74: 2015 | C74: January | D74: 123.1 | E74: 123.1 | F74: 122.1 | G74: 124.9 | H74: 111 | I74: 130.4 | J74: 132.3 | K74: 117.2 | L74: 100.5 | M74: 117.2 | N74: 117.9 | O74: 125.6 | P74: 122.8 | Q74: 122.7 | R74: 124.4 | S74: 121.6 | T74: 124 | U74: NA | V74: 118.4 | W74: 118.9 | X74: 116.6 | Y74: 111 | Z74: 114 | AA74: 118.2 | AB74: 110.2 | AC74: 114.5 | AD74: 120.3
A75: Urban | B75: 2015 | C75: January | D75: 124 | E75: 125.5 | F75: 126.6 | G75: 125.2 | H75: 104.3 | I75: 121.3 | J75: 134.4 | K75: 122.9 | L75: 96.1 | M75: 126.6 | N75: 116.5 | O75: 128 | P75: 123.5 | Q75: 127.4 | R75: 121 | S75: 116.1 | T75: 120.2 | U75: 117.3 | V75: 113.4 | W75: 117.2 | X75: 113.7 | Y75: 107.9 | Z75: 114.6 | AA75: 120.8 | AB75: 111.4 | AC75: 113.4 | AD75: 118.5
A76: Rural+Urban | B76: 2015 | C76: January | D76: 123.4 | E76: 123.9 | F76: 123.8 | G76: 125 | H76: 108.5 | I76: 126.2 | J76: 133 | K76: 119.1 | L76: 99 | M76: 120.3 | N76: 117.3 | O76: 126.7 | P76: 123.1 | Q76: 124 | R76: 123.1 | S76: 119.3 | T76: 122.5 | U76: 117.3 | V76: 116.5 | W76: 118.1 | X76: 115.5 | Y76: 109.4 | Z76: 114.3 | AA76: 119.7 | AB76: 110.7 | AC76: 114 | AD76: 119.5
A77: Rural | B77: 2015 | C77: February | D77: 123.4 | E77: 124.4 | F77: 122.1 | G77: 125.8 | H77: 111.5 | I77: 129.4 | J77: 128.2 | K77: 118.8 | L77: 100 | M77: 118.6 | N77: 118.8 | O77: 126.8 | P77: 122.8 | Q77: 124.2 | R77: 125.4 | S77: 122.7 | T77: 125 | U77: NA | V77: 120 | W77: 119.6 | X77: 117.7 | Y77: 110.9 | Z77: 114.8 | AA77: 118.7 | AB77: 110.8 | AC77: 115 | AD77: 120.6
A78: Urban | B78: 2015 | C78: February | D78: 124.3 | E78: 126.5 | F78: 119.5 | G78: 125.6 | H78: 104.9 | I78: 121.6 | J78: 131.8 | K78: 125.1 | L78: 95 | M78: 127.7 | N78: 116.8 | O78: 128.6 | P78: 123.7 | Q78: 128.1 | R78: 121.3 | S78: 116.5 | T78: 120.6 | U78: 118.1 | V78: 114 | W78: 117.7 | X78: 114.1 | Y78: 106.8 | Z78: 114.9 | AA78: 120.4 | AB78: 111.7 | AC78: 113.2 | AD78: 118.7
A79: Rural+Urban | B79: 2015 | C79: February | D79: 123.7 | E79: 125.1 | F79: 121.1 | G79: 125.7 | H79: 109.1 | I79: 125.8 | J79: 129.4 | K79: 120.9 | L79: 98.3 | M79: 121.6 | N79: 118 | O79: 127.6 | P79: 123.1 | Q79: 125.2 | R79: 123.8 | S79: 120.1 | T79: 123.3 | U79: 118.1 | V79: 117.7 | W79: 118.7 | X79: 116.3 | Y79: 108.7 | Z79: 114.9 | AA79: 119.7 | AB79: 111.2 | AC79: 114.1 | AD79: 119.7
A80: Rural | B80: 2015 | C80: March | D80: 123.3 | E80: 124.7 | F80: 118.9 | G80: 126 | H80: 111.8 | I80: 130.9 | J80: 128 | K80: 119.9 | L80: 98.9 | M80: 119.4 | N80: 118.9 | O80: 127.7 | P80: 123.1 | Q80: 124.7 | R80: 126 | S80: 122.9 | T80: 125.5 | U80: NA | V80: 120.6 | W80: 120.2 | X80: 118.2 | Y80: 111.6 | Z80: 115.5 | AA80: 119.4 | AB80: 110.8 | AC80: 115.5 | AD80: 121.1
A81: Urban | B81: 2015 | C81: March | D81: 124 | E81: 126.7 | F81: 113.5 | G81: 125.9 | H81: 104.8 | I81: 123.8 | J81: 131.4 | K81: 127.2 | L81: 93.2 | M81: 127.4 | N81: 117 | O81: 129.2 | P81: 123.9 | Q81: 128.8 | R81: 121.7 | S81: 116.9 | T81: 120.9 | U81: 118.6 | V81: 114.4 | W81: 118 | X81: 114.3 | Y81: 108.4 | Z81: 115.4 | AA81: 120.6 | AB81: 111.3 | AC81: 113.8 | AD81: 119.1
A82: Rural+Urban | B82: 2015 | C82: March | D82: 123.5 | E82: 125.4 | F82: 116.8 | G82: 126 | H82: 109.2 | I82: 127.6 | J82: 129.2 | K82: 122.4 | L82: 97 | M82: 122.1 | N82: 118.1 | O82: 128.4 | P82: 123.4 | Q82: 125.8 | R82: 124.3 | S82: 120.4 | T82: 123.7 | U82: 118.6 | V82: 118.3 | W82: 119.2 | X82: 116.7 | Y82: 109.9 | Z82: 115.4 | AA82: 120.1 | AB82: 111 | AC82: 114.7 | AD82: 120.2
A83: Rural | B83: 2015 | C83: April | D83: 123.3 | E83: 125.5 | F83: 117.2 | G83: 126.8 | H83: 111.9 | I83: 134.2 | J83: 127.5 | K83: 121.5 | L83: 97.8 | M83: 119.8 | N83: 119.4 | O83: 128.7 | P83: 123.6 | Q83: 125.7 | R83: 126.4 | S83: 123.3 | T83: 126 | U83: NA | V83: 121.2 | W83: 120.9 | X83: 118.6 | Y83: 111.9 | Z83: 116.2 | AA83: 119.9 | AB83: 111.6 | AC83: 116 | AD83: 121.5
A84: Urban | B84: 2015 | C84: April | D84: 123.8 | E84: 128.2 | F84: 110 | G84: 126.3 | H84: 104.5 | I84: 130.6 | J84: 130.8 | K84: 131.3 | L84: 91.6 | M84: 127.7 | N84: 117.2 | O84: 129.5 | P84: 124.6 | Q84: 130.1 | R84: 122.1 | S84: 117.2 | T84: 121.3 | U84: 119.2 | V84: 114.7 | W84: 118.4 | X84: 114.6 | Y84: 108.4 | Z84: 115.6 | AA84: 121.7 | AB84: 111.8 | AC84: 114.2 | AD84: 119.7
A85: Rural+Urban | B85: 2015 | C85: April | D85: 123.5 | E85: 126.4 | F85: 114.4 | G85: 126.6 | H85: 109.2 | I85: 132.5 | J85: 128.6 | K85: 124.8 | L85: 95.7 | M85: 122.4 | N85: 118.5 | O85: 129.1 | P85: 124 | Q85: 126.9 | R85: 124.7 | S85: 120.8 | T85: 124.1 | U85: 119.2 | V85: 118.7 | W85: 119.7 | X85: 117.1 | Y85: 110.1 | Z85: 115.9 | AA85: 121 | AB85: 111.7 | AC85: 115.1 | AD85: 120.7
A86: Rural | B86: 2015 | C86: May | D86: 123.5 | E86: 127.1 | F86: 117.3 | G86: 127.7 | H86: 112.5 | I86: 134.1 | J86: 128.5 | K86: 124.3 | L86: 97.6 | M86: 120.7 | N86: 120.2 | O86: 129.8 | P86: 124.4 | Q86: 126.7 | R86: 127.3 | S86: 124.1 | T86: 126.8 | U86: NA | V86: 121.9 | W86: 121.5 | X86: 119.4 | Y86: 113.3 | Z86: 116.7 | AA86: 120.5 | AB86: 112.3 | AC86: 116.9 | AD86: 122.4
A87: Urban | B87: 2015 | C87: May | D87: 123.8 | E87: 129.7 | F87: 111.3 | G87: 126.6 | H87: 105.2 | I87: 130.8 | J87: 135.6 | K87: 142.6 | L87: 90.8 | M87: 128.8 | N87: 117.7 | O87: 129.9 | P87: 126.1 | Q87: 131.3 | R87: 122.4 | S87: 117.4 | T87: 121.6 | U87: 119.6 | V87: 114.9 | W87: 118.7 | X87: 114.9 | Y87: 110.8 | Z87: 116 | AA87: 122 | AB87: 112.4 | AC87: 115.2 | AD87: 120.7
A88: Rural+Urban | B88: 2015 | C88: May | D88: 123.6 | E88: 128 | F88: 115 | G88: 127.3 | H88: 109.8 | I88: 132.6 | J88: 130.9 | K88: 130.5 | L88: 95.3 | M88: 123.4 | N88: 119.2 | O88: 129.8 | P88: 125 | Q88: 127.9 | R88: 125.4 | S88: 121.3 | T88: 124.7 | U88: 119.6 | V88: 119.2 | W88: 120.2 | X88: 117.7 | Y88: 112 | Z88: 116.3 | AA88: 121.4 | AB88: 112.3 | AC88: 116.1 | AD88: 121.6
A89: Rural | B89: 2015 | C89: June | D89: 124.1 | E89: 130.4 | F89: 122.1 | G89: 128.7 | H89: 114.1 | I89: 133.2 | J89: 135.2 | K89: 131.9 | L89: 96.3 | M89: 123 | N89: 121.1 | O89: 131.2 | P89: 126.6 | Q89: 128.2 | R89: 128.4 | S89: 125.1 | T89: 128 | U89: NA | V89: 122.6 | W89: 122.8 | X89: 120.4 | Y89: 114.2 | Z89: 117.9 | AA89: 122 | AB89: 113 | AC89: 117.9 | AD89: 124.1
A90: Urban | B90: 2015 | C90: June | D90: 123.6 | E90: 134.4 | F90: 120.9 | G90: 127.3 | H90: 106 | I90: 132.3 | J90: 146.7 | K90: 148.1 | L90: 89.8 | M90: 130.5 | N90: 118 | O90: 130.5 | P90: 128.5 | Q90: 132.1 | R90: 123.2 | S90: 117.6 | T90: 122.3 | U90: 119 | V90: 115.1 | W90: 119.2 | X90: 115.4 | Y90: 111.7 | Z90: 116.2 | AA90: 123.8 | AB90: 112.5 | AC90: 116 | AD90: 121.7
A91: Rural+Urban | B91: 2015 | C91: June | D91: 123.9 | E91: 131.8 | F91: 121.6 | G91: 128.2 | H91: 111.1 | I91: 132.8 | J91: 139.1 | K91: 137.4 | L91: 94.1 | M91: 125.5 | N91: 119.8 | O91: 130.9 | P91: 127.3 | Q91: 129.2 | R91: 126.4 | S91: 122 | T91: 125.7 | U91: 119 | V91: 119.8 | W91: 121.1 | X91: 118.5 | Y91: 112.9 | Z91: 116.9 | AA91: 123.1 | AB91: 112.8 | AC91: 117 | AD91: 123
A92: Rural | B92: 2015 | C92: July | D92: 124 | E92: 131.5 | F92: 122 | G92: 128.7 | H92: 113.5 | I92: 133.3 | J92: 140.8 | K92: 133.8 | L92: 94.1 | M92: 123.4 | N92: 121 | O92: 131.7 | P92: 127.5 | Q92: 129.4 | R92: 128.8 | S92: 125.5 | T92: 128.3 | U92: NA | V92: 123 | W92: 123 | X92: 120.8 | Y92: 114.1 | Z92: 118 | AA92: 122.9 | AB92: 112.7 | AC92: 118.1 | AD92: 124.7
A93: Urban | B93: 2015 | C93: July | D93: 123.2 | E93: 134.3 | F93: 119.5 | G93: 127.7 | H93: 106.3 | I93: 132.8 | J93: 153.5 | K93: 149.5 | L93: 85.7 | M93: 131.5 | N93: 118.3 | O93: 131.1 | P93: 129.5 | Q93: 133.1 | R93: 123.5 | S93: 117.9 | T93: 122.7 | U93: 119.9 | V93: 115.3 | W93: 119.5 | X93: 116 | Y93: 111.5 | Z93: 116.6 | AA93: 125.4 | AB93: 111.7 | AC93: 116.3 | AD93: 122.4
A94: Rural+Urban | B94: 2015 | C94: July | D94: 123.7 | E94: 132.5 | F94: 121 | G94: 128.3 | H94: 110.9 | I94: 133.1 | J94: 145.1 | K94: 139.1 | L94: 91.3 | M94: 126.1 | N94: 119.9 | O94: 131.4 | P94: 128.2 | Q94: 130.4 | R94: 126.7 | S94: 122.3 | T94: 126.1 | U94: 119.9 | V94: 120.1 | W94: 121.3 | X94: 119 | Y94: 112.7 | Z94: 117.2 | AA94: 124.4 | AB94: 112.3 | AC94: 117.2 | AD94: 123.6
A95: Rural | B95: 2015 | C95: August | D95: 124.7 | E95: 131.3 | F95: 121.3 | G95: 128.8 | H95: 114 | I95: 134.2 | J95: 153.6 | K95: 137.9 | L95: 93.1 | M95: 123.9 | N95: 121.5 | O95: 132.5 | P95: 129.8 | Q95: 130.1 | R95: 129.5 | S95: 126.3 | T95: 129 | U95: NA | V95: 123.8 | W95: 123.7 | X95: 121.1 | Y95: 113.6 | Z95: 118.5 | AA95: 123.6 | AB95: 112.5 | AC95: 118.2 | AD95: 126.1
A96: Urban | B96: 2015 | C96: August | D96: 123.1 | E96: 131.7 | F96: 118.1 | G96: 128 | H96: 106.8 | I96: 130.1 | J96: 165.5 | K96: 156 | L96: 85.3 | M96: 132.7 | N96: 118.8 | O96: 131.7 | P96: 131.1 | Q96: 134.2 | R96: 123.7 | S96: 118.2 | T96: 122.9 | U96: 120.9 | V96: 115.3 | W96: 120 | X96: 116.6 | Y96: 109.9 | Z96: 117.2 | AA96: 126.2 | AB96: 112 | AC96: 116.2 | AD96: 123.2
A97: Rural+Urban | B97: 2015 | C97: August | D97: 124.2 | E97: 131.4 | F97: 120.1 | G97: 128.5 | H97: 111.4 | I97: 132.3 | J97: 157.6 | K97: 144 | L97: 90.5 | M97: 126.8 | N97: 120.4 | O97: 132.1 | P97: 130.3 | Q97: 131.2 | R97: 127.2 | S97: 122.9 | T97: 126.6 | U97: 120.9 | V97: 120.6 | W97: 122 | X97: 119.4 | Y97: 111.7 | Z97: 117.8 | AA97: 125.1 | AB97: 112.3 | AC97: 117.2 | AD97: 124.8
A98: Rural | B98: 2015 | C98: September | D98: 125.1 | E98: 131.1 | F98: 120.7 | G98: 129.2 | H98: 114.7 | I98: 132.3 | J98: 158.9 | K98: 142.1 | L98: 92.5 | M98: 125.4 | N98: 121.9 | O98: 132.7 | P98: 131 | Q98: 131 | R98: 130.4 | S98: 126.8 | T98: 129.9 | U98: NA | V98: 123.7 | W98: 124.5 | X98: 121.4 | Y98: 113.8 | Z98: 119.6 | AA98: 124.5 | AB98: 113.7 | AC98: 118.8 | AD98: 127
A99: Urban | B99: 2015 | C99: September | D99: 123.4 | E99: 129 | F99: 115.6 | G99: 128.3 | H99: 107 | I99: 124 | J99: 168.5 | K99: 165.4 | L99: 86.3 | M99: 134.4 | N99: 119.1 | O99: 132.3 | P99: 131.5 | Q99: 134.7 | R99: 124 | S99: 118.6 | T99: 123.2 | U99: 121.6 | V99: 115.1 | W99: 120.4 | X99: 117.1 | Y99: 109.1 | Z99: 117.3 | AA99: 126.5 | AB99: 112.9 | AC99: 116.2 | AD99: 123.5
A100: Rural+Urban | B100: 2015 | C100: September | D100: 124.6 | E100: 130.4 | F100: 118.7 | G100: 128.9 | H100: 111.9 | I100: 128.4 | J100: 162.2 | K100: 150 | L100: 90.4 | M100: 128.4 | N100: 120.7 | O100: 132.5 | P100: 131.2 | Q100: 132 | R100: 127.9 | S100: 123.4 | T100: 127.2 | U100: 121.6 | V100: 120.4 | W100: 122.6 | X100: 119.8 | Y100: 111.3 | Z100: 118.3 | AA100: 125.7 | AB100: 113.4 | AC100: 117.5 | AD100: 125.4
...

Sheet Broader Categories
A1: Category | B1: Broader Category
A2: Cereals and products | B2: Food
A3: Meat and fish | B3: Food
A4: Egg | B4: Food
A5: Milk and products | B5: Food
A6: Oils and fats | B6: Food
A7: Fruits | B7: Food
A8: Vegetables | B8: Food
A9: Pulses and products | B9: Food
A10: Sugar and Confectionery | B10: Food
A11: Spices | B11: Food
A12: Non-alcoholic beverages | B12: Food
... A28: General index | B28: Does not come under any category

Sheet Main Data
A1: Sector | B1: Year | C1: Month | D1: Year - Month | E1: Cereals and products | F1: Meat and fish | G1: Egg | H1: Milk and products | I1: Oils and fats | J1: Fruits | K1: Vegetables | L1: Pulses and products | M1: Sugar and Confectionery | N1: Spices | O1: Non-alcoholic beverages | P1: Prepared meals, snacks, sweets etc. | Q1: Food and beverages | R1: Pan, tobacco and intoxicants | S1: Clothing | T1: Footwear | U1: Clothing and footwear | V1: Housing | W1: Fuel and light | X1: Household goods and services | Y1: Health | Z1: Transport and communication | AA1: Recreation and amusement | AB1: Education | AC1: Personal care and effects | AD1: Miscellaneous | AE1: General index | AF1: Food | AG1: Apparels | AH1: Home | AI1: Health Care | AJ1: Transport | AK1: Recreation | AL1: Education Index
A2: Rural | B2: 2013 | C2: January | D2: =B2 & " - " & C2 -> 2013 - January | E2: 107.5 | F2: 106.3 | G2: 108.1 | H2: 104.9 | I2: 106.1 | J2: 103.9 | K2: 101.9 | L2: 106.1 | M2: 106.8 | N2: 103.1 | O2: 104.8 | P2: 106.7 | Q2: 105.5 | R2: 105.1 | S2: 106.5 | T2: 105.8 | U2: 106.4 | V2: NA | W2: 105.5 | X2: 104.8 | Y2: 104 | Z2: 103.3 | AA2: 103.4 | AB2: 103.8 | AC2: 104.7 | AD2: 104 | AE2: 105.1 | AF2: =SUM(E2:R2) -> 1476.8 | AG2: =SUM(S2:U2) -> 318.7 | AH2: =SUM(V2:X2) -> 210.3 | AI2: =SUM(Y2,AC2) -> 208.7 | AJ2: =SUM(Z2) -> 103.3 | AK2: =SUM(AA2) -> 103.4 | AL2: =SUM(AB2) -> 103.8
A3: Urban | B3: 2013 | C3: January | D3: =B3 & " - " & C3 -> 2013 - January | E3: 110.5 | F3: 109.1 | G3: 113 | H3: 103.6 | I3: 103.4 | J3: 102.3 | K3: 102.9 | L3: 105.8 | M3: 105.1 | N3: 101.8 | O3: 105.1 | P3: 107.9 | Q3: 105.9 | R3: 105.2 | S3: 105.9 | T3: 105 | U3: 105.8 | V3: 100.3 | W3: 105.4 | X3: 104.8 | Y3: 104.1 | Z3: 103.2 | AA3: 102.9 | AB3: 103.5 | AC3: 104.3 | AD3: 103.7 | AE3: 104 | AF3: =SUM(E3:R3) -> 1481.6 | AG3: =SUM(S3:U3) -> 316.7 | AH3: =SUM(V3:X3) -> 310.5 | AI3: =SUM(Y3,AC3) -> 208.4 | AJ3: =SUM(Z3) -> 103.2 | AK3: =SUM(AA3) -> 102.9 | AL3: =SUM(AB3) -> 103.5
A4: Rural+Urban | B4: 2013 | C4: January | D4: =B4 & " - " & C4 -> 2013 - January | E4: 108.4 | F4: 107.3 | G4: 110 | H4: 104.4 | I4: 105.1 | J4: 103.2 | K4: 102.2 | L4: 106 | M4: 106.2 | N4: 102.7 | O4: 104.9 | P4: 107.3 | Q4: 105.6 | R4: 105.1 | S4: 106.3 | T4: 105.5 | U4: 106.2 | V4: 100.3 | W4: 105.5 | X4: 104.8 | Y4: 104 | Z4: 103.2 | AA4: 103.1 | AB4: 103.6 | AC4: 104.5 | AD4: 103.9 | AE4: 104.6 | AF4: =SUM(E4:R4) -> 1478.4 | AG4: =SUM(S4:U4) -> 318 | AH4: =SUM(V4:X4) -> 310.6 | AI4: =SUM(Y4,AC4) -> 208.5 | AJ4: =SUM(Z4) -> 103.2 | AK4: =SUM(AA4) -> 103.1 | AL4: =SUM(AB4) -> 103.6
A5: Rural | B5: 2013 | C5: February | D5: =B5 & " - " & C5 -> 2013 - February | E5: 109.2 | F5: 108.7 | G5: 110.2 | H5: 105.4 | I5: 106.7 | J5: 104 | K5: 102.4 | L5: 105.9 | M5: 105.7 | N5: 103.1 | O5: 105.1 | P5: 107.7 | Q5: 106.3 | R5: 105.6 | S5: 107.1 | T5: 106.3 | U5: 107 | V5: NA | W5: 106.2 | X5: 105.2 | Y5: 104.4 | Z5: 103.9 | AA5: 104 | AB5: 104.1 | AC5: 104.6 | AD5: 104.4 | AE5: 105.8 | AF5: =SUM(E5:R5) -> 1486 | AG5: =SUM(S5:U5) -> 320.4 | AH5: =SUM(V5:X5) -> 211.4 | AI5: =SUM(Y5,AC5) -> 209 | AJ5: =SUM(Z5) -> 103.9 | AK5: =SUM(AA5) -> 104 | AL5: =SUM(AB5) -> 104.1
A6: Urban | B6: 2013 | C6: February | D6: =B6 & " - " & C6 -> 2013 - February | E6: 112.9 | F6: 112.9 | G6: 116.9 | H6: 104 | I6: 103.5 | J6: 103.1 | K6: 104.9 | L6: 104.1 | M6: 103.8 | N6: 102.3 | O6: 106 | P6: 109 | Q6: 107.2 | R6: 106 | S6: 106.6 | T6: 105.5 | U6: 106.4 | V6: 100.4 | W6: 105.7 | X6: 105.2 | Y6: 104.7 | Z6: 104.4 | AA6: 103.3 | AB6: 103.7 | AC6: 104.3 | AD6: 104.3 | AE6: 104.7 | AF6: =SUM(E6:R6) -> 1496.6 | AG6: =SUM(S6:U6) -> 318.5 | AH6: =SUM(V6:X6) -> 311.3 | AI6: =SUM(Y6,AC6) -> 209 | AJ6: =SUM(Z6) -> 104.4 | AK6: =SUM(AA6) -> 103.3 | AL6: =SUM(AB6) -> 103.7
A7: Rural+Urban | B7: 2013 | C7: February | D7: =B7 & " - " & C7 -> 2013 - February | E7: 110.4 | F7: 110.2 | G7: 112.8 | H7: 104.9 | I7: 105.5 | J7: 103.6 | K7: 103.2 | L7: 105.3 | M7: 105.1 | N7: 102.8 | O7: 105.5 | P7: 108.3 | Q7: 106.6 | R7: 105.7 | S7: 106.9 | T7: 106 | U7: 106.8 | V7: 100.4 | W7: 106 | X7: 105.2 | Y7: 104.5 | Z7: 104.2 | AA7: 103.6 | AB7: 103.9 | AC7: 104.5 | AD7: 104.4 | AE7: 105.3 | AF7: =SUM(E7:R7) -> 1489.9 | AG7: =SUM(S7:U7) -> 319.7 | AH7: =SUM(V7:X7) -> 311.6 | AI7: =SUM(Y7,AC7) -> 209 | AJ7: =SUM(Z7) -> 104.2 | AK7: =SUM(AA7) -> 103.6 | AL7: =SUM(AB7) -> 103.9
A8: Rural | B8: 2013 | C8: March | D8: =B8 & " - " & C8 -> 2013 - March | E8: 110.2 | F8: 108.8 | G8: 109.9 | H8: 105.6 | I8: 106.2 | J8: 105.7 | K8: 101.4 | L8: 105.7 | M8: 105 | N8: 103.3 | O8: 105.6 | P8: 108.2 | Q8: 106.6 | R8: 106.5 | S8: 107.6 | T8: 106.8 | U8: 107.5 | V8: NA | W8: 106.1 | X8: 105.6 | Y8: 104.7 | Z8: 104.6 | AA8: 104 | AB8: 104.3 | AC8: 104.3 | AD8: 104.6 | AE8: 106 | AF8: =SUM(E8:R8) -> 1488.7 | AG8: =SUM(S8:U8) -> 321.9 | AH8: =SUM(V8:X8) -> 211.7 | AI8: =SUM(Y8,AC8) -> 209 | AJ8: =SUM(Z8) -> 104.6 | AK8: =SUM(AA8) -> 104 | AL8: =SUM(AB8) -> 104.3
A9: Urban | B9: 2013 | C9: March | D9: =B9 & " - " & C9 -> 2013 - March | E9: 113.9 | F9: 111.4 | G9: 113.2 | H9: 104.3 | I9: 102.7 | J9: 104.9 | K9: 103.8 | L9: 103.5 | M9: 102.6 | N9: 102.4 | O9: 107 | P9: 109.8 | Q9: 107.3 | R9: 106.8 | S9: 107.2 | T9: 106 | U9: 107 | V9: 100.4 | W9: 106 | X9: 105.7 | Y9: 105.2 | Z9: 105.5 | AA9: 103.5 | AB9: 103.8 | AC9: 104.2 | AD9: 104.9 | AE9: 105 | AF9: =SUM(E9:R9) -> 1493.6 | AG9: =SUM(S9:U9) -> 320.2 | AH9: =SUM(V9:X9) -> 312.1 | AI9: =SUM(Y9,AC9) -> 209.4 | AJ9: =SUM(Z9) -> 105.5 | AK9: =SUM(AA9) -> 103.5 | AL9: =SUM(AB9) -> 103.8
A10: Rural+Urban | B10: 2013 | C10: March | D10: =B10 & " - " & C10 -> 2013 - March | E10: 111.4 | F10: 109.7 | G10: 111.2 | H10: 105.1 | I10: 104.9 | J10: 105.3 | K10: 102.2 | L10: 105 | M10: 104.2 | N10: 103 | O10: 106.2 | P10: 108.9 | Q10: 106.9 | R10: 106.6 | S10: 107.4 | T10: 106.5 | U10: 107.3 | V10: 100.4 | W10: 106.1 | X10: 105.6 | Y10: 104.9 | Z10: 105.1 | AA10: 103.7 | AB10: 104 | AC10: 104.3 | AD10: 104.7 | AE10: 105.5 | AF10: =SUM(E10:R10) -> 1490.6 | AG10: =SUM(S10:U10) -> 321.2 | AH10: =SUM(V10:X10) -> 312.1 | AI10: =SUM(Y10,AC10) -> 209.2 | AJ10: =SUM(Z10) -> 105.1 | AK10: =SUM(AA10) -> 103.7 | AL10: =SUM(AB10) -> 104
A11: Rural | B11: 2013 | C11: April | D11: =B11 & " - " & C11 -> 2013 - April | E11: 110.2 | F11: 109.5 | G11: 106.9 | H11: 106.3 | I11: 105.7 | J11: 108.3 | K11: 103.4 | L11: 105.7 | M11: 104.2 | N11: 103.2 | O11: 106.5 | P11: 108.8 | Q11: 107.1 | R11: 107.1 | S11: 108.1 | T11: 107.4 | U11: 108 | V11: NA | W11: 106.5 | X11: 106.1 | Y11: 105.1 | Z11: 104.4 | AA11: 104.5 | AB11: 104.8 | AC11: 102.7 | AD11: 104.6 | AE11: 106.4 | AF11: =SUM(E11:R11) -> 1492.9 | AG11: =SUM(S11:U11) -> 323.5 | AH11: =SUM(V11:X11) -> 212.6 | AI11: =SUM(Y11,AC11) -> 207.8 | AJ11: =SUM(Z11) -> 104.4 | AK11: =SUM(AA11) -> 104.5 | AL11: =SUM(AB11) -> 104.8
A12: Urban | B12: 2013 | C12: April | D12: =B12 & " - " & C12 -> 2013 - April | E12: 114.6 | F12: 113.4 | G12: 106 | H12: 104.7 | I12: 102.1 | J12: 109.5 | K12: 109.7 | L12: 104.6 | M12: 102 | N12: 103.5 | O12: 108.2 | P12: 110.6 | Q12: 108.8 | R12: 108.5 | S12: 107.9 | T12: 106.4 | U12: 107.7 | V12: 100.5 | W12: 106.4 | X12: 106.5 | Y12: 105.7 | Z12: 105 | AA12: 104 | AB12: 105.2 | AC12: 103.2 | AD12: 105.1 | AE12: 105.7 | AF12: =SUM(E12:R12) -> 1506.2 | AG12: =SUM(S12:U12) -> 322 | AH12: =SUM(V12:X12) -> 313.4 | AI12: =SUM(Y12,AC12) -> 208.9 | AJ12: =SUM(Z12) -> 105 | AK12: =SUM(AA12) -> 104 | AL12: =SUM(AB12) -> 105.2
A13: Rural+Urban | B13: 2013 | C13: April | D13: =B13 & " - " & C13 -> 2013 - April | E13: 111.6 | F13: 110.9 | G13: 106.6 | H13: 105.7 | I13: 104.4 | J13: 108.9 | K13: 105.5 | L13: 105.3 | M13: 103.5 | N13: 103.3 | O13: 107.2 | P13: 109.6 | Q13: 107.7 | R13: 107.5 | S13: 108 | T13: 107 | U13: 107.9 | V13: 100.5 | W13: 106.5 | X13: 106.3 | Y13: 105.3 | Z13: 104.7 | AA13: 104.2 | AB13: 105 | AC13: 102.9 | AD13: 104.8 | AE13: 106.1 | AF13: =SUM(E13:R13) -> 1497.7 | AG13: =SUM(S13:U13) -> 322.9 | AH13: =SUM(V13:X13) -> 313.3 | AI13: =SUM(Y13,AC13) -> 208.2 | AJ13: =SUM(Z13) -> 104.7 | AK13: =SUM(AA13) -> 104.2 | AL13: =SUM(AB13) -> 105
A14: Rural | B14: 2013 | C14: May | D14: =B14 & " - " & C14 -> 2013 - May | E14: 110.9 | F14: 109.8 | G14: 105.9 | H14: 107.5 | I14: 105.3 | J14: 108.1 | K14: 107.3 | L14: 106.1 | M14: 103.7 | N14: 104 | O14: 107.4 | P14: 109.9 | Q14: 108.1 | R14: 108.1 | S14: 108.8 | T14: 107.9 | U14: 108.6 | V14: NA | W14: 107.5 | X14: 106.8 | Y14: 105.7 | Z14: 104.1 | AA14: 105 | AB14: 105.5 | AC14: 102.1 | AD14: 104.8 | AE14: 107.2 | AF14: =SUM(E14:R14) -> 1502.1 | AG14: =SUM(S14:U14) -> 325.3 | AH14: =SUM(V14:X14) -> 214.3 | AI14: =SUM(Y14,AC14) -> 207.8 | AJ14: =SUM(Z14) -> 104.1 | AK14: =SUM(AA14) -> 105 | AL14: =SUM(AB14) -> 105.5
A15: Urban | B15: 2013 | C15: May | D15: =B15 & " - " & C15 -> 2013 - May | E15: 115.4 | F15: 114.2 | G15: 102.7 | H15: 105.5 | I15: 101.5 | J15: 110.6 | K15: 123.7 | L15: 105.2 | M15: 101.9 | N15: 105 | O15: 109.1 | P15: 111.3 | Q15: 111.1 | R15: 109.8 | S15: 108.5 | T15: 106.7 | U15: 108.3 | V15: 100.5 | W15: 107.2 | X15: 107.1 | Y15: 106.2 | Z15: 103.9 | AA15: 104.6 | AB15: 105.7 | AC15: 102.6 | AD15: 104.9 | AE15: 106.6 | AF15: =SUM(E15:R15) -> 1527 | AG15: =SUM(S15:U15) -> 323.5 | AH15: =SUM(V15:X15) -> 314.8 | AI15: =SUM(Y15,AC15) -> 208.8 | AJ15: =SUM(Z15) -> 103.9 | AK15: =SUM(AA15) -> 104.6 | AL15: =SUM(AB15) -> 105.7
A16: Rural+Urban | B16: 2013 | C16: May | D16: =B16 & " - " & C16 -> 2013 - May | E16: 112.3 | F16: 111.3 | G16: 104.7 | H16: 106.8 | I16: 103.9 | J16: 109.3 | K16: 112.9 | L16: 105.8 | M16: 103.1 | N16: 104.3 | O16: 108.1 | P16: 110.5 | Q16: 109.2 | R16: 108.6 | S16: 108.7 | T16: 107.4 | U16: 108.5 | V16: 100.5 | W16: 107.4 | X16: 106.9 | Y16: 105.9 | Z16: 104 | AA16: 104.8 | AB16: 105.6 | AC16: 102.3 | AD16: 104.8 | AE16: 106.9 | AF16: =SUM(E16:R16) -> 1510.8 | AG16: =SUM(S16:U16) -> 324.6 | AH16: =SUM(V16:X16) -> 314.8 | AI16: =SUM(Y16,AC16) -> 208.2 | AJ16: =SUM(Z16) -> 104 | AK16: =SUM(AA16) -> 104.8 | AL16: =SUM(AB16) -> 105.6
A17: Rural | B17: 2013 | C17: June | D17: =B17 & " - " & C17 -> 2013 - June | E17: 112.3 | F17: 112.1 | G17: 108.1 | H17: 108.3 | I17: 105.9 | J17: 109.2 | K17: 118 | L17: 106.8 | M17: 104.1 | N17: 105.4 | O17: 108.2 | P17: 111 | Q17: 110.6 | R17: 109 | S17: 109.7 | T17: 108.8 | U17: 109.5 | V17: NA | W17: 108.5 | X17: 107.5 | Y17: 106.3 | Z17: 105 | AA17: 105.6 | AB17: 106.5 | AC17: 102.5 | AD17: 105.5 | AE17: 108.9 | AF17: =SUM(E17:R17) -> 1529 | AG17: =SUM(S17:U17) -> 328 | AH17: =SUM(V17:X17) -> 216 | AI17: =SUM(Y17,AC17) -> 208.8 | AJ17: =SUM(Z17) -> 105 | AK17: =SUM(AA17) -> 105.6 | AL17: =SUM(AB17) -> 106.5
A18: Urban | B18: 2013 | C18: June | D18: =B18 & " - " & C18 -> 2013 - June | E18: 117 | F18: 120.1 | G18: 112.5 | H18: 107.3 | I18: 101.3 | J18: 112.4 | K18: 143.6 | L18: 105.4 | M18: 101.4 | N18: 106.4 | O18: 110 | P18: 112.2 | Q18: 115 | R18: 110.9 | S18: 109.2 | T18: 107.2 | U18: 108.9 | V18: 106.6 | W18: 108 | X18: 107.7 | Y18: 106.5 | Z18: 105.2 | AA18: 105.2 | AB18: 108.1 | AC18: 103.3 | AD18: 106.1 | AE18: 109.7 | AF18: =SUM(E18:R18) -> 1575.5 | AG18: =SUM(S18:U18) -> 325.3 | AH18: =SUM(V18:X18) -> 322.3 | AI18: =SUM(Y18,AC18) -> 209.8 | AJ18: =SUM(Z18) -> 105.2 | AK18: =SUM(AA18) -> 105.2 | AL18: =SUM(AB18) -> 108.1
A19: Rural+Urban | B19: 2013 | C19: June | D19: =B19 & " - " & C19 -> 2013 - June | E19: 113.8 | F19: 114.9 | G19: 109.8 | H19: 107.9 | I19: 104.2 | J19: 110.7 | K19: 126.7 | L19: 106.3 | M19: 103.2 | N19: 105.7 | O19: 109 | P19: 111.6 | Q19: 112.2 | R19: 109.5 | S19: 109.5 | T19: 108.1 | U19: 109.3 | V19: 106.6 | W19: 108.3 | X19: 107.6 | Y19: 106.4 | Z19: 105.1 | AA19: 105.4 | AB19: 107.4 | AC19: 102.8 | AD19: 105.8 | AE19: 109.3 | AF19: =SUM(E19:R19) -> 1545.5 | AG19: =SUM(S19:U19) -> 326.9 | AH19: =SUM(V19:X19) -> 322.5 | AI19: =SUM(Y19,AC19) -> 209.2 | AJ19: =SUM(Z19) -> 105.1 | AK19: =SUM(AA19) -> 105.4 | AL19: =SUM(AB19) -> 107.4
A20: Rural | B20: 2013 | C20: July | D20: =B20 & " - " & C20 -> 2013 - July | E20: 113.4 | F20: 114.9 | G20: 110.5 | H20: 109.3 | I20: 106.2 | J20: 110.3 | K20: 129.2 | L20: 107.1 | M20: 104.3 | N20: 106.4 | O20: 109.1 | P20: 112.1 | Q20: 113.1 | R20: 109.8 | S20: 110.5 | T20: 109.5 | U20: 110.3 | V20: NA | W20: 109.5 | X20: 108.3 | Y20: 106.9 | Z20: 106.8 | AA20: 106.4 | AB20: 107.8 | AC20: 102.5 | AD20: 106.5 | AE20: 110.7 | AF20: =SUM(E20:R20) -> 1555.7 | AG20: =SUM(S20:U20) -> 330.3 | AH20: =SUM(V20:X20) -> 217.8 | AI20: =SUM(Y20,AC20) -> 209.4 | AJ20: =SUM(Z20) -> 106.8 | AK20: =SUM(AA20) -> 106.4 | AL20: =SUM(AB20) -> 107.8
A21: Urban | B21: 2013 | C21: July | D21: =B21 & " - " & C21 -> 2013 - July | E21: 117.8 | F21: 119.2 | G21: 114 | H21: 108.3 | I21: 101.1 | J21: 113.2 | K21: 160.9 | L21: 105.1 | M21: 101.3 | N21: 107.5 | O21: 110.4 | P21: 113.1 | Q21: 117.5 | R21: 111.7 | S21: 109.8 | T21: 107.8 | U21: 109.5 | V21: 107.7 | W21: 108.6 | X21: 108.1 | Y21: 107.1 | Z21: 107.3 | AA21: 105.9 | AB21: 110.1 | AC21: 103.2 | AD21: 107.3 | AE21: 111.4 | AF21: =SUM(E21:R21) -> 1601.1 | AG21: =SUM(S21:U21) -> 327.1 | AH21: =SUM(V21:X21) -> 324.4 | AI21: =SUM(Y21,AC21) -> 210.3 | AJ21: =SUM(Z21) -> 107.3 | AK21: =SUM(AA21) -> 105.9 | AL21: =SUM(AB21) -> 110.1
A22: Rural+Urban | B22: 2013 | C22: July | D22: =B22 & " - " & C22 -> 2013 - July | E22: 114.8 | F22: 116.4 | G22: 111.9 | H22: 108.9 | I22: 104.3 | J22: 111.7 | K22: 140 | L22: 106.4 | M22: 103.3 | N22: 106.8 | O22: 109.6 | P22: 112.6 | Q22: 114.7 | R22: 110.3 | S22: 110.2 | T22: 108.8 | U22: 110 | V22: 107.7 | W22: 109.2 | X22: 108.2 | Y22: 107 | Z22: 107.1 | AA22: 106.1 | AB22: 109.1 | AC22: 102.8 | AD22: 106.9 | AE22: 111 | AF22: =SUM(E22:R22) -> 1571.7 | AG22: =SUM(S22:U22) -> 329 | AH22: =SUM(V22:X22) -> 325.1 | AI22: =SUM(Y22,AC22) -> 209.8 | AJ22: =SUM(Z22) -> 107.1 | AK22: =SUM(AA22) -> 106.1 | AL22: =SUM(AB22) -> 109.1
A23: Rural | B23: 2013 | C23: August | D23: =B23 & " - " & C23 -> 2013 - August | E23: 114.3 | F23: 115.4 | G23: 111.1 | H23: 110 | I23: 106.4 | J23: 110.8 | K23: 138.9 | L23: 107.4 | M23: 104.1 | N23: 106.9 | O23: 109.7 | P23: 112.6 | Q23: 114.9 | R23: 110.7 | S23: 111.3 | T23: 110.2 | U23: 111.1 | V23: NA | W23: 109.9 | X23: 108.7 | Y23: 107.5 | Z23: 107.8 | AA23: 106.8 | AB23: 108.7 | AC23: 105 | AD23: 107.5 | AE23: 112.1 | AF23: =SUM(E23:R23) -> 1573.2 | AG23: =SUM(S23:U23) -> 332.6 | AH23: =SUM(V23:X23) -> 218.6 | AI23: =SUM(Y23,AC23) -> 212.5 | AJ23: =SUM(Z23) -> 107.8 | AK23: =SUM(AA23) -> 106.8 | AL23: =SUM(AB23) -> 108.7
A24: Urban | B24: 2013 | C24: August | D24: =B24 & " - " & C24 -> 2013 - August | E24: 118.3 | F24: 120.4 | G24: 112.7 | H24: 108.9 | I24: 101.1 | J24: 108.7 | K24: 177 | L24: 104.7 | M24: 101 | N24: 108.5 | O24: 110.9 | P24: 114.3 | Q24: 119.6 | R24: 112.4 | S24: 110.6 | T24: 108.3 | U24: 110.2 | V24: 108.9 | W24: 109.3 | X24: 108.7 | Y24: 107.6 | Z24: 108.1 | AA24: 106.5 | AB24: 110.8 | AC24: 106 | AD24: 108.3 | AE24: 112.7 | AF24: =SUM(E24:R24) -> 1618.5 | AG24: =SUM(S24:U24) -> 329.1 | AH24: =SUM(V24:X24) -> 326.9 | AI24: =SUM(Y24,AC24) -> 213.6 | AJ24: =SUM(Z24) -> 108.1 | AK24: =SUM(AA24) -> 106.5 | AL24: =SUM(AB24) -> 110.8
A25: Rural+Urban | B25: 2013 | C25: August | D25: =B25 & " - " & C25 -> 2013 - August | E25: 115.6 | F25: 117.2 | G25: 111.7 | H25: 109.6 | I25: 104.5 | J25: 109.8 | K25: 151.8 | L25: 106.5 | M25: 103.1 | N25: 107.4 | O25: 110.2 | P25: 113.4 | Q25: 116.6 | R25: 111.2 | S25: 111 | T25: 109.4 | U25: 110.7 | V25: 108.9 | W25: 109.7 | X25: 108.7 | Y25: 107.5 | Z25: 108 | AA25: 106.6 | AB25: 109.9 | AC25: 105.4 | AD25: 107.9 | AE25: 112.4 | AF25: =SUM(E25:R25) -> 1588.6 | AG25: =SUM(S25:U25) -> 331.1 | AH25: =SUM(V25:X25) -> 327.3 | AI25: =SUM(Y25,AC25) -> 212.9 | AJ25: =SUM(Z25) -> 108 | AK25: =SUM(AA25) -> 106.6 | AL25: =SUM(AB25) -> 109.9
A26: Rural | B26: 2013 | C26: September | D26: =B26 & " - " & C26 -> 2013 - September | E26: 115.4 | F26: 115.7 | G26: 111.7 | H26: 111 | I26: 107.4 | J26: 110.9 | K26: 154 | L26: 108.1 | M26: 104.2 | N26: 107.9 | O26: 110.4 | P26: 114 | Q26: 117.8 | R26: 111.7 | S26: 112.7 | T26: 111.4 | U26: 112.5 | V26: NA | W26: 111.1 | X26: 109.6 | Y26: 108.3 | Z26: 109.3 | AA26: 107.7 | AB26: 109.8 | AC26: 106.7 | AD26: 108.7 | AE26: 114.2 | AF26: =SUM(E26:R26) -> 1600.2 | AG26: =SUM(S26:U26) -> 336.6 | AH26: =SUM(V26:X26) -> 220.7 | AI26: =SUM(Y26,AC26) -> 215 | AJ26: =SUM(Z26) -> 109.3 | AK26: =SUM(AA26) -> 107.7 | AL26: =SUM(AB26) -> 109.8
A27: Urban | B27: 2013 | C27: September | D27: =B27 & " - " & C27 -> 2013 - September | E27: 118.6 | F27: 119.1 | G27: 113.2 | H27: 109.6 | I27: 101.7 | J27: 103.2 | K27: 174.3 | L27: 105.1 | M27: 100.8 | N27: 109.1 | O27: 111.1 | P27: 115.4 | Q27: 119.2 | R27: 112.9 | S27: 111.4 | T27: 109 | U27: 111.1 | V27: 109.7 | W27: 109.5 | X27: 109.6 | Y27: 107.9 | Z27: 110.4 | AA27: 107.4 | AB27: 111.2 | AC27: 106.9 | AD27: 109.4 | AE27: 113.2 | AF27: =SUM(E27:R27) -> 1613.3 | AG27: =SUM(S27:U27) -> 331.5 | AH27: =SUM(V27:X27) -> 328.8 | AI27: =SUM(Y27,AC27) -> 214.8 | AJ27: =SUM(Z27) -> 110.4 | AK27: =SUM(AA27) -> 107.4 | AL27: =SUM(AB27) -> 111.2
A28: Rural+Urban | B28: 2013 | C28: September | D28: =B28 & " - " & C28 -> 2013 - September | E28: 116.4 | F28: 116.9 | G28: 112.3 | H28: 110.5 | I28: 105.3 | J28: 107.3 | K28: 160.9 | L28: 107.1 | M28: 103.1 | N28: 108.3 | O28: 110.7 | P28: 114.6 | Q28: 118.3 | R28: 112 | S28: 112.2 | T28: 110.4 | U28: 111.9 | V28: 109.7 | W28: 110.5 | X28: 109.6 | Y28: 108.1 | Z28: 109.9 | AA28: 107.5 | AB28: 110.6 | AC28: 106.8 | AD28: 109 | AE28: 113.7 | AF28: =SUM(E28:R28) -> 1603.7 | AG28: =SUM(S28:U28) -> 334.5 | AH28: =SUM(V28:X28) -> 329.8 | AI28: =SUM(Y28,AC28) -> 214.9 | AJ28: =SUM(Z28) -> 109.9 | AK28: =SUM(AA28) -> 107.5 | AL28: =SUM(AB28) -> 110.6
A29: Rural | B29: 2013 | C29: October | D29: =B29 & " - " & C29 -> 2013 - October | E29: 116.3 | F29: 115.4 | G29: 112.6 | H29: 111.7 | I29: 107.7 | J29: 113.2 | K29: 164.9 | L29: 108.3 | M29: 103.9 | N29: 108.2 | O29: 111.1 | P29: 114.9 | Q29: 119.8 | R29: 112.2 | S29: 113.6 | T29: 112.3 | U29: 113.4 | V29: NA | W29: 111.6 | X29: 110.4 | Y29: 108.9 | Z29: 109.3 | AA29: 108.3 | AB29: 110.2 | AC29: 107.5 | AD29: 109.1 | AE29: 115.5 | AF29: =SUM(E29:R29) -> 1620.2 | AG29: =SUM(S29:U29) -> 339.3 | AH29: =SUM(V29:X29) -> 222 | AI29: =SUM(Y29,AC29) -> 216.4 | AJ29: =SUM(Z29) -> 109.3 | AK29: =SUM(AA29) -> 108.3 | AL29: =SUM(AB29) -> 110.2
A30: Urban | B30: 2013 | C30: October | D30: =B30 & " - " & C30 -> 2013 - October | E30: 118.9 | F30: 118.1 | G30: 114.5 | H30: 110.4 | I30: 102.3 | J30: 106.2 | K30: 183.5 | L30: 105.3 | M30: 100.2 | N30: 109.6 | O30: 111.4 | P30: 116 | Q30: 120.8 | R30: 113.5 | S30: 112.5 | T30: 109.7 | U30: 112 | V30: 110.5 | W30: 109.7 | X30: 110.2 | Y30: 108.2 | Z30: 109.7 | AA30: 108 | AB30: 111.3 | AC30: 107.3 | AD30: 109.4 | AE30: 114 | AF30: =SUM(E30:R30) -> 1630.7 | AG30: =SUM(S30:U30) -> 334.2 | AH30: =SUM(V30:X30) -> 330.4 | AI30: =SUM(Y30,AC30) -> 215.5 | AJ30: =SUM(Z30) -> 109.7 | AK30: =SUM(AA30) -> 108 | AL30: =SUM(AB30) -> 111.3
A31: Rural+Urban | B31: 2013 | C31: October | D31: =B31 & " - " & C31 -> 2013 - October | E31: 117.1 | F31: 116.3 | G31: 113.3 | H31: 111.2 | I31: 105.7 | J31: 109.9 | K31: 171.2 | L31: 107.3 | M31: 102.7 | N31: 108.7 | O31: 111.2 | P31: 115.4 | Q31: 120.2 | R31: 112.5 | S31: 113.2 | T31: 111.2 | U31: 112.8 | V31: 110.5 | W31: 110.9 | X31: 110.3 | Y31: 108.6 | Z31: 109.5 | AA31: 108.1 | AB31: 110.8 | AC31: 107.4 | AD31: 109.2 | AE31: 114.8 | AF31: =SUM(E31:R31) -> 1622.7 | AG31: =SUM(S31:U31) -> 337.2 | AH31: =SUM(V31:X31) -> 331.7 | AI31: =SUM(Y31,AC31) -> 216 | AJ31: =SUM(Z31) -> 109.5 | AK31: =SUM(AA31) -> 108.1 | AL31: =SUM(AB31) -> 110.8
A32: Rural | B32: 2013 | C32: November | D32: =B32 & " - " & C32 -> 2013 - November | E32: 117.3 | F32: 114.9 | G32: 116.2 | H32: 112.8 | I32: 108.9 | J32: 116.6 | K32: 178.1 | L32: 109.1 | M32: 103.6 | N32: 109 | O32: 111.8 | P32: 116 | Q32: 122.5 | R32: 112.8 | S32: 114.6 | T32: 113.1 | U32: 114.4 | V32: NA | W32: 112.6 | X32: 111.3 | Y32: 109.7 | Z32: 109.6 | AA32: 108.7 | AB32: 111 | AC32: 108.2 | AD32: 109.8 | AE32: 117.4 | AF32: =SUM(E32:R32) -> 1649.6 | AG32: =SUM(S32:U32) -> 342.1 | AH32: =SUM(V32:X32) -> 223.9 | AI32: =SUM(Y32,AC32) -> 217.9 | AJ32: =SUM(Z32) -> 109.6 | AK32: =SUM(AA32) -> 108.7 | AL32: =SUM(AB32) -> 111
A33: Urban | B33: 2013 | C33: November | D33: =B33 & " - " & C33 -> 2013 - November | E33: 119.8 | F33: 116.3 | G33: 122.6 | H33: 112 | I33: 103.2 | J33: 110 | K33: 192.8 | L33: 106.3 | M33: 99.5 | N33: 110.3 | O33: 111.8 | P33: 117.1 | Q33: 122.9 | R33: 114.1 | S33: 113.5 | T33: 110.3 | U33: 113 | V33: 111.1 | W33: 110 | X33: 110.9 | Y33: 108.6 | Z33: 109.5 | AA33: 108.5 | AB33: 111.3 | AC33: 107.9 | AD33: 109.6 | AE33: 115 | AF33: =SUM(E33:R33) -> 1658.7 | AG33: =SUM(S33:U33) -> 336.8 | AH33: =SUM(V33:X33) -> 332 | AI33: =SUM(Y33,AC33) -> 216.5 | AJ33: =SUM(Z33) -> 109.5 | AK33: =SUM(AA33) -> 108.5 | AL33: =SUM(AB33) -> 111.3
A34: Rural+Urban | B34: 2013 | C34: November | D34: =B34 & " - " & C34 -> 2013 - November | E34: 118.1 | F34: 115.4 | G34: 118.7 | H34: 112.5 | I34: 106.8 | J34: 113.5 | K34: 183.1 | L34: 108.2 | M34: 102.2 | N34: 109.4 | O34: 111.8 | P34: 116.5 | Q34: 122.6 | R34: 113.1 | S34: 114.2 | T34: 111.9 | U34: 113.8 | V34: 111.1 | W34: 111.6 | X34: 111.1 | Y34: 109.3 | Z34: 109.5 | AA34: 108.6 | AB34: 111.2 | AC34: 108.1 | AD34: 109.7 | AE34: 116.3 | AF34: =SUM(E34:R34) -> 1651.9 | AG34: =SUM(S34:U34) -> 339.9 | AH34: =SUM(V34:X34) -> 333.8 | AI34: =SUM(Y34,AC34) -> 217.4 | AJ34: =SUM(Z34) -> 109.5 | AK34: =SUM(AA34) -> 108.6 | AL34: =SUM(AB34) -> 111.2
A35: Rural | B35: 2013 | C35: December | D35: =B35 & " - " & C35 -> 2013 - December | E35: 118.4 | F35: 115.9 | G35: 120.4 | H35: 113.8 | I35: 109.5 | J35: 115.5 | K35: 145.7 | L35: 109.5 | M35: 102.9 | N35: 109.8 | O35: 112.1 | P35: 116.8 | Q35: 118.7 | R35: 113.6 | S35: 115.8 | T35: 114 | U35: 115.5 | V35: NA | W35: 112.8 | X35: 112.1 | Y35: 110.1 | Z35: 109.9 | AA35: 109.2 | AB35: 111.6 | AC35: 108.1 | AD35: 110.1 | AE35: 115.5 | AF35: =SUM(E35:R35) -> 1622.6 | AG35: =SUM(S35:U35) -> 345.3 | AH35: =SUM(V35:X35) -> 224.9 | AI35: =SUM(Y35,AC35) -> 218.2 | AJ35: =SUM(Z35) -> 109.9 | AK35: =SUM(AA35) -> 109.2 | AL35: =SUM(AB35) -> 111.6
A36: Urban | B36: 2013 | C36: December | D36: =B36 & " - " & C36 -> 2013 - December | E36: 120.5 | F36: 118.1 | G36: 128.5 | H36: 112.8 | I36: 103.4 | J36: 110.7 | K36: 144.8 | L36: 107.1 | M36: 98.6 | N36: 111.9 | O36: 112.1 | P36: 118.1 | Q36: 117.8 | R36: 115 | S36: 114.2 | T36: 110.9 | U36: 113.7 | V36: 110.7 | W36: 110.4 | X36: 111.3 | Y36: 109 | Z36: 109.7 | AA36: 108.9 | AB36: 111.4 | AC36: 107.7 | AD36: 109.8 | AE36: 113.3 | AF36: =SUM(E36:R36) -> 1619.4 | AG36: =SUM(S36:U36) -> 338.8 | AH36: =SUM(V36:X36) -> 332.4 | AI36: =SUM(Y36,AC36) -> 216.7 | AJ36: =SUM(Z36) -> 109.7 | AK36: =SUM(AA36) -> 108.9 | AL36: =SUM(AB36) -> 111.4
A37: Rural+Urban | B37: 2013 | C37: December | D37: =B37 & " - " & C37 -> 2013 - December | E37: 119.1 | F37: 116.7 | G37: 123.5 | H37: 113.4 | I37: 107.3 | J37: 113.3 | K37: 145.4 | L37: 108.7 | M37: 101.5 | N37: 110.5 | O37: 112.1 | P37: 117.4 | Q37: 118.4 | R37: 114 | S37: 115.2 | T37: 112.7 | U37: 114.8 | V37: 110.7 | W37: 111.9 | X37: 111.7 | Y37: 109.7 | Z37: 109.8 | AA37: 109 | AB37: 111.5 | AC37: 107.9 | AD37: 110 | AE37: 114.5 | AF37: =SUM(E37:R37) -> 1621.3 | AG37: =SUM(S37:U37) -> 342.7 | AH37: =SUM(V37:X37) -> 334.3 | AI37: =SUM(Y37,AC37) -> 217.6 | AJ37: =SUM(Z37) -> 109.8 | AK37: =SUM(AA37) -> 109 | AL37: =SUM(AB37) -> 111.5
A38: Rural | B38: 2014 | C38: January | D38: =B38 & " - " & C38 -> 2014 - January | E38: 118.9 | F38: 117.1 | G38: 120.5 | H38: 114.4 | I38: 109 | J38: 115.5 | K38: 123.9 | L38: 109.6 | M38: 101.8 | N38: 110.2 | O38: 112.4 | P38: 117.3 | Q38: 116 | R38: 114 | S38: 116.5 | T38: 114.5 | U38: 116.2 | V38: NA | W38: 113 | X38: 112.6 | Y38: 110.6 | Z38: 110.5 | AA38: 109.6 | AB38: 111.8 | AC38: 108.3 | AD38: 110.6 | AE38: 114.2 | AF38: =SUM(E38:R38) -> 1600.6 | AG38: =SUM(S38:U38) -> 347.2 | AH38: =SUM(V38:X38) -> 225.6 | AI38: =SUM(Y38,AC38) -> 218.9 | AJ38: =SUM(Z38) -> 110.5 | AK38: =SUM(AA38) -> 109.6 | AL38: =SUM(AB38) -> 111.8
A39: Urban | B39: 2014 | C39: January | D39: =B39 & " - " & C39 -> 2014 - January | E39: 121.2 | F39: 122 | G39: 129.9 | H39: 113.6 | I39: 102.9 | J39: 112.1 | K39: 118.9 | L39: 107.5 | M39: 96.9 | N39: 112.7 | O39: 112.1 | P39: 119 | Q39: 115.5 | R39: 115.7 | S39: 114.8 | T39: 111.3 | U39: 114.3 | V39: 111.6 | W39: 111 | X39: 111.9 | Y39: 109.7 | Z39: 110.8 | AA39: 109.8 | AB39: 111.5 | AC39: 108 | AD39: 110.5 | AE39: 112.9 | AF39: =SUM(E39:R39) -> 1600 | AG39: =SUM(S39:U39) -> 340.4 | AH39: =SUM(V39:X39) -> 334.5 | AI39: =SUM(Y39,AC39) -> 217.7 | AJ39: =SUM(Z39) -> 110.8 | AK39: =SUM(AA39) -> 109.8 | AL39: =SUM(AB39) -> 111.5
A40: Rural+Urban | B40: 2014 | C40: January | D40: =B40 & " - " & C40 -> 2014 - January | E40: 119.6 | F40: 118.8 | G40: 124.1 | H40: 114.1 | I40: 106.8 | J40: 113.9 | K40: 122.2 | L40: 108.9 | M40: 100.2 | N40: 111 | O40: 112.3 | P40: 118.1 | Q40: 115.8 | R40: 114.5 | S40: 115.8 | T40: 113.2 | U40: 115.4 | V40: 111.6 | W40: 112.2 | X40: 112.3 | Y40: 110.3 | Z40: 110.7 | AA40: 109.7 | AB40: 111.6 | AC40: 108.2 | AD40: 110.6 | AE40: 113.6 | AF40: =SUM(E40:R40) -> 1600.3 | AG40: =SUM(S40:U40) -> 344.4 | AH40: =SUM(V40:X40) -> 336.1 | AI40: =SUM(Y40,AC40) -> 218.5 | AJ40: =SUM(Z40) -> 110.7 | AK40: =SUM(AA40) -> 109.7 | AL40: =SUM(AB40) -> 111.6
A41: Rural | B41: 2014 | C41: February | D41: =B41 & " - " & C41 -> 2014 - February | E41: 119.4 | F41: 117.7 | G41: 121.2 | H41: 115 | I41: 109 | J41: 116.6 | K41: 116 | L41: 109.8 | M41: 101.1 | N41: 110.4 | O41: 112.9 | P41: 117.8 | Q41: 115.3 | R41: 114.2 | S41: 117.1 | T41: 114.5 | U41: 116.7 | V41: NA | W41: 113.2 | X41: 112.9 | Y41: 110.9 | Z41: 110.8 | AA41: 109.9 | AB41: 112 | AC41: 108.7 | AD41: 110.9 | AE41: 114 | AF41: =SUM(E41:R41) -> 1596.4 | AG41: =SUM(S41:U41) -> 348.3 | AH41: =SUM(V41:X41) -> 226.1 | AI41: =SUM(Y41,AC41) -> 219.6 | AJ41: =SUM(Z41) -> 110.8 | AK41: =SUM(AA41) -> 109.9 | AL41: =SUM(AB41) -> 112
A42: Urban | B42: 2014 | C42: February | D42: =B42 & " - " & C42 -> 2014 - February | E42: 121.9 | F42: 122 | G42: 124.5 | H42: 115.2 | I42: 102.5 | J42: 114.1 | K42: 111.5 | L42: 108.2 | M42: 95.4 | N42: 113.5 | O42: 112.1 | P42: 119.9 | Q42: 115.2 | R42: 116.2 | S42: 115.3 | T42: 111.7 | U42: 114.7 | V42: 112.5 | W42: 111.1 | X42: 112.6 | Y42: 110.4 | Z42: 111.3 | AA42: 110.3 | AB42: 111.6 | AC42: 108.7 | AD42: 111 | AE42: 113.1 | AF42: =SUM(E42:R42) -> 1592.2 | AG42: =SUM(S42:U42) -> 341.7 | AH42: =SUM(V42:X42) -> 336.2 | AI42: =SUM(Y42,AC42) -> 219.1 | AJ42: =SUM(Z42) -> 111.3 | AK42: =SUM(AA42) -> 110.3 | AL42: =SUM(AB42) -> 111.6
A43: Rural+Urban | B43: 2014 | C43: February | D43: =B43 & " - " & C43 -> 2014 - February | E43: 120.2 | F43: 119.2 | G43: 122.5 | H43: 115.1 | I43: 106.6 | J43: 115.4 | K43: 114.5 | L43: 109.3 | M43: 99.2 | N43: 111.4 | O43: 112.6 | P43: 118.8 | Q43: 115.3 | R43: 114.7 | S43: 116.4 | T43: 113.3 | U43: 115.9 | V43: 112.5 | W43: 112.4 | X43: 112.8 | Y43: 110.7 | Z43: 111.1 | AA43: 110.1 | AB43: 111.8 | AC43: 108.7 | AD43: 110.9 | AE43: 113.6 | AF43: =SUM(E43:R43) -> 1594.8 | AG43: =SUM(S43:U43) -> 345.6 | AH43: =SUM(V43:X43) -> 337.7 | AI43: =SUM(Y43,AC43) -> 219.4 | AJ43: =SUM(Z43) -> 111.1 | AK43: =SUM(AA43) -> 110.1 | AL43: =SUM(AB43) -> 111.8
A44: Rural | B44: 2014 | C44: March | D44: =B44 & " - " & C44 -> 2014 - March | E44: 120.1 | F44: 118.1 | G44: 120.7 | H44: 116.1 | I44: 109.3 | J44: 119.6 | K44: 117.9 | L44: 110.2 | M44: 101.2 | N44: 110.7 | O44: 113 | P44: 118.3 | Q44: 116.2 | R44: 114.6 | S44: 117.5 | T44: 114.9 | U44: 117.2 | V44: NA | W44: 113.4 | X44: 113.4 | Y44: 111.4 | Z44: 111.2 | AA44: 110.2 | AB44: 112.4 | AC44: 108.9 | AD44: 111.3 | AE44: 114.6 | AF44: =SUM(E44:R44) -> 1606 | AG44: =SUM(S44:U44) -> 349.6 | AH44: =SUM(V44:X44) -> 226.8 | AI44: =SUM(Y44,AC44) -> 220.3 | AJ44: =SUM(Z44) -> 111.2 | AK44: =SUM(AA44) -> 110.2 | AL44: =SUM(AB44) -> 112.4
A45: Urban | B45: 2014 | C45: March | D45: =B45 & " - " & C45 -> 2014 - March | E45: 122.1 | F45: 121.4 | G45: 121.5 | H45: 116.2 | I45: 102.8 | J45: 117.7 | K45: 113.3 | L45: 108.9 | M45: 96.3 | N45: 114.1 | O45: 112.2 | P45: 120.5 | Q45: 116 | R45: 116.7 | S45: 115.8 | T45: 112.1 | U45: 115.2 | V45: 113.2 | W45: 110.9 | X45: 113 | Y45: 110.8 | Z45: 111.6 | AA45: 110.9 | AB45: 111.8 | AC45: 109.2 | AD45: 111.4 | AE45: 113.7 | AF45: =SUM(E45:R45) -> 1599.7 | AG45: =SUM(S45:U45) -> 343.1 | AH45: =SUM(V45:X45) -> 337.1 | AI45: =SUM(Y45,AC45) -> 220 | AJ45: =SUM(Z45) -> 111.6 | AK45: =SUM(AA45) -> 110.9 | AL45: =SUM(AB45) -> 111.8
A46: Rural+Urban | B46: 2014 | C46: Marcrh | D46: =B46 & " - " & C46 -> 2014 - Marcrh | E46: 120.7 | F46: 119.3 | G46: 121 | H46: 116.1 | I46: 106.9 | J46: 118.7 | K46: 116.3 | L46: 109.8 | M46: 99.6 | N46: 111.8 | O46: 112.7 | P46: 119.3 | Q46: 116.1 | R46: 115.2 | S46: 116.8 | T46: 113.7 | U46: 116.4 | V46: 113.2 | W46: 112.5 | X46: 113.2 | Y46: 111.2 | Z46: 111.4 | AA46: 110.6 | AB46: 112 | AC46: 109 | AD46: 111.3 | AE46: 114.2 | AF46: =SUM(E46:R46) -> 1603.5 | AG46: =SUM(S46:U46) -> 346.9 | AH46: =SUM(V46:X46) -> 338.9 | AI46: =SUM(Y46,AC46) -> 220.2 | AJ46: =SUM(Z46) -> 111.4 | AK46: =SUM(AA46) -> 110.6 | AL46: =SUM(AB46) -> 112
A47: Rural | B47: 2014 | C47: April | D47: =B47 & " - " & C47 -> 2014 - April | E47: 120.2 | F47: 118.9 | G47: 118.1 | H47: 117 | I47: 109.7 | J47: 125.5 | K47: 120.5 | L47: 111 | M47: 102.6 | N47: 111.2 | O47: 113.5 | P47: 118.7 | Q47: 117.2 | R47: 115.4 | S47: 118.1 | T47: 116.1 | U47: 117.8 | V47: NA | W47: 113.4 | X47: 113.7 | Y47: 111.8 | Z47: 111.2 | AA47: 110.5 | AB47: 113 | AC47: 108.9 | AD47: 111.5 | AE47: 115.4 | AF47: =SUM(E47:R47) -> 1619.5 | AG47: =SUM(S47:U47) -> 352 | AH47: =SUM(V47:X47) -> 227.1 | AI47: =SUM(Y47,AC47) -> 220.7 | AJ47: =SUM(Z47) -> 111.2 | AK47: =SUM(AA47) -> 110.5 | AL47: =SUM(AB47) -> 113
A48: Urban | B48: 2014 | C48: April | D48: =B48 & " - " & C48 -> 2014 - April | E48: 122.5 | F48: 121.7 | G48: 113.3 | H48: 117 | I48: 103.1 | J48: 126.7 | K48: 121.2 | L48: 111 | M48: 100.3 | N48: 115.3 | O48: 112.7 | P48: 121 | Q48: 118.2 | R48: 117.6 | S48: 116.3 | T48: 112.5 | U48: 115.7 | V48: 113.9 | W48: 110.9 | X48: 113.4 | Y48: 111 | Z48: 111.2 | AA48: 111.2 | AB48: 112.5 | AC48: 109.1 | AD48: 111.4 | AE48: 114.7 | AF48: =SUM(E48:R48) -> 1621.6 | AG48: =SUM(S48:U48) -> 344.5 | AH48: =SUM(V48:X48) -> 338.2 | AI48: =SUM(Y48,AC48) -> 220.1 | AJ48: =SUM(Z48) -> 111.2 | AK48: =SUM(AA48) -> 111.2 | AL48: =SUM(AB48) -> 112.5
A49: Rural+Urban | B49: 2014 | C49: April | D49: =B49 & " - " & C49 -> 2014 - April | E49: 120.9 | F49: 119.9 | G49: 116.2 | H49: 117 | I49: 107.3 | J49: 126.1 | K49: 120.7 | L49: 111 | M49: 101.8 | N49: 112.6 | O49: 113.2 | P49: 119.8 | Q49: 117.6 | R49: 116 | S49: 117.4 | T49: 114.6 | U49: 117 | V49: 113.9 | W49: 112.5 | X49: 113.6 | Y49: 111.5 | Z49: 111.2 | AA49: 110.9 | AB49: 112.7 | AC49: 109 | AD49: 111.5 | AE49: 115.1 | AF49: =SUM(E49:R49) -> 1620.1 | AG49: =SUM(S49:U49) -> 349 | AH49: =SUM(V49:X49) -> 340 | AI49: =SUM(Y49,AC49) -> 220.5 | AJ49: =SUM(Z49) -> 111.2 | AK49: =SUM(AA49) -> 110.9 | AL49: =SUM(AB49) -> 112.7
A50: Rural | B50: 2014 | C50: May | D50: =B50 & " - " & C50 -> 2014 - May | E50: 120.3 | F50: 120.2 | G50: 116.9 | H50: 118 | I50: 110.1 | J50: 126.3 | K50: 123.9 | L50: 111.5 | M50: 103.5 | N50: 111.6 | O50: 114.2 | P50: 119.2 | Q50: 118.2 | R50: 116.3 | S50: 118.7 | T50: 116.8 | U50: 118.5 | V50: NA | W50: 113.4 | X50: 114.1 | Y50: 112.1 | Z50: 111.4 | AA50: 110.9 | AB50: 113.1 | AC50: 108.9 | AD50: 111.8 | AE50: 116 | AF50: =SUM(E50:R50) -> 1630.2 | AG50: =SUM(S50:U50) -> 354 | AH50: =SUM(V50:X50) -> 227.5 | AI50: =SUM(Y50,AC50) -> 221 | AJ50: =SUM(Z50) -> 111.4 | AK50: =SUM(AA50) -> 110.9 | AL50: =SUM(AB50) -> 113.1
A51: Urban | B51: 2014 | C51: May | D51: =B51 & " - " & C51 -> 2014 - May | E51: 122.7 | F51: 124.1 | G51: 114.2 | H51: 119.1 | I51: 103.5 | J51: 129.2 | K51: 127 | L51: 112.6 | M51: 101.3 | N51: 117 | O51: 112.9 | P51: 121.7 | Q51: 120 | R51: 118.3 | S51: 116.8 | T51: 112.9 | U51: 116.2 | V51: 114.3 | W51: 111.1 | X51: 114.1 | Y51: 111.2 | Z51: 111.3 | AA51: 111.5 | AB51: 112.9 | AC51: 109.3 | AD51: 111.7 | AE51: 115.6 | AF51: =SUM(E51:R51) -> 1643.6 | AG51: =SUM(S51:U51) -> 345.9 | AH51: =SUM(V51:X51) -> 339.5 | AI51: =SUM(Y51,AC51) -> 220.5 | AJ51: =SUM(Z51) -> 111.3 | AK51: =SUM(AA51) -> 111.5 | AL51: =SUM(AB51) -> 112.9
A52: Rural+Urban | B52: 2014 | C52: May | D52: =B52 & " - " & C52 -> 2014 - May | E52: 121.1 | F52: 121.6 | G52: 115.9 | H52: 118.4 | I52: 107.7 | J52: 127.7 | K52: 125 | L52: 111.9 | M52: 102.8 | N52: 113.4 | O52: 113.7 | P52: 120.4 | Q52: 118.9 | R52: 116.8 | S52: 118 | T52: 115.2 | U52: 117.6 | V52: 114.3 | W52: 112.5 | X52: 114.1 | Y52: 111.8 | Z52: 111.3 | AA52: 111.2 | AB52: 113 | AC52: 109.1 | AD52: 111.8 | AE52: 115.8 | AF52: =SUM(E52:R52) -> 1635.3 | AG52: =SUM(S52:U52) -> 350.8 | AH52: =SUM(V52:X52) -> 340.9 | AI52: =SUM(Y52,AC52) -> 220.9 | AJ52: =SUM(Z52) -> 111.3 | AK52: =SUM(AA52) -> 111.2 | AL52: =SUM(AB52) -> 113
A53: Rural | B53: 2014 | C53: June | D53: =B53 & " - " & C53 -> 2014 - June | E53: 120.7 | F53: 121.6 | G53: 116.1 | H53: 119.3 | I53: 110.3 | J53: 125.8 | K53: 129.3 | L53: 112.2 | M53: 103.6 | N53: 112.3 | O53: 114.9 | P53: 120.1 | Q53: 119.5 | R53: 117.3 | S53: 119.7 | T53: 117.3 | U53: 119.3 | V53: NA | W53: 114.4 | X53: 114.9 | Y53: 112.8 | Z53: 112.2 | AA53: 111.4 | AB53: 114.3 | AC53: 108 | AD53: 112.3 | AE53: 117 | AF53: =SUM(E53:R53) -> 1643 | AG53: =SUM(S53:U53) -> 356.3 | AH53: =SUM(V53:X53) -> 229.3 | AI53: =SUM(Y53,AC53) -> 220.8 | AJ53: =SUM(Z53) -> 112.2 | AK53: =SUM(AA53) -> 111.4 | AL53: =SUM(AB53) -> 114.3
A54: Urban | B54: 2014 | C54: June | D54: =B54 & " - " & C54 -> 2014 - June | E54: 123.1 | F54: 125.9 | G54: 115.4 | H54: 120.4 | I54: 103.4 | J54: 131.2 | K54: 137.5 | L54: 112.8 | M54: 101.4 | N54: 118.3 | O54: 113.2 | P54: 122.4 | Q54: 122 | R54: 119 | S54: 117.4 | T54: 113.2 | U54: 116.7 | V54: 113.9 | W54: 111.2 | X54: 114.3 | Y54: 111.4 | Z54: 111.5 | AA54: 111.8 | AB54: 115.1 | AC54: 108.7 | AD54: 112.2 | AE54: 116.4 | AF54: =SUM(E54:R54) -> 1666 | AG54: =SUM(S54:U54) -> 347.3 | AH54: =SUM(V54:X54) -> 339.4 | AI54: =SUM(Y54,AC54) -> 220.1 | AJ54: =SUM(Z54) -> 111.5 | AK54: =SUM(AA54) -> 111.8 | AL54: =SUM(AB54) -> 115.1
A55: Rural+Urban | B55: 2014 | C55: June | D55: =B55 & " - " & C55 -> 2014 - June | E55: 121.5 | F55: 123.1 | G55: 115.8 | H55: 119.7 | I55: 107.8 | J55: 128.3 | K55: 132.1 | L55: 112.4 | M55: 102.9 | N55: 114.3 | O55: 114.2 | P55: 121.2 | Q55: 120.4 | R55: 117.8 | S55: 118.8 | T55: 115.6 | U55: 118.3 | V55: 113.9 | W55: 113.2 | X55: 114.6 | Y55: 112.3 | Z55: 111.8 | AA55: 111.6 | AB55: 114.8 | AC55: 108.3 | AD55: 112.3 | AE55: 116.7 | AF55: =SUM(E55:R55) -> 1651.5 | AG55: =SUM(S55:U55) -> 352.7 | AH55: =SUM(V55:X55) -> 341.7 | AI55: =SUM(Y55,AC55) -> 220.6 | AJ55: =SUM(Z55) -> 111.8 | AK55: =SUM(AA55) -> 111.6 | AL55: =SUM(AB55) -> 114.8
A56: Rural | B56: 2014 | C56: July | D56: =B56 & " - " & C56 -> 2014 - July | E56: 121.7 | F56: 122.5 | G56: 117.7 | H56: 120.6 | I56: 110.4 | J56: 129.1 | K56: 150.1 | L56: 113.2 | M56: 104.8 | N56: 113.3 | O56: 115.6 | P56: 120.9 | Q56: 123.3 | R56: 118 | S56: 120.7 | T56: 118.3 | U56: 120.3 | V56: NA | W56: 115.3 | X56: 115.4 | Y56: 113.4 | Z56: 113.2 | AA56: 111.8 | AB56: 115.5 | AC56: 108.8 | AD56: 113.1 | AE56: 119.5 | AF56: =SUM(E56:R56) -> 1681.2 | AG56: =SUM(S56:U56) -> 359.3 | AH56: =SUM(V56:X56) -> 230.7 | AI56: =SUM(Y56,AC56) -> 222.2 | AJ56: =SUM(Z56) -> 113.2 | AK56: =SUM(AA56) -> 111.8 | AL56: =SUM(AB56) -> 115.5
A57: Urban | B57: 2014 | C57: July | D57: =B57 & " - " & C57 -> 2014 - July | E57: 123.8 | F57: 126.4 | G57: 118 | H57: 121.6 | I57: 103.5 | J57: 133.7 | K57: 172.4 | L57: 113.1 | M57: 102.7 | N57: 120 | O57: 113.8 | P57: 123.4 | Q57: 127.1 | R57: 121 | S57: 118 | T57: 113.6 | U57: 117.4 | V57: 114.8 | W57: 111.6 | X57: 114.9 | Y57: 111.5 | Z57: 113 | AA57: 112.4 | AB57: 117.8 | AC57: 109.7 | AD57: 113.5 | AE57: 118.9 | AF57: =SUM(E57:R57) -> 1720.5 | AG57: =SUM(S57:U57) -> 349 | AH57: =SUM(V57:X57) -> 341.3 | AI57: =SUM(Y57,AC57) -> 221.2 | AJ57: =SUM(Z57) -> 113 | AK57: =SUM(AA57) -> 112.4 | AL57: =SUM(AB57) -> 117.8
A58: Rural+Urban | B58: 2014 | C58: July | D58: =B58 & " - " & C58 -> 2014 - July | E58: 122.4 | F58: 123.9 | G58: 117.8 | H58: 121 | I58: 107.9 | J58: 131.2 | K58: 157.7 | L58: 113.2 | M58: 104.1 | N58: 115.5 | O58: 114.8 | P58: 122.1 | Q58: 124.7 | R58: 118.8 | S58: 119.6 | T58: 116.3 | U58: 119.1 | V58: 114.8 | W58: 113.9 | X58: 115.2 | Y58: 112.7 | Z58: 113.1 | AA58: 112.1 | AB58: 116.8 | AC58: 109.2 | AD58: 113.3 | AE58: 119.2 | AF58: =SUM(E58:R58) -> 1695.1 | AG58: =SUM(S58:U58) -> 355 | AH58: =SUM(V58:X58) -> 343.9 | AI58: =SUM(Y58,AC58) -> 221.9 | AJ58: =SUM(Z58) -> 113.1 | AK58: =SUM(AA58) -> 112.1 | AL58: =SUM(AB58) -> 116.8
A59: Rural | B59: 2014 | C59: August | D59: =B59 & " - " & C59 -> 2014 - August | E59: 121.8 | F59: 122.8 | G59: 117.8 | H59: 121.9 | I59: 110.6 | J59: 129.7 | K59: 161.1 | L59: 114.1 | M59: 105.1 | N59: 114.6 | O59: 115.8 | P59: 121.7 | Q59: 125.3 | R59: 118.8 | S59: 120.9 | T59: 118.8 | U59: 120.7 | V59: NA | W59: 115.4 | X59: 115.9 | Y59: 114 | Z59: 113.2 | AA59: 112.2 | AB59: 116.2 | AC59: 109.4 | AD59: 113.5 | AE59: 120.7 | AF59: =SUM(E59:R59) -> 1701.1 | AG59: =SUM(S59:U59) -> 360.4 | AH59: =SUM(V59:X59) -> 231.3 | AI59: =SUM(Y59,AC59) -> 223.4 | AJ59: =SUM(Z59) -> 113.2 | AK59: =SUM(AA59) -> 112.2 | AL59: =SUM(AB59) -> 116.2
A60: Urban | B60: 2014 | C60: August | D60: =B60 & " - " & C60 -> 2014 - August | E60: 124.8 | F60: 127.3 | G60: 116.5 | H60: 122.2 | I60: 103.6 | J60: 132.7 | K60: 181.9 | L60: 115.2 | M60: 102.7 | N60: 122.1 | O60: 114.4 | P60: 124.7 | Q60: 128.9 | R60: 123 | S60: 118.6 | T60: 114.1 | U60: 117.9 | V60: 115.5 | W60: 111.8 | X60: 115.3 | Y60: 112.2 | Z60: 112.5 | AA60: 112.9 | AB60: 119.2 | AC60: 110.5 | AD60: 113.9 | AE60: 119.9 | AF60: =SUM(E60:R60) -> 1740 | AG60: =SUM(S60:U60) -> 350.6 | AH60: =SUM(V60:X60) -> 342.6 | AI60: =SUM(Y60,AC60) -> 222.7 | AJ60: =SUM(Z60) -> 112.5 | AK60: =SUM(AA60) -> 112.9 | AL60: =SUM(AB60) -> 119.2
A61: Rural+Urban | B61: 2014 | C61: August | D61: =B61 & " - " & C61 -> 2014 - August | E61: 122.7 | F61: 124.4 | G61: 117.3 | H61: 122 | I61: 108 | J61: 131.1 | K61: 168.2 | L61: 114.5 | M61: 104.3 | N61: 117.1 | O61: 115.2 | P61: 123.1 | Q61: 126.6 | R61: 119.9 | S61: 120 | T61: 116.8 | U61: 119.6 | V61: 115.5 | W61: 114 | X61: 115.6 | Y61: 113.3 | Z61: 112.8 | AA61: 112.6 | AB61: 118 | AC61: 109.9 | AD61: 113.7 | AE61: 120.3 | AF61: =SUM(E61:R61) -> 1714.4 | AG61: =SUM(S61:U61) -> 356.4 | AH61: =SUM(V61:X61) -> 345.1 | AI61: =SUM(Y61,AC61) -> 223.2 | AJ61: =SUM(Z61) -> 112.8 | AK61: =SUM(AA61) -> 112.6 | AL61: =SUM(AB61) -> 118
A62: Rural | B62: 2014 | C62: September | D62: =B62 & " - " & C62 -> 2014 - September | E62: 122.3 | F62: 122.4 | G62: 117.8 | H62: 122.7 | I62: 110.4 | J62: 129.8 | K62: 158.8 | L62: 115 | M62: 104.7 | N62: 114.9 | O62: 116.5 | P62: 122.6 | Q62: 125.3 | R62: 119.5 | S62: 121.7 | T62: 119.2 | U62: 121.3 | V62: NA | W62: 115.8 | X62: 116.7 | Y62: 114.5 | Z62: 112.8 | AA62: 112.6 | AB62: 116.6 | AC62: 109.1 | AD62: 113.7 | AE62: 120.9 | AF62: =SUM(E62:R62) -> 1702.7 | AG62: =SUM(S62:U62) -> 362.2 | AH62: =SUM(V62:X62) -> 232.5 | AI62: =SUM(Y62,AC62) -> 223.6 | AJ62: =SUM(Z62) -> 112.8 | AK62: =SUM(AA62) -> 112.6 | AL62: =SUM(AB62) -> 116.6
A63: Urban | B63: 2014 | C63: September | D63: =B63 & " - " & C63 -> 2014 - September | E63: 124.2 | F63: 125.4 | G63: 116.4 | H63: 122.7 | I63: 103.5 | J63: 124.5 | K63: 168.6 | L63: 116.9 | M63: 101.9 | N63: 122.9 | O63: 114.8 | P63: 125.2 | Q63: 126.7 | R63: 124.3 | S63: 119.2 | T63: 114.5 | U63: 118.4 | V63: 116.1 | W63: 111.8 | X63: 115.5 | Y63: 112.3 | Z63: 111.2 | AA63: 113.4 | AB63: 120 | AC63: 110 | AD63: 113.6 | AE63: 119.2 | AF63: =SUM(E63:R63) -> 1718 | AG63: =SUM(S63:U63) -> 352.1 | AH63: =SUM(V63:X63) -> 343.4 | AI63: =SUM(Y63,AC63) -> 222.3 | AJ63: =SUM(Z63) -> 111.2 | AK63: =SUM(AA63) -> 113.4 | AL63: =SUM(AB63) -> 120
A64: Rural+Urban | B64: 2014 | C64: September | D64: =B64 & " - " & C64 -> 2014 - September | E64: 122.9 | F64: 123.5 | G64: 117.3 | H64: 122.7 | I64: 107.9 | J64: 127.3 | K64: 162.1 | L64: 115.6 | M64: 103.8 | N64: 117.6 | O64: 115.8 | P64: 123.8 | Q64: 125.8 | R64: 120.8 | S64: 120.7 | T64: 117.2 | U64: 120.1 | V64: 116.1 | W64: 114.3 | X64: 116.1 | Y64: 113.7 | Z64: 112 | AA64: 113.1 | AB64: 118.6 | AC64: 109.5 | AD64: 113.7 | AE64: 120.1 | AF64: =SUM(E64:R64) -> 1706.9 | AG64: =SUM(S64:U64) -> 358 | AH64: =SUM(V64:X64) -> 346.5 | AI64: =SUM(Y64,AC64) -> 223.2 | AJ64: =SUM(Z64) -> 112 | AK64: =SUM(AA64) -> 113.1 | AL64: =SUM(AB64) -> 118.6
A65: Rural | B65: 2014 | C65: October | D65: =B65 & " - " & C65 -> 2014 - October | E65: 122.6 | F65: 122.5 | G65: 118.3 | H65: 123.2 | I65: 110.5 | J65: 128.9 | K65: 155.3 | L65: 115.5 | M65: 104 | N65: 115.3 | O65: 116.8 | P65: 123.2 | Q65: 125.1 | R65: 120 | S65: 122.7 | T65: 120.3 | U65: 122.3 | V65: NA | W65: 116.4 | X65: 117.5 | Y65: 115.3 | Z65: 112.6 | AA65: 113 | AB65: 116.9 | AC65: 109.3 | AD65: 114 | AE65: 121 | AF65: =SUM(E65:R65) -> 1701.2 | AG65: =SUM(S65:U65) -> 365.3 | AH65: =SUM(V65:X65) -> 233.9 | AI65: =SUM(Y65,AC65) -> 224.6 | AJ65: =SUM(Z65) -> 112.6 | AK65: =SUM(AA65) -> 113 | AL65: =SUM(AB65) -> 116.9
A66: Urban | B66: 2014 | C66: October | D66: =B66 & " - " & C66 -> 2014 - October | E66: 124.6 | F66: 126.1 | G66: 117.8 | H66: 123.1 | I66: 103.5 | J66: 123.5 | K66: 159.6 | L66: 117.4 | M66: 101.2 | N66: 123.8 | O66: 115.2 | P66: 125.9 | Q66: 125.8 | R66: 124.3 | S66: 119.6 | T66: 114.9 | U66: 118.9 | V66: 116.7 | W66: 112 | X66: 115.8 | Y66: 112.6 | Z66: 111 | AA66: 113.6 | AB66: 120.2 | AC66: 110.1 | AD66: 113.7 | AE66: 119.1 | AF66: =SUM(E66:R66) -> 1711.8 | AG66: =SUM(S66:U66) -> 353.4 | AH66: =SUM(V66:X66) -> 344.5 | AI66: =SUM(Y66,AC66) -> 222.7 | AJ66: =SUM(Z66) -> 111 | AK66: =SUM(AA66) -> 113.6 | AL66: =SUM(AB66) -> 120.2
A67: Rural+Urban | B67: 2014 | C67: October | D67: =B67 & " - " & C67 -> 2014 - October | E67: 123.2 | F67: 123.8 | G67: 118.1 | H67: 123.2 | I67: 107.9 | J67: 126.4 | K67: 156.8 | L67: 116.1 | M67: 103.1 | N67: 118.1 | O67: 116.1 | P67: 124.5 | Q67: 125.4 | R67: 121.1 | S67: 121.5 | T67: 118.1 | U67: 121 | V67: 116.7 | W67: 114.7 | X67: 116.7 | Y67: 114.3 | Z67: 111.8 | AA67: 113.3 | AB67: 118.8 | AC67: 109.6 | AD67: 113.9 | AE67: 120.1 | AF67: =SUM(E67:R67) -> 1703.8 | AG67: =SUM(S67:U67) -> 360.6 | AH67: =SUM(V67:X67) -> 348.1 | AI67: =SUM(Y67,AC67) -> 223.9 | AJ67: =SUM(Z67) -> 111.8 | AK67: =SUM(AA67) -> 113.3 | AL67: =SUM(AB67) -> 118.8
A68: Rural | B68: 2014 | C68: November | D68: =B68 & " - " & C68 -> 2014 - November | E68: 122.7 | F68: 122.6 | G68: 119.9 | H68: 124 | I68: 110.5 | J68: 128.8 | K68: 152 | L68: 116.2 | M68: 103.3 | N68: 115.8 | O68: 116.8 | P68: 124.5 | Q68: 124.9 | R68: 120.8 | S68: 123.3 | T68: 120.5 | U68: 122.9 | V68: NA | W68: 117.3 | X68: 118.1 | Y68: 115.9 | Z68: 112 | AA68: 113.3 | AB68: 117.2 | AC68: 108.8 | AD68: 114.1 | AE68: 121.1 | AF68: =SUM(E68:R68) -> 1702.8 | AG68: =SUM(S68:U68) -> 366.7 | AH68: =SUM(V68:X68) -> 235.4 | AI68: =SUM(Y68,AC68) -> 224.7 | AJ68: =SUM(Z68) -> 112 | AK68: =SUM(AA68) -> 113.3 | AL68: =SUM(AB68) -> 117.2
A69: Urban | B69: 2014 | C69: November | D69: =B69 & " - " & C69 -> 2014 - November | E69: 124.5 | F69: 125.6 | G69: 122.7 | H69: 124.6 | I69: 103.2 | J69: 122.2 | K69: 153.2 | L69: 119.3 | M69: 99.8 | N69: 124.6 | O69: 115.8 | P69: 126.9 | Q69: 125.4 | R69: 125.8 | S69: 120.3 | T69: 115.4 | U69: 119.5 | V69: 117.1 | W69: 112.6 | X69: 116.4 | Y69: 113 | Z69: 109.7 | AA69: 114 | AB69: 120.3 | AC69: 109.6 | AD69: 113.4 | AE69: 119 | AF69: =SUM(E69:R69) -> 1713.6 | AG69: =SUM(S69:U69) -> 355.2 | AH69: =SUM(V69:X69) -> 346.1 | AI69: =SUM(Y69,AC69) -> 222.6 | AJ69: =SUM(Z69) -> 109.7 | AK69: =SUM(AA69) -> 114 | AL69: =SUM(AB69) -> 120.3
A70: Rural+Urban | B70: 2014 | C70: November | D70: =B70 & " - " & C70 -> 2014 - November | E70: 123.3 | F70: 123.7 | G70: 121 | H70: 124.2 | I70: 107.8 | J70: 125.7 | K70: 152.4 | L70: 117.2 | M70: 102.1 | N70: 118.7 | O70: 116.4 | P70: 125.6 | Q70: 125.1 | R70: 122.1 | S70: 122.1 | T70: 118.4 | U70: 121.6 | V70: 117.1 | W70: 115.5 | X70: 117.3 | Y70: 114.8 | Z70: 110.8 | AA70: 113.7 | AB70: 119 | AC70: 109.1 | AD70: 113.8 | AE70: 120.1 | AF70: =SUM(E70:R70) -> 1705.3 | AG70: =SUM(S70:U70) -> 362.1 | AH70: =SUM(V70:X70) -> 349.9 | AI70: =SUM(Y70,AC70) -> 223.9 | AJ70: =SUM(Z70) -> 110.8 | AK70: =SUM(AA70) -> 113.7 | AL70: =SUM(AB70) -> 119
A71: Rural | B71: 2014 | C71: December | D71: =B71 & " - " & C71 -> 2014 - December | E71: 122.4 | F71: 122.4 | G71: 121.8 | H71: 124.2 | I71: 110.2 | J71: 128.6 | K71: 140.3 | L71: 116.3 | M71: 102 | N71: 116 | O71: 117.3 | P71: 124.8 | Q71: 123.3 | R71: 121.7 | S71: 123.8 | T71: 120.6 | U71: 123.3 | V71: NA | W71: 117.4 | X71: 118.2 | Y71: 116.2 | Z71: 111.5 | AA71: 113.3 | AB71: 117.7 | AC71: 109.4 | AD71: 114.2 | AE71: 120.3 | AF71: =SUM(E71:R71) -> 1691.3 | AG71: =SUM(S71:U71) -> 367.7 | AH71: =SUM(V71:X71) -> 235.6 | AI71: =SUM(Y71,AC71) -> 225.6 | AJ71: =SUM(Z71) -> 111.5 | AK71: =SUM(AA71) -> 113.3 | AL71: =SUM(AB71) -> 117.7
A72: Urban | B72: 2014 | C72: December | D72: =B72 & " - " & C72 -> 2014 - December | E72: 124 | F72: 124.7 | G72: 126.3 | H72: 124.9 | I72: 103 | J72: 122.3 | K72: 141 | L72: 120.1 | M72: 97.8 | N72: 125.4 | O72: 116.1 | P72: 127.6 | Q72: 124 | R72: 126.4 | S72: 120.7 | T72: 115.8 | U72: 120 | V72: 116.5 | W72: 113 | X72: 116.8 | Y72: 113.2 | Z72: 108.8 | AA72: 114.3 | AB72: 120.7 | AC72: 110.4 | AD72: 113.4 | AE72: 118.4 | AF72: =SUM(E72:R72) -> 1703.6 | AG72: =SUM(S72:U72) -> 356.5 | AH72: =SUM(V72:X72) -> 346.3 | AI72: =SUM(Y72,AC72) -> 223.6 | AJ72: =SUM(Z72) -> 108.8 | AK72: =SUM(AA72) -> 114.3 | AL72: =SUM(AB72) -> 120.7
A73: Rural+Urban | B73: 2014 | C73: December | D73: =B73 & " - " & C73 -> 2014 - December | E73: 122.9 | F73: 123.2 | G73: 123.5 | H73: 124.5 | I73: 107.6 | J73: 125.7 | K73: 140.5 | L73: 117.6 | M73: 100.6 | N73: 119.1 | O73: 116.8 | P73: 126.1 | Q73: 123.6 | R73: 123 | S73: 122.6 | T73: 118.6 | U73: 122 | V73: 116.5 | W73: 115.7 | X73: 117.5 | Y73: 115.1 | Z73: 110.1 | AA73: 113.9 | AB73: 119.5 | AC73: 109.8 | AD73: 113.8 | AE73: 119.4 | AF73: =SUM(E73:R73) -> 1694.7 | AG73: =SUM(S73:U73) -> 363.2 | AH73: =SUM(V73:X73) -> 349.7 | AI73: =SUM(Y73,AC73) -> 224.9 | AJ73: =SUM(Z73) -> 110.1 | AK73: =SUM(AA73) -> 113.9 | AL73: =SUM(AB73) -> 119.5
A74: Rural | B74: 2015 | C74: January | D74: =B74 & " - " & C74 -> 2015 - January | E74: 123.1 | F74: 123.1 | G74: 122.1 | H74: 124.9 | I74: 111 | J74: 130.4 | K74: 132.3 | L74: 117.2 | M74: 100.5 | N74: 117.2 | O74: 117.9 | P74: 125.6 | Q74: 122.8 | R74: 122.7 | S74: 124.4 | T74: 121.6 | U74: 124 | V74: NA | W74: 118.4 | X74: 118.9 | Y74: 116.6 | Z74: 111 | AA74: 114 | AB74: 118.2 | AC74: 110.2 | AD74: 114.5 | AE74: 120.3 | AF74: =SUM(E74:R74) -> 1690.8 | AG74: =SUM(S74:U74) -> 370 | AH74: =SUM(V74:X74) -> 237.3 | AI74: =SUM(Y74,AC74) -> 226.8 | AJ74: =SUM(Z74) -> 111 | AK74: =SUM(AA74) -> 114 | AL74: =SUM(AB74) -> 118.2
A75: Urban | B75: 2015 | C75: January | D75: =B75 & " - " & C75 -> 2015 - January | E75: 124 | F75: 125.5 | G75: 126.6 | H75: 125.2 | I75: 104.3 | J75: 121.3 | K75: 134.4 | L75: 122.9 | M75: 96.1 | N75: 126.6 | O75: 116.5 | P75: 128 | Q75: 123.5 | R75: 127.4 | S75: 121 | T75: 116.1 | U75: 120.2 | V75: 117.3 | W75: 113.4 | X75: 117.2 | Y75: 113.7 | Z75: 107.9 | AA75: 114.6 | AB75: 120.8 | AC75: 111.4 | AD75: 113.4 | AE75: 118.5 | AF75: =SUM(E75:R75) -> 1702.3 | AG75: =SUM(S75:U75) -> 357.3 | AH75: =SUM(V75:X75) -> 347.9 | AI75: =SUM(Y75,AC75) -> 225.1 | AJ75: =SUM(Z75) -> 107.9 | AK75: =SUM(AA75) -> 114.6 | AL75: =SUM(AB75) -> 120.8
A76: Rural+Urban | B76: 2015 | C76: January | D76: =B76 & " - " & C76 -> 2015 - January | E76: 123.4 | F76: 123.9 | G76: 123.8 | H76: 125 | I76: 108.5 | J76: 126.2 | K76: 133 | L76: 119.1 | M76: 99 | N76: 120.3 | O76: 117.3 | P76: 126.7 | Q76: 123.1 | R76: 124 | S76: 123.1 | T76: 119.3 | U76: 122.5 | V76: 117.3 | W76: 116.5 | X76: 118.1 | Y76: 115.5 | Z76: 109.4 | AA76: 114.3 | AB76: 119.7 | AC76: 110.7 | AD76: 114 | AE76: 119.5 | AF76: =SUM(E76:R76) -> 1693.3 | AG76: =SUM(S76:U76) -> 364.9 | AH76: =SUM(V76:X76) -> 351.9 | AI76: =SUM(Y76,AC76) -> 226.2 | AJ76: =SUM(Z76) -> 109.4 | AK76: =SUM(AA76) -> 114.3 | AL76: =SUM(AB76) -> 119.7
A77: Rural | B77: 2015 | C77: February | D77: =B77 & " - " & C77 -> 2015 - February | E77: 123.4 | F77: 124.4 | G77: 122.1 | H77: 125.8 | I77: 111.5 | J77: 129.4 | K77: 128.2 | L77: 118.8 | M77: 100 | N77: 118.6 | O77: 118.8 | P77: 126.8 | Q77: 122.8 | R77: 124.2 | S77: 125.4 | T77: 122.7 | U77: 125 | V77: NA | W77: 120 | X77: 119.6 | Y77: 117.7 | Z77: 110.9 | AA77: 114.8 | AB77: 118.7 | AC77: 110.8 | AD77: 115 | AE77: 120.6 | AF77: =SUM(E77:R77) -> 1694.8 | AG77: =SUM(S77:U77) -> 373.1 | AH77: =SUM(V77:X77) -> 239.6 | AI77: =SUM(Y77,AC77) -> 228.5 | AJ77: =SUM(Z77) -> 110.9 | AK77: =SUM(AA77) -> 114.8 | AL77: =SUM(AB77) -> 118.7
A78: Urban | B78: 2015 | C78: February | D78: =B78 & " - " & C78 -> 2015 - February | E78: 124.3 | F78: 126.5 | G78: 119.5 | H78: 125.6 | I78: 104.9 | J78: 121.6 | K78: 131.8 | L78: 125.1 | M78: 95 | N78: 127.7 | O78: 116.8 | P78: 128.6 | Q78: 123.7 | R78: 128.1 | S78: 121.3 | T78: 116.5 | U78: 120.6 | V78: 118.1 | W78: 114 | X78: 117.7 | Y78: 114.1 | Z78: 106.8 | AA78: 114.9 | AB78: 120.4 | AC78: 111.7 | AD78: 113.2 | AE78: 118.7 | AF78: =SUM(E78:R78) -> 1699.2 | AG78: =SUM(S78:U78) -> 358.4 | AH78: =SUM(V78:X78) -> 349.8 | AI78: =SUM(Y78,AC78) -> 225.8 | AJ78: =SUM(Z78) -> 106.8 | AK78: =SUM(AA78) -> 114.9 | AL78: =SUM(AB78) -> 120.4
A79: Rural+Urban | B79: 2015 | C79: February | D79: =B79 & " - " & C79 -> 2015 - February | E79: 123.7 | F79: 125.1 | G79: 121.1 | H79: 125.7 | I79: 109.1 | J79: 125.8 | K79: 129.4 | L79: 120.9 | M79: 98.3 | N79: 121.6 | O79: 118 | P79: 127.6 | Q79: 123.1 | R79: 125.2 | S79: 123.8 | T79: 120.1 | U79: 123.3 | V79: 118.1 | W79: 117.7 | X79: 118.7 | Y79: 116.3 | Z79: 108.7 | AA79: 114.9 | AB79: 119.7 | AC79: 111.2 | AD79: 114.1 | AE79: 119.7 | AF79: =SUM(E79:R79) -> 1694.6 | AG79: =SUM(S79:U79) -> 367.2 | AH79: =SUM(V79:X79) -> 354.5 | AI79: =SUM(Y79,AC79) -> 227.5 | AJ79: =SUM(Z79) -> 108.7 | AK79: =SUM(AA79) -> 114.9 | AL79: =SUM(AB79) -> 119.7
A80: Rural | B80: 2015 | C80: March | D80: =B80 & " - " & C80 -> 2015 - March | E80: 123.3 | F80: 124.7 | G80: 118.9 | H80: 126 | I80: 111.8 | J80: 130.9 | K80: 128 | L80: 119.9 | M80: 98.9 | N80: 119.4 | O80: 118.9 | P80: 127.7 | Q80: 123.1 | R80: 124.7 | S80: 126 | T80: 122.9 | U80: 125.5 | V80: NA | W80: 120.6 | X80: 120.2 | Y80: 118.2 | Z80: 111.6 | AA80: 115.5 | AB80: 119.4 | AC80: 110.8 | AD80: 115.5 | AE80: 121.1 | AF80: =SUM(E80:R80) -> 1696.2 | AG80: =SUM(S80:U80) -> 374.4 | AH80: =SUM(V80:X80) -> 240.8 | AI80: =SUM(Y80,AC80) -> 229 | AJ80: =SUM(Z80) -> 111.6 | AK80: =SUM(AA80) -> 115.5 | AL80: =SUM(AB80) -> 119.4
A81: Urban | B81: 2015 | C81: March | D81: =B81 & " - " & C81 -> 2015 - March | E81: 124 | F81: 126.7 | G81: 113.5 | H81: 125.9 | I81: 104.8 | J81: 123.8 | K81: 131.4 | L81: 127.2 | M81: 93.2 | N81: 127.4 | O81: 117 | P81: 129.2 | Q81: 123.9 | R81: 128.8 | S81: 121.7 | T81: 116.9 | U81: 120.9 | V81: 118.6 | W81: 114.4 | X81: 118 | Y81: 114.3 | Z81: 108.4 | AA81: 115.4 | AB81: 120.6 | AC81: 111.3 | AD81: 113.8 | AE81: 119.1 | AF81: =SUM(E81:R81) -> 1696.8 | AG81: =SUM(S81:U81) -> 359.5 | AH81: =SUM(V81:X81) -> 351 | AI81: =SUM(Y81,AC81) -> 225.6 | AJ81: =SUM(Z81) -> 108.4 | AK81: =SUM(AA81) -> 115.4 | AL81: =SUM(AB81) -> 120.6
A82: Rural+Urban | B82: 2015 | C82: March | D82: =B82 & " - " & C82 -> 2015 - March | E82: 123.5 | F82: 125.4 | G82: 116.8 | H82: 126 | I82: 109.2 | J82: 127.6 | K82: 129.2 | L82: 122.4 | M82: 97 | N82: 122.1 | O82: 118.1 | P82: 128.4 | Q82: 123.4 | R82: 125.8 | S82: 124.3 | T82: 120.4 | U82: 123.7 | V82: 118.6 | W82: 118.3 | X82: 119.2 | Y82: 116.7 | Z82: 109.9 | AA82: 115.4 | AB82: 120.1 | AC82: 111 | AD82: 114.7 | AE82: 120.2 | AF82: =SUM(E82:R82) -> 1694.9 | AG82: =SUM(S82:U82) -> 368.4 | AH82: =SUM(V82:X82) -> 356.1 | AI82: =SUM(Y82,AC82) -> 227.7 | AJ82: =SUM(Z82) -> 109.9 | AK82: =SUM(AA82) -> 115.4 | AL82: =SUM(AB82) -> 120.1
A83: Rural | B83: 2015 | C83: April | D83: =B83 & " - " & C83 -> 2015 - April | E83: 123.3 | F83: 125.5 | G83: 117.2 | H83: 126.8 | I83: 111.9 | J83: 134.2 | K83: 127.5 | L83: 121.5 | M83: 97.8 | N83: 119.8 | O83: 119.4 | P83: 128.7 | Q83: 123.6 | R83: 125.7 | S83: 126.4 | T83: 123.3 | U83: 126 | V83: NA | W83: 121.2 | X83: 120.9 | Y83: 118.6 | Z83: 111.9 | AA83: 116.2 | AB83: 119.9 | AC83: 111.6 | AD83: 116 | AE83: 121.5 | AF83: =SUM(E83:R83) -> 1702.9 | AG83: =SUM(S83:U83) -> 375.7 | AH83: =SUM(V83:X83) -> 242.1 | AI83: =SUM(Y83,AC83) -> 230.2 | AJ83: =SUM(Z83) -> 111.9 | AK83: =SUM(AA83) -> 116.2 | AL83: =SUM(AB83) -> 119.9
A84: Urban | B84: 2015 | C84: April | D84: =B84 & " - " & C84 -> 2015 - April | E84: 123.8 | F84: 128.2 | G84: 110 | H84: 126.3 | I84: 104.5 | J84: 130.6 | K84: 130.8 | L84: 131.3 | M84: 91.6 | N84: 127.7 | O84: 117.2 | P84: 129.5 | Q84: 124.6 | R84: 130.1 | S84: 122.1 | T84: 117.2 | U84: 121.3 | V84: 119.2 | W84: 114.7 | X84: 118.4 | Y84: 114.6 | Z84: 108.4 | AA84: 115.6 | AB84: 121.7 | AC84: 111.8 | AD84: 114.2 | AE84: 119.7 | AF84: =SUM(E84:R84) -> 1706.2 | AG84: =SUM(S84:U84) -> 360.6 | AH84: =SUM(V84:X84) -> 352.3 | AI84: =SUM(Y84,AC84) -> 226.4 | AJ84: =SUM(Z84) -> 108.4 | AK84: =SUM(AA84) -> 115.6 | AL84: =SUM(AB84) -> 121.7
A85: Rural+Urban | B85: 2015 | C85: April | D85: =B85 & " - " & C85 -> 2015 - April | E85: 123.5 | F85: 126.4 | G85: 114.4 | H85: 126.6 | I85: 109.2 | J85: 132.5 | K85: 128.6 | L85: 124.8 | M85: 95.7 | N85: 122.4 | O85: 118.5 | P85: 129.1 | Q85: 124 | R85: 126.9 | S85: 124.7 | T85: 120.8 | U85: 124.1 | V85: 119.2 | W85: 118.7 | X85: 119.7 | Y85: 117.1 | Z85: 110.1 | AA85: 115.9 | AB85: 121 | AC85: 111.7 | AD85: 115.1 | AE85: 120.7 | AF85: =SUM(E85:R85) -> 1702.6 | AG85: =SUM(S85:U85) -> 369.6 | AH85: =SUM(V85:X85) -> 357.6 | AI85: =SUM(Y85,AC85) -> 228.8 | AJ85: =SUM(Z85) -> 110.1 | AK85: =SUM(AA85) -> 115.9 | AL85: =SUM(AB85) -> 121
A86: Rural | B86: 2015 | C86: May | D86: =B86 & " - " & C86 -> 2015 - May | E86: 123.5 | F86: 127.1 | G86: 117.3 | H86: 127.7 | I86: 112.5 | J86: 134.1 | K86: 128.5 | L86: 124.3 | M86: 97.6 | N86: 120.7 | O86: 120.2 | P86: 129.8 | Q86: 124.4 | R86: 126.7 | S86: 127.3 | T86: 124.1 | U86: 126.8 | V86: NA | W86: 121.9 | X86: 121.5 | Y86: 119.4 | Z86: 113.3 | AA86: 116.7 | AB86: 120.5 | AC86: 112.3 | AD86: 116.9 | AE86: 122.4 | AF86: =SUM(E86:R86) -> 1714.4 | AG86: =SUM(S86:U86) -> 378.2 | AH86: =SUM(V86:X86) -> 243.4 | AI86: =SUM(Y86,AC86) -> 231.7 | AJ86: =SUM(Z86) -> 113.3 | AK86: =SUM(AA86) -> 116.7 | AL86: =SUM(AB86) -> 120.5
A87: Urban | B87: 2015 | C87: May | D87: =B87 & " - " & C87 -> 2015 - May | E87: 123.8 | F87: 129.7 | G87: 111.3 | H87: 126.6 | I87: 105.2 | J87: 130.8 | K87: 135.6 | L87: 142.6 | M87: 90.8 | N87: 128.8 | O87: 117.7 | P87: 129.9 | Q87: 126.1 | R87: 131.3 | S87: 122.4 | T87: 117.4 | U87: 121.6 | V87: 119.6 | W87: 114.9 | X87: 118.7 | Y87: 114.9 | Z87: 110.8 | AA87: 116 | AB87: 122 | AC87: 112.4 | AD87: 115.2 | AE87: 120.7 | AF87: =SUM(E87:R87) -> 1730.2 | AG87: =SUM(S87:U87) -> 361.4 | AH87: =SUM(V87:X87) -> 353.2 | AI87: =SUM(Y87,AC87) -> 227.3 | AJ87: =SUM(Z87) -> 110.8 | AK87: =SUM(AA87) -> 116 | AL87: =SUM(AB87) -> 122
A88: Rural+Urban | B88: 2015 | C88: May | D88: =B88 & " - " & C88 -> 2015 - May | E88: 123.6 | F88: 128 | G88: 115 | H88: 127.3 | I88: 109.8 | J88: 132.6 | K88: 130.9 | L88: 130.5 | M88: 95.3 | N88: 123.4 | O88: 119.2 | P88: 129.8 | Q88: 125 | R88: 127.9 | S88: 125.4 | T88: 121.3 | U88: 124.7 | V88: 119.6 | W88: 119.2 | X88: 120.2 | Y88: 117.7 | Z88: 112 | AA88: 116.3 | AB88: 121.4 | AC88: 112.3 | AD88: 116.1 | AE88: 121.6 | AF88: =SUM(E88:R88) -> 1718.3 | AG88: =SUM(S88:U88) -> 371.4 | AH88: =SUM(V88:X88) -> 359 | AI88: =SUM(Y88,AC88) -> 230 | AJ88: =SUM(Z88) -> 112 | AK88: =SUM(AA88) -> 116.3 | AL88: =SUM(AB88) -> 121.4
A89: Rural | B89: 2015 | C89: June | D89: =B89 & " - " & C89 -> 2015 - June | E89: 124.1 | F89: 130.4 | G89: 122.1 | H89: 128.7 | I89: 114.1 | J89: 133.2 | K89: 135.2 | L89: 131.9 | M89: 96.3 | N89: 123 | O89: 121.1 | P89: 131.2 | Q89: 126.6 | R89: 128.2 | S89: 128.4 | T89: 125.1 | U89: 128 | V89: NA | W89: 122.6 | X89: 122.8 | Y89: 120.4 | Z89: 114.2 | AA89: 117.9 | AB89: 122 | AC89: 113 | AD89: 117.9 | AE89: 124.1 | AF89: =SUM(E89:R89) -> 1746.1 | AG89: =SUM(S89:U89) -> 381.5 | AH89: =SUM(V89:X89) -> 245.4 | AI89: =SUM(Y89,AC89) -> 233.4 | AJ89: =SUM(Z89) -> 114.2 | AK89: =SUM(AA89) -> 117.9 | AL89: =SUM(AB89) -> 122
A90: Urban | B90: 2015 | C90: June | D90: =B90 & " - " & C90 -> 2015 - June | E90: 123.6 | F90: 134.4 | G90: 120.9 | H90: 127.3 | I90: 106 | J90: 132.3 | K90: 146.7 | L90: 148.1 | M90: 89.8 | N90: 130.5 | O90: 118 | P90: 130.5 | Q90: 128.5 | R90: 132.1 | S90: 123.2 | T90: 117.6 | U90: 122.3 | V90: 119 | W90: 115.1 | X90: 119.2 | Y90: 115.4 | Z90: 111.7 | AA90: 116.2 | AB90: 123.8 | AC90: 112.5 | AD90: 116 | AE90: 121.7 | AF90: =SUM(E90:R90) -> 1768.7 | AG90: =SUM(S90:U90) -> 363.1 | AH90: =SUM(V90:X90) -> 353.3 | AI90: =SUM(Y90,AC90) -> 227.9 | AJ90: =SUM(Z90) -> 111.7 | AK90: =SUM(AA90) -> 116.2 | AL90: =SUM(AB90) -> 123.8
A91: Rural+Urban | B91: 2015 | C91: June | D91: =B91 & " - " & C91 -> 2015 - June | E91: 123.9 | F91: 131.8 | G91: 121.6 | H91: 128.2 | I91: 111.1 | J91: 132.8 | K91: 139.1 | L91: 137.4 | M91: 94.1 | N91: 125.5 | O91: 119.8 | P91: 130.9 | Q91: 127.3 | R91: 129.2 | S91: 126.4 | T91: 122 | U91: 125.7 | V91: 119 | W91: 119.8 | X91: 121.1 | Y91: 118.5 | Z91: 112.9 | AA91: 116.9 | AB91: 123.1 | AC91: 112.8 | AD91: 117 | AE91: 123 | AF91: =SUM(E91:R91) -> 1752.7 | AG91: =SUM(S91:U91) -> 374.1 | AH91: =SUM(V91:X91) -> 359.9 | AI91: =SUM(Y91,AC91) -> 231.3 | AJ91: =SUM(Z91) -> 112.9 | AK91: =SUM(AA91) -> 116.9 | AL91: =SUM(AB91) -> 123.1
A92: Rural | B92: 2015 | C92: July | D92: =B92 & " - " & C92 -> 2015 - July | E92: 124 | F92: 131.5 | G92: 122 | H92: 128.7 | I92: 113.5 | J92: 133.3 | K92: 140.8 | L92: 133.8 | M92: 94.1 | N92: 123.4 | O92: 121 | P92: 131.7 | Q92: 127.5 | R92: 129.4 | S92: 128.8 | T92: 125.5 | U92: 128.3 | V92: NA | W92: 123 | X92: 123 | Y92: 120.8 | Z92: 114.1 | AA92: 118 | AB92: 122.9 | AC92: 112.7 | AD92: 118.1 | AE92: 124.7 | AF92: =SUM(E92:R92) -> 1754.7 | AG92: =SUM(S92:U92) -> 382.6 | AH92: =SUM(V92:X92) -> 246 | AI92: =SUM(Y92,AC92) -> 233.5 | AJ92: =SUM(Z92) -> 114.1 | AK92: =SUM(AA92) -> 118 | AL92: =SUM(AB92) -> 122.9
A93: Urban | B93: 2015 | C93: July | D93: =B93 & " - " & C93 -> 2015 - July | E93: 123.2 | F93: 134.3 | G93: 119.5 | H93: 127.7 | I93: 106.3 | J93: 132.8 | K93: 153.5 | L93: 149.5 | M93: 85.7 | N93: 131.5 | O93: 118.3 | P93: 131.1 | Q93: 129.5 | R93: 133.1 | S93: 123.5 | T93: 117.9 | U93: 122.7 | V93: 119.9 | W93: 115.3 | X93: 119.5 | Y93: 116 | Z93: 111.5 | AA93: 116.6 | AB93: 125.4 | AC93: 111.7 | AD93: 116.3 | AE93: 122.4 | AF93: =SUM(E93:R93) -> 1776 | AG93: =SUM(S93:U93) -> 364.1 | AH93: =SUM(V93:X93) -> 354.7 | AI93: =SUM(Y93,AC93) -> 227.7 | AJ93: =SUM(Z93) -> 111.5 | AK93: =SUM(AA93) -> 116.6 | AL93: =SUM(AB93) -> 125.4
A94: Rural+Urban | B94: 2015 | C94: July | D94: =B94 & " - " & C94 -> 2015 - July | E94: 123.7 | F94: 132.5 | G94: 121 | H94: 128.3 | I94: 110.9 | J94: 133.1 | K94: 145.1 | L94: 139.1 | M94: 91.3 | N94: 126.1 | O94: 119.9 | P94: 131.4 | Q94: 128.2 | R94: 130.4 | S94: 126.7 | T94: 122.3 | U94: 126.1 | V94: 119.9 | W94: 120.1 | X94: 121.3 | Y94: 119 | Z94: 112.7 | AA94: 117.2 | AB94: 124.4 | AC94: 112.3 | AD94: 117.2 | AE94: 123.6 | AF94: =SUM(E94:R94) -> 1761 | AG94: =SUM(S94:U94) -> 375.1 | AH94: =SUM(V94:X94) -> 361.3 | AI94: =SUM(Y94,AC94) -> 231.3 | AJ94: =SUM(Z94) -> 112.7 | AK94: =SUM(AA94) -> 117.2 | AL94: =SUM(AB94) -> 124.4
A95: Rural | B95: 2015 | C95: August | D95: =B95 & " - " & C95 -> 2015 - August | E95: 124.7 | F95: 131.3 | G95: 121.3 | H95: 128.8 | I95: 114 | J95: 134.2 | K95: 153.6 | L95: 137.9 | M95: 93.1 | N95: 123.9 | O95: 121.5 | P95: 132.5 | Q95: 129.8 | R95: 130.1 | S95: 129.5 | T95: 126.3 | U95: 129 | V95: NA | W95: 123.8 | X95: 123.7 | Y95: 121.1 | Z95: 113.6 | AA95: 118.5 | AB95: 123.6 | AC95: 112.5 | AD95: 118.2 | AE95: 126.1 | AF95: =SUM(E95:R95) -> 1776.7 | AG95: =SUM(S95:U95) -> 384.8 | AH95: =SUM(V95:X95) -> 247.5 | AI95: =SUM(Y95,AC95) -> 233.6 | AJ95: =SUM(Z95) -> 113.6 | AK95: =SUM(AA95) -> 118.5 | AL95: =SUM(AB95) -> 123.6
A96: Urban | B96: 2015 | C96: August | D96: =B96 & " - " & C96 -> 2015 - August | E96: 123.1 | F96: 131.7 | G96: 118.1 | H96: 128 | I96: 106.8 | J96: 130.1 | K96: 165.5 | L96: 156 | M96: 85.3 | N96: 132.7 | O96: 118.8 | P96: 131.7 | Q96: 131.1 | R96: 134.2 | S96: 123.7 | T96: 118.2 | U96: 122.9 | V96: 120.9 | W96: 115.3 | X96: 120 | Y96: 116.6 | Z96: 109.9 | AA96: 117.2 | AB96: 126.2 | AC96: 112 | AD96: 116.2 | AE96: 123.2 | AF96: =SUM(E96:R96) -> 1793.1 | AG96: =SUM(S96:U96) -> 364.8 | AH96: =SUM(V96:X96) -> 356.2 | AI96: =SUM(Y96,AC96) -> 228.6 | AJ96: =SUM(Z96) -> 109.9 | AK96: =SUM(AA96) -> 117.2 | AL96: =SUM(AB96) -> 126.2
A97: Rural+Urban | B97: 2015 | C97: August | D97: =B97 & " - " & C97 -> 2015 - August | E97: 124.2 | F97: 131.4 | G97: 120.1 | H97: 128.5 | I97: 111.4 | J97: 132.3 | K97: 157.6 | L97: 144 | M97: 90.5 | N97: 126.8 | O97: 120.4 | P97: 132.1 | Q97: 130.3 | R97: 131.2 | S97: 127.2 | T97: 122.9 | U97: 126.6 | V97: 120.9 | W97: 120.6 | X97: 122 | Y97: 119.4 | Z97: 111.7 | AA97: 117.8 | AB97: 125.1 | AC97: 112.3 | AD97: 117.2 | AE97: 124.8 | AF97: =SUM(E97:R97) -> 1780.8 | AG97: =SUM(S97:U97) -> 376.7 | AH97: =SUM(V97:X97) -> 363.5 | AI97: =SUM(Y97,AC97) -> 231.7 | AJ97: =SUM(Z97) -> 111.7 | AK97: =SUM(AA97) -> 117.8 | AL97: =SUM(AB97) -> 125.1
A98: Rural | B98: 2015 | C98: September | D98: =B98 & " - " & C98 -> 2015 - September | E98: 125.1 | F98: 131.1 | G98: 120.7 | H98: 129.2 | I98: 114.7 | J98: 132.3 | K98: 158.9 | L98: 142.1 | M98: 92.5 | N98: 125.4 | O98: 121.9 | P98: 132.7 | Q98: 131 | R98: 131 | S98: 130.4 | T98: 126.8 | U98: 129.9 | V98: NA | W98: 123.7 | X98: 124.5 | Y98: 121.4 | Z98: 113.8 | AA98: 119.6 | AB98: 124.5 | AC98: 113.7 | AD98: 118.8 | AE98: 127 | AF98: =SUM(E98:R98) -> 1788.6 | AG98: =SUM(S98:U98) -> 387.1 | AH98: =SUM(V98:X98) -> 248.2 | AI98: =SUM(Y98,AC98) -> 235.1 | AJ98: =SUM(Z98) -> 113.8 | AK98: =SUM(AA98) -> 119.6 | AL98: =SUM(AB98) -> 124.5
A99: Urban | B99: 2015 | C99: September | D99: =B99 & " - " & C99 -> 2015 - September | E99: 123.4 | F99: 129 | G99: 115.6 | H99: 128.3 | I99: 107 | J99: 124 | K99: 168.5 | L99: 165.4 | M99: 86.3 | N99: 134.4 | O99: 119.1 | P99: 132.3 | Q99: 131.5 | R99: 134.7 | S99: 124 | T99: 118.6 | U99: 123.2 | V99: 121.6 | W99: 115.1 | X99: 120.4 | Y99: 117.1 | Z99: 109.1 | AA99: 117.3 | AB99: 126.5 | AC99: 112.9 | AD99: 116.2 | AE99: 123.5 | AF99: =SUM(E99:R99) -> 1799.5 | AG99: =SUM(S99:U99) -> 365.8 | AH99: =SUM(V99:X99) -> 357.1 | AI99: =SUM(Y99,AC99) -> 230 | AJ99: =SUM(Z99) -> 109.1 | AK99: =SUM(AA99) -> 117.3 | AL99: =SUM(AB99) -> 126.5
A100: Rural+Urban | B100: 2015 | C100: September | D100: =B100 & " - " & C100 -> 2015 - September | E100: 124.6 | F100: 130.4 | G100: 118.7 | H100: 128.9 | I100: 111.9 | J100: 128.4 | K100: 162.2 | L100: 150 | M100: 90.4 | N100: 128.4 | O100: 120.7 | P100: 132.5 | Q100: 131.2 | R100: 132 | S100: 127.9 | T100: 123.4 | U100: 127.2 | V100: 121.6 | W100: 120.4 | X100: 122.6 | Y100: 119.8 | Z100: 111.3 | AA100: 118.3 | AB100: 125.7 | AC100: 113.4 | AD100: 117.5 | AE100: 125.4 | AF100: =SUM(E100:R100) -> 1790.3 | AG100: =SUM(S100:U100) -> 378.5 | AH100: =SUM(V100:X100) -> 364.6 | AI100: =SUM(Y100,AC100) -> 233.2 | AJ100: =SUM(Z100) -> 111.3 | AK100: =SUM(AA100) -> 118.3 | AL100: =SUM(AB100) -> 125.7
...

Sheet Transpose
D1: 2013 | E1: 2013 | F1: 2013 | G1: 2013 | H1: 2013 | I1: 2013 | J1: 2013 | K1: 2013 | L1: 2013 | M1: 2013 | N1: 2013 | O1: 2013 | P1: 2014 | Q1: 2014 | R1: 2014 | S1: 2014 | T1: 2014 | U1: 2014 | V1: 2014 | W1: 2014 | X1: 2014 | Y1: 2014 | Z1: 2014 | AA1: 2014 | AB1: 2015 | AC1: 2015 | AD1: 2015 | AE1: 2015 | AF1: 2015 | AG1: 2015 | AH1: 2015 | AI1: 2015 | AJ1: 2015 | AK1: 2015 | AL1: 2015 | AM1: 2015 | AN1: 2016 | AO1: 2016 | AP1: 2016 | AQ1: 2016 | AR1: 2016 | AS1: 2016 | AT1: 2016 | AU1: 2016 | AV1: 2016 | AW1: 2016 | AX1: 2016 | AY1: 2016 | AZ1: 2017 | BA1: 2017 | BB1: 2017 | BC1: 2017 | BD1: 2017 | BE1: 2017 | BF1: 2017 | BG1: 2017 | BH1: 2017 | BI1: 2017 | BJ1: 2017 | BK1: 2017 | BL1: 2018 | BM1: 2018 | BN1: 2018 | BO1: 2018 | BP1: 2018 | BQ1: 2018 | BR1: 2018 | BS1: 2018 | BT1: 2018 | BU1: 2018 | BV1: 2018 | BW1: 2018 | BX1: 2019 | BY1: 2019 | BZ1: 2019 | CA1: 2019 | CB1: 2019 | CC1: 2019 | CD1: 2019 | CE1: 2019 | CF1: 2019 | CG1: 2019 | CH1: 2019 | CI1: 2020 | CJ1: 2020 | CK1: 2020 | CL1: 2020 | CM1: 2020 | CN1: 2020 | CO1: 2020 | CP1: 2020 | CQ1: 2020 | CR1: 2020 | CS1: 2020 | CT1: 2020 | CU1: 2021 | CV1: 2021 | CW1: 2021 | CX1: 2021 | CY1: 2021 | CZ1: 2021 | DA1: 2021 | DB1: 2021 | DC1: 2021 | DD1: 2021 | DE1: 2021 | DF1: 2021 | DG1: 2022 | DH1: 2022 | DI1: 2022 | DJ1: 2022 | DK1: 2022 | DL1: 2022 | DM1: 2022 | DN1: 2022 | DO1: 2022 | DP1: 2022 | DQ1: 2022 | DR1: 2022 | DS1: 2023 | DT1: 2023 | DU1: 2023 | DV1: 2023 | DW1: 2023
A2: Sector | B2: Broader Cat | C2: Category | D2: January | E2: February | F2: March | G2: April | H2: May | I2: June | J2: July | K2: August | L2: September | M2: October | N2: November | O2: December | P2: January | Q2: February | R2: March | S2: April | T2: May | U2: June | V2: July | W2: August | X2: September | Y2: October | Z2: November | AA2: December | AB2: January | AC2: February | AD2: March | AE2: April | AF2: May | AG2: June | AH2: July | AI2: August | AJ2: September | AK2: October | AL2: November | AM2: December | AN2: January | AO2: February | AP2: March | AQ2: April | AR2: May | AS2: June | AT2: July | AU2: August | AV2: September | AW2: October | AX2: November | AY2: December | AZ2: January | BA2: February | BB2: March | BC2: April | BD2: May | BE2: June | BF2: July | BG2: August | BH2: September | BI2: October | BJ2: November | BK2: December | BL2: January | BM2: February | BN2: March | BO2: April | BP2: May | BQ2: June | BR2: July | BS2: August | BT2: September | BU2: October | BV2: November | BW2: December | BX2: January | BY2: February | BZ2: March | CA2: May | CB2: June | CC2: July | CD2: August | CE2: September | CF2: October | CG2: November | CH2: December | CI2: January | CJ2: February | CK2: March | CL2: April | CM2: May | CN2: June | CO2: July | CP2: August | CQ2: September | CR2: October | CS2: November | CT2: December | CU2: January | CV2: February | CW2: March | CX2: April | CY2: May | CZ2: June | DA2: July | DB2: August | DC2: September | DD2: October | DE2: November | DF2: December | DG2: January | DH2: February | DI2: March | DJ2: April | DK2: May | DL2: June | DM2: July | DN2: August | DO2: September | DP2: October | DQ2: November | DR2: December | DS2: January | DT2: February | DU2: March | DV2: April | DW2: May
A3: Rural | B3: =VLOOKUP(C3,'Broader Categories'!$A$1:$B$28,2,FALSE) -> Food | C3: Cereals and products | D3: 107.5 | E3: 109.2 | F3: 110.2 | G3: 110.2 | H3: 110.9 | I3: 112.3 | J3: 113.4 | K3: 114.3 | L3: 115.4 | M3: 116.3 | N3: 117.3 | O3: 118.4 | P3: 118.9 | Q3: 119.4 | R3: 120.1 | S3: 120.2 | T3: 120.3 | U3: 120.7 | V3: 121.7 | W3: 121.8 | X3: 122.3 | Y3: 122.6 | Z3: 122.7 | AA3: 122.4 | AB3: 123.1 | AC3: 123.4 | AD3: 123.3 | AE3: 123.3 | AF3: 123.5 | AG3: 124.1 | AH3: 124 | AI3: 124.7 | AJ3: 125.1 | AK3: 125.6 | AL3: 126.1 | AM3: 126.3 | AN3: 126.8 | AO3: 127.1 | AP3: 127.3 | AQ3: 127.4 | AR3: 127.6 | AS3: 128.6 | AT3: 129.3 | AU3: 130.1 | AV3: 130.8 | AW3: 131.3 | AX3: 132 | AY3: 132.6 | AZ3: 133.1 | BA3: 133.3 | BB3: 133.6 | BC3: 133.2 | BD3: 133.1 | BE3: 133.5 | BF3: 134 | BG3: 134.8 | BH3: 135.2 | BI3: 135.9 | BJ3: 136.3 | BK3: 136.4 | BL3: 136.6 | BM3: 136.4 | BN3: 136.8 | BO3: 137.1 | BP3: 137.4 | BQ3: 137.6 | BR3: 138.4 | BS3: 139.2 | BT3: 139.4 | BU3: 139.3 | BV3: 137.1 | BW3: 137.1 | BX3: 136.6 | BY3: 136.8 | BZ3: 136.9 | CA3: 137.4 | CB3: 137.8 | CC3: 138.4 | CD3: 139.2 | CE3: 140.1 | CF3: 141 | CG3: 141.8 | CH3: 142.8 | CI3: 143.7 | CJ3: 144.2 | CK3: 144.4 | CL3: 147.2 | CM3: NA | CN3: 148.2 | CO3: 148.2 | CP3: 147.6 | CQ3: 146.9 | CR3: 146 | CS3: 145.4 | CT3: 144.6 | CU3: 143.4 | CV3: 142.8 | CW3: 142.5 | CX3: 142.7 | CY3: 145.1 | CZ3: 145.6 | DA3: 145.1 | DB3: 144.9 | DC3: 145.4 | DD3: 146.1 | DE3: 146.9 | DF3: 147.4 | DG3: 148.3 | DH3: 148.8 | DI3: 150.2 | DJ3: 151.8 | DK3: 152.9 | DL3: 153.8 | DM3: 155.2 | DN3: 159.5 | DO3: 162.9 | DP3: 164.7 | DQ3: 166.9 | DR3: 168.8 | DS3: 174 | DT3: 174.2 | DU3: 174.3 | DV3: 173.3 | DW3: 173.2
A4: Rural | B4: =VLOOKUP(C4,'Broader Categories'!$A$1:$B$28,2,FALSE) -> Food | C4: Meat and fish | D4: 106.3 | E4: 108.7 | F4: 108.8 | G4: 109.5 | H4: 109.8 | I4: 112.1 | J4: 114.9 | K4: 115.4 | L4: 115.7 | M4: 115.4 | N4: 114.9 | O4: 115.9 | P4: 117.1 | Q4: 117.7 | R4: 118.1 | S4: 118.9 | T4: 120.2 | U4: 121.6 | V4: 122.5 | W4: 122.8 | X4: 122.4 | Y4: 122.5 | Z4: 122.6 | AA4: 122.4 | AB4: 123.1 | AC4: 124.4 | AD4: 124.7 | AE4: 125.5 | AF4: 127.1 | AG4: 130.4 | AH4: 131.5 | AI4: 131.3 | AJ4: 131.1 | AK4: 130.4 | AL4: 130.6 | AM4: 131.3 | AN4: 133.2 | AO4: 133.7 | AP4: 134.4 | AQ4: 135.4 | AR4: 137.5 | AS4: 138.6 | AT4: 139.5 | AU4: 138.8 | AV4: 138.2 | AW4: 137.6 | AX4: 137.4 | AY4: 137.3 | AZ4: 137.8 | BA4: 138.3 | BB4: 138.8 | BC4: 138.7 | BD4: 140.3 | BE4: 143.7 | BF4: 144.2 | BG4: 143.1 | BH4: 142 | BI4: 141.9 | BJ4: 142.5 | BK4: 143.7 | BL4: 144.4 | BM4: 143.7 | BN4: 143.8 | BO4: 144.5 | BP4: 145.7 | BQ4: 148.1 | BR4: 149.3 | BS4: 148.8 | BT4: 147.2 | BU4: 147.6 | BV4: 150.8 | BW4: 151.9 | BX4: 152.5 | BY4: 153 | BZ4: 154.1 | CA4: 159.5 | CB4: 163.5 | CC4: 164 | CD4: 161.9 | CE4: 161.9 | CF4: 161.6 | CG4: 163.7 | CH4: 165.3 | CI4: 167.3 | CJ4: 167.5 | CK4: 166.8 | CL4: NA | CM4: NA | CN4: 190.3 | CO4: 190.3 | CP4: 187.2 | CQ4: 183.9 | CR4: 186.3 | CS4: 188.6 | CT4: 188.5 | CU4: 187.5 | CV4: 184 | CW4: 189.4 | CX4: 195.5 | CY4: 198.5 | CZ4: 200.1 | DA4: 204.5 | DB4: 202.3 | DC4: 202.1 | DD4: 202.5 | DE4: 199.8 | DF4: 197 | DG4: 196.9 | DH4: 198.1 | DI4: 208 | DJ4: 209.7 | DK4: 214.7 | DL4: 217.2 | DM4: 210.8 | DN4: 204.1 | DO4: 206.7 | DP4: 208.8 | DQ4: 207.2 | DR4: 206.9 | DS4: 208.3 | DT4: 205.2 | DU4: 205.2 | DV4: 206.9 | DW4: 211.5
A5: Rural | B5: =VLOOKUP(C5,'Broader Categories'!$A$1:$B$28,2,FALSE) -> Food | C5: Egg | D5: 108.1 | E5: 110.2 | F5: 109.9 | G5: 106.9 | H5: 105.9 | I5: 108.1 | J5: 110.5 | K5: 111.1 | L5: 111.7 | M5: 112.6 | N5: 116.2 | O5: 120.4 | P5: 120.5 | Q5: 121.2 | R5: 120.7 | S5: 118.1 | T5: 116.9 | U5: 116.1 | V5: 117.7 | W5: 117.8 | X5: 117.8 | Y5: 118.3 | Z5: 119.9 | AA5: 121.8 | AB5: 122.1 | AC5: 122.1 | AD5: 118.9 | AE5: 117.2 | AF5: 117.3 | AG5: 122.1 | AH5: 122 | AI5: 121.3 | AJ5: 120.7 | AK5: 120.8 | AL5: 121.7 | AM5: 123.3 | AN5: 126.5 | AO5: 127.7 | AP5: 125.1 | AQ5: 123.4 | AR5: 124.4 | AS5: 126.6 | AT5: 129.6 | AU5: 130.3 | AV5: 130.5 | AW5: 130.1 | AX5: 130.6 | AY5: 131.6 | AZ5: 131.9 | BA5: 129.3 | BB5: 128.8 | BC5: 127.1 | BD5: 126.8 | BE5: 128 | BF5: 129.8 | BG5: 130 | BH5: 130.5 | BI5: 131 | BJ5: 140.5 | BK5: 144.8 | BL5: 143.8 | BM5: 140.6 | BN5: 140 | BO5: 135.9 | BP5: 135.5 | BQ5: 136.7 | BR5: 139.3 | BS5: 139.1 | BT5: 136.6 | BU5: 134.6 | BV5: 136.7 | BW5: 137.4 | BX5: 138.2 | BY5: 139.1 | BZ5: 138.7 | CA5: 134.5 | CB5: 136.2 | CC5: 138.4 | CD5: 137.1 | CE5: 138.3 | CF5: 141.2 | CG5: 143.8 | CH5: 149.5 | CI5: 153.5 | CJ5: 150.9 | CK5: 147.6 | CL5: 146.9 | CM5: NA | CN5: 149.4 | CO5: 149.4 | CP5: 148.4 | CQ5: 149.5 | CR5: 159.2 | CS5: 171.6 | CT5: 173.4 | CU5: 173.4 | CV5: 168 | CW5: 163.2 | CX5: 163.4 | CY5: 168.6 | CZ5: 179.3 | DA5: 180.4 | DB5: 176.5 | DC5: 172 | DD5: 170.1 | DE5: 171.5 | DF5: 176.5 | DG5: 178 | DH5: 175.5 | DI5: 167.9 | DJ5: 164.5 | DK5: 161.4 | DL5: 169.6 | DM5: 174.3 | DN5: 168.3 | DO5: 169 | DP5: 170.3 | DQ5: 180.2 | DR5: 189.1 | DS5: 192.9 | DT5: 173.9 | DU5: 173.9 | DV5: 167.9 | DW5: 171
A6: Rural | B6: =VLOOKUP(C6,'Broader Categories'!$A$1:$B$28,2,FALSE) -> Food | C6: Milk and products | D6: 104.9 | E6: 105.4 | F6: 105.6 | G6: 106.3 | H6: 107.5 | I6: 108.3 | J6: 109.3 | K6: 110 | L6: 111 | M6: 111.7 | N6: 112.8 | O6: 113.8 | P6: 114.4 | Q6: 115 | R6: 116.1 | S6: 117 | T6: 118 | U6: 119.3 | V6: 120.6 | W6: 121.9 | X6: 122.7 | Y6: 123.2 | Z6: 124 | AA6: 124.2 | AB6: 124.9 | AC6: 125.8 | AD6: 126 | AE6: 126.8 | AF6: 127.7 | AG6: 128.7 | AH6: 128.7 | AI6: 128.8 | AJ6: 129.2 | AK6: 129.4 | AL6: 129.5 | AM6: 129.8 | AN6: 130.3 | AO6: 130.7 | AP6: 130.5 | AQ6: 131.3 | AR6: 132.4 | AS6: 133.6 | AT6: 134.5 | AU6: 135.3 | AV6: 135.5 | AW6: 136 | AX6: 136.2 | AY6: 136.3 | AZ6: 136.7 | BA6: 137.2 | BB6: 137.2 | BC6: 137.7 | BD6: 138.2 | BE6: 138.6 | BF6: 139 | BG6: 139.4 | BH6: 140.2 | BI6: 141.5 | BJ6: 141.5 | BK6: 141.9 | BL6: 142 | BM6: 141.5 | BN6: 142 | BO6: 142.4 | BP6: 142.9 | BQ6: 143.2 | BR6: 143.4 | BS6: 143.5 | BT6: 143.7 | BU6: 141.9 | BV6: 141.9 | BW6: 142.4 | BX6: 142.4 | BY6: 142.5 | BZ6: 142.5 | CA6: 142.6 | CB6: 143.2 | CC6: 143.9 | CD6: 144.6 | CE6: 145.7 | CF6: 146.5 | CG6: 147.1 | CH6: 148.7 | CI6: 150.5 | CJ6: 150.9 | CK6: 151.7 | CL6: 155.6 | CM6: NA | CN6: 153.3 | CO6: 153.3 | CP6: 153.3 | CQ6: 153.4 | CR6: 153.6 | CS6: 153.8 | CT6: 154 | CU6: 154 | CV6: 154.4 | CW6: 154.5 | CX6: 155 | CY6: 155.8 | CZ6: 156.1 | DA6: 157.1 | DB6: 157.5 | DC6: 158 | DD6: 158.4 | DE6: 159.1 | DF6: 159.8 | DG6: 160.5 | DH6: 160.7 | DI6: 162 | DJ6: 163.8 | DK6: 164.6 | DL6: 165.4 | DM6: 166.3 | DN6: 167.9 | DO6: 169.5 | DP6: 170.9 | DQ6: 172.3 | DR6: 173.4 | DS6: 174.3 | DT6: 177 | DU6: 177 | DV6: 178.2 | DW6: 179.6
A7: Rural | B7: =VLOOKUP(C7,'Broader Categories'!$A$1:$B$28,2,FALSE) -> Food | C7: Oils and fats | D7: 106.1 | E7: 106.7 | F7: 106.2 | G7: 105.7 | H7: 105.3 | I7: 105.9 | J7: 106.2 | K7: 106.4 | L7: 107.4 | M7: 107.7 | N7: 108.9 | O7: 109.5 | P7: 109 | Q7: 109 | R7: 109.3 | S7: 109.7 | T7: 110.1 | U7: 110.3 | V7: 110.4 | W7: 110.6 | X7: 110.4 | Y7: 110.5 | Z7: 110.5 | AA7: 110.2 | AB7: 111 | AC7: 111.5 | AD7: 111.8 | AE7: 111.9 | AF7: 112.5 | AG7: 114.1 | AH7: 113.5 | AI7: 114 | AJ7: 114.7 | AK7: 115.8 | AL7: 117.8 | AM7: 118.3 | AN7: 118.9 | AO7: 118.5 | AP7: 118.3 | AQ7: 118.2 | AR7: 118.2 | AS7: 118.6 | AT7: 119.5 | AU7: 119.9 | AV7: 120.2 | AW7: 120.8 | AX7: 121.1 | AY7: 121.6 | AZ7: 122 | BA7: 122.1 | BB7: 121.6 | BC7: 121.3 | BD7: 120.8 | BE7: 120.9 | BF7: 120.9 | BG7: 120.5 | BH7: 120.7 | BI7: 121.4 | BJ7: 121.6 | BK7: 123.1 | BL7: 123.2 | BM7: 122.9 | BN7: 123.2 | BO7: 123.5 | BP7: 123.6 | BQ7: 124 | BR7: 124.1 | BS7: 125 | BT7: 124.6 | BU7: 123.5 | BV7: 122.8 | BW7: 124.2 | BX7: 123.9 | BY7: 124.1 | BZ7: 124.1 | CA7: 124 | CB7: 124.3 | CC7: 124.4 | CD7: 124.7 | CE7: 125.1 | CF7: 125.6 | CG7: 126 | CH7: 127.5 | CI7: 132 | CJ7: 133.7 | CK7: 133.3 | CL7: 137.1 | CM7: NA | CN7: 138.2 | CO7: 138.2 | CP7: 139.8 | CQ7: 140.4 | CR7: 142.6 | CS7: 145.4 | CT7: 150 | CU7: 154.8 | CV7: 163 | CW7: 168.2 | CX7: 175.2 | CY7: 184.4 | CZ7: 190.4 | DA7: 188.7 | DB7: 190.9 | DC7: 195.5 | DD7: 198.8 | DE7: 198.4 | DF7: 195.8 | DG7: 192.6 | DH7: 192.6 | DI7: 203.1 | DJ7: 207.4 | DK7: 209.9 | DL7: 208.1 | DM7: 202.2 | DN7: 198.1 | DO7: 194.1 | DP7: 191.6 | DQ7: 194 | DR7: 193.9 | DS7: 192.6 | DT7: 183.4 | DU7: 183.3 | DV7: 178.5 | DW7: 173.3
A8: Rural | B8: =VLOOKUP(C8,'Broader Categories'!$A$1:$B$28,2,FALSE) -> Food | C8: Fruits | D8: 103.9 | E8: 104 | F8: 105.7 | G8: 108.3 | H8: 108.1 | I8: 109.2 | J8: 110.3 | K8: 110.8 | L8: 110.9 | M8: 113.2 | N8: 116.6 | O8: 115.5 | P8: 115.5 | Q8: 116.6 | R8: 119.6 | S8: 125.5 | T8: 126.3 | U8: 125.8 | V8: 129.1 | W8: 129.7 | X8: 129.8 | Y8: 128.9 | Z8: 128.8 | AA8: 128.6 | AB8: 130.4 | AC8: 129.4 | AD8: 130.9 | AE8: 134.2 | AF8: 134.1 | AG8: 133.2 | AH8: 133.3 | AI8: 134.2 | AJ8: 132.3 | AK8: 133.2 | AL8: 132.1 | AM8: 131.6 | AN8: 131.6 | AO8: 130.4 | AP8: 131.7 | AQ8: 138.1 | AR8: 138.1 | AS8: 137.4 | AT8: 138.5 | AU8: 140.2 | AV8: 139.2 | AW8: 138.4 | AX8: 136.9 | AY8: 135.6 | AZ8: 136 | BA8: 138.7 | BB8: 139.7 | BC8: 141.8 | BD8: 140.2 | BE8: 140.9 | BF8: 143.9 | BG8: 148 | BH8: 147.8 | BI8: 146.7 | BJ8: 147.3 | BK8: 147.2 | BL8: 147.9 | BM8: 149.4 | BN8: 152.9 | BO8: 156.4 | BP8: 157.5 | BQ8: 154.1 | BR8: 153.3 | BS8: 154.4 | BT8: 150.1 | BU8: 144.5 | BV8: 143.9 | BW8: 140.2 | BX8: 135.5 | BY8: 135.8 | BZ8: 136.1 | CA8: 143.7 | CB8: 143.3 | CC8: 146.4 | CD8: 145.5 | CE8: 143.8 | CF8: 145.7 | CG8: 146.2 | CH8: 144.3 | CI8: 142.2 | CJ8: 140.7 | CK8: 141.8 | CL8: 147.3 | CM8: NA | CN8: 143.2 | CO8: 143.2 | CP8: 146.9 | CQ8: 147 | CR8: 147.2 | CS8: 146.5 | CT8: 145.9 | CU8: 147 | CV8: 147.8 | CW8: 150.5 | CX8: 160.6 | CY8: 162.3 | CZ8: 158.6 | DA8: 157.7 | DB8: 155.7 | DC8: 152.7 | DD8: 152.6 | DE8: 153.2 | DF8: 152 | DG8: 151.2 | DH8: 151.4 | DI8: 155.9 | DJ8: 169.7 | DK8: 168 | DL8: 165.8 | DM8: 169.6 | DN8: 169.2 | DO8: 164.1 | DP8: 162.2 | DQ8: 159.1 | DR8: 156.7 | DS8: 156.3 | DT8: 167.2 | DU8: 167.2 | DV8: 173.7 | DW8: 169
A9: Rural | B9: =VLOOKUP(C9,'Broader Categories'!$A$1:$B$28,2,FALSE) -> Food | C9: Vegetables | D9: 101.9 | E9: 102.4 | F9: 101.4 | G9: 103.4 | H9: 107.3 | I9: 118 | J9: 129.2 | K9: 138.9 | L9: 154 | M9: 164.9 | N9: 178.1 | O9: 145.7 | P9: 123.9 | Q9: 116 | R9: 117.9 | S9: 120.5 | T9: 123.9 | U9: 129.3 | V9: 150.1 | W9: 161.1 | X9: 158.8 | Y9: 155.3 | Z9: 152 | AA9: 140.3 | AB9: 132.3 | AC9: 128.2 | AD9: 128 | AE9: 127.5 | AF9: 128.5 | AG9: 135.2 | AH9: 140.8 | AI9: 153.6 | AJ9: 158.9 | AK9: 157.7 | AL9: 155.2 | AM9: 145.5 | AN9: 140.1 | AO9: 130.9 | AP9: 130.7 | AQ9: 134.1 | AR9: 141.8 | AS9: 152.5 | AT9: 158.2 | AU9: 156.9 | AV9: 149.5 | AW9: 149.2 | AX9: 141.8 | AY9: 127.5 | AZ9: 119.8 | BA9: 119.1 | BB9: 119.7 | BC9: 121.5 | BD9: 123.8 | BE9: 128.8 | BF9: 151.5 | BG9: 162.9 | BH9: 154.5 | BI9: 157.1 | BJ9: 168 | BK9: 161 | BL9: 152.1 | BM9: 142.4 | BN9: 138 | BO9: 135.1 | BP9: 137.8 | BQ9: 143.5 | BR9: 154.2 | BS9: 156.3 | BT9: 149.4 | BU9: 147.6 | BV9: 147.5 | BW9: 136.6 | BX9: 131.7 | BY9: 128.7 | BZ9: 128.2 | CA9: 133.4 | CB9: 140.6 | CC9: 150.1 | CD9: 156.2 | CE9: 163.4 | CF9: 178.8 | CG9: 191.4 | CH9: 209.5 | CI9: 191.5 | CJ9: 165.1 | CK9: 152.3 | CL9: 162.7 | CM9: NA | CN9: 148.9 | CO9: 148.9 | CP9: 171 | CQ9: 178.8 | CR9: 200.6 | CS9: 222.2 | CT9: 225.2 | CU9: 187.8 | CV9: 149.7 | CW9: 141 | CX9: 135.1 | CY9: 138.4 | CZ9: 144.7 | DA9: 152.8 | DB9: 153.9 | DC9: 151.4 | DD9: 170.4 | DE9: 183.9 | DF9: 172.3 | DG9: 159.2 | DH9: 155.2 | DI9: 155.8 | DJ9: 153.6 | DK9: 160.4 | DL9: 167.3 | DM9: 168.6 | DN9: 173.1 | DO9: 176.9 | DP9: 184.8 | DQ9: 171.6 | DR9: 150.2 | DS9: 142.9 | DT9: 140.9 | DU9: 140.9 | DV9: 142.8 | DW9: 148.7
A10: Rural | B10: =VLOOKUP(C10,'Broader Categories'!$A$1:$B$28,2,FALSE) -> Food | C10: Pulses and products | D10: 106.1 | E10: 105.9 | F10: 105.7 | G10: 105.7 | H10: 106.1 | I10: 106.8 | J10: 107.1 | K10: 107.4 | L10: 108.1 | M10: 108.3 | N10: 109.1 | O10: 109.5 | P10: 109.6 | Q10: 109.8 | R10: 110.2 | S10: 111 | T10: 111.5 | U10: 112.2 | V10: 113.2 | W10: 114.1 | X10: 115 | Y10: 115.5 | Z10: 116.2 | AA10: 116.3 | AB10: 117.2 | AC10: 118.8 | AD10: 119.9 | AE10: 121.5 | AF10: 124.3 | AG10: 131.9 | AH10: 133.8 | AI10: 137.9 | AJ10: 142.1 | AK10: 154.2 | AL10: 160.8 | AM10: 162.1 | AN10: 163.8 | AO10: 162.8 | AP10: 161.2 | AQ10: 162.7 | AR10: 166 | AS10: 169.2 | AT10: 171.8 | AU10: 172.2 | AV10: 170.4 | AW10: 170.2 | AX10: 170 | AY10: 167.9 | AZ10: 161.7 | BA10: 156.9 | BB10: 148 | BC10: 144.5 | BD10: 141.8 | BE10: 140.2 | BF10: 138.1 | BG10: 137.4 | BH10: 137.1 | BI10: 136.4 | BJ10: 135.8 | BK10: 133.8 | BL10: 131.8 | BM10: 130.2 | BN10: 129.3 | BO10: 128.4 | BP10: 127.2 | BQ10: 126 | BR10: 126.4 | BS10: 126.8 | BT10: 125.4 | BU10: 121.4 | BV10: 121 | BW10: 120.9 | BX10: 121.3 | BY10: 121.5 | BZ10: 122.3 | CA10: 125.1 | CB10: 128.7 | CC10: 130.6 | CD10: 131.5 | CE10: 132.2 | CF10: 133.1 | CG10: 136.2 | CH10: 138.8 | CI10: 141.1 | CJ10: 141.8 | CK10: 141.8 | CL10: 150.2 | CM10: NA | CN10: 150.3 | CO10: 150.3 | CP10: 149.9 | CQ10: 149.3 | CR10: 150.3 | CS10: 155.9 | CT10: 159.5 | CU10: 159.5 | CV10: 158.3 | CW10: 159.2 | CX10: 161.1 | CY10: 165.1 | CZ10: 165.5 | DA10: 163.6 | DB10: 162.8 | DC10: 163.9 | DD10: 165.2 | DE10: 165.4 | DF10: 164.5 | DG10: 164 | DH10: 163.9 | DI10: 164.2 | DJ10: 165.1 | DK10: 165 | DL10: 164.6 | DM10: 164.4 | DN10: 167.1 | DO10: 169 | DP10: 169.7 | DQ10: 170.2 | DR10: 170.5 | DS10: 170.7 | DT10: 170.4 | DU10: 170.5 | DV10: 172.8 | DW10: 174.9
A11: Rural | B11: =VLOOKUP(C11,'Broader Categories'!$A$1:$B$28,2,FALSE) -> Food | C11: Sugar and Confectionery | D11: 106.8 | E11: 105.7 | F11: 105 | G11: 104.2 | H11: 103.7 | I11: 104.1 | J11: 104.3 | K11: 104.1 | L11: 104.2 | M11: 103.9 | N11: 103.6 | O11: 102.9 | P11: 101.8 | Q11: 101.1 | R11: 101.2 | S11: 102.6 | T11: 103.5 | U11: 103.6 | V11: 104.8 | W11: 105.1 | X11: 104.7 | Y11: 104 | Z11: 103.3 | AA11: 102 | AB11: 100.5 | AC11: 100 | AD11: 98.9 | AE11: 97.8 | AF11: 97.6 | AG11: 96.3 | AH11: 94.1 | AI11: 93.1 | AJ11: 92.5 | AK11: 93.7 | AL11: 94.5 | AM11: 95.4 | AN11: 97.7 | AO11: 98.7 | AP11: 100.4 | AQ11: 105 | AR11: 107.5 | AS11: 108.8 | AT11: 110.3 | AU11: 112.1 | AV11: 113.1 | AW11: 113.4 | AX11: 113.4 | AY11: 113.8 | AZ11: 114.8 | BA11: 116.2 | BB11: 116.9 | BC11: 117.4 | BD11: 118.6 | BE11: 118.9 | BF11: 120 | BG11: 120.8 | BH11: 121 | BI11: 121.4 | BJ11: 122.5 | BK11: 121.9 | BL11: 119.5 | BM11: 117.9 | BN11: 117.1 | BO11: 115.2 | BP11: 111.8 | BQ11: 112.4 | BR11: 114.3 | BS11: 115.4 | BT11: 114.4 | BU11: 112.3 | BV11: 111.6 | BW11: 109.9 | BX11: 108.4 | BY11: 108.3 | BZ11: 108.3 | CA11: 109.3 | CB11: 110.6 | CC11: 110.8 | CD11: 111.7 | CE11: 112.8 | CF11: 113.6 | CG11: 113.8 | CH11: 113.6 | CI11: 113.8 | CJ11: 113.1 | CK11: 112.6 | CL11: 119.8 | CM11: NA | CN11: 113.2 | CO11: 113.2 | CP11: 114.2 | CQ11: 115.1 | CR11: 115.3 | CS11: 114.9 | CT11: 114.4 | CU11: 113.8 | CV11: 111.8 | CW11: 111.7 | CX11: 112.2 | CY11: 114.3 | CZ11: 114.6 | DA11: 113.9 | DB11: 115.2 | DC11: 119.3 | DD11: 121.6 | DE11: 122.1 | DF11: 120.6 | DG11: 119.3 | DH11: 118.1 | DI11: 118.1 | DJ11: 118.2 | DK11: 118.9 | DL11: 119.1 | DM11: 119.2 | DN11: 120.2 | DO11: 120.8 | DP11: 121.1 | DQ11: 121.5 | DR11: 121.2 | DS11: 120.3 | DT11: 119.1 | DU11: 119.1 | DV11: 120.4 | DW11: 121.9
A12: Rural | B12: =VLOOKUP(C12,'Broader Categories'!$A$1:$B$28,2,FALSE) -> Food | C12: Spices | D12: 103.1 | E12: 103.1 | F12: 103.3 | G12: 103.2 | H12: 104 | I12: 105.4 | J12: 106.4 | K12: 106.9 | L12: 107.9 | M12: 108.2 | N12: 109 | O12: 109.8 | P12: 110.2 | Q12: 110.4 | R12: 110.7 | S12: 111.2 | T12: 111.6 | U12: 112.3 | V12: 113.3 | W12: 114.6 | X12: 114.9 | Y12: 115.3 | Z12: 115.8 | AA12: 116 | AB12: 117.2 | AC12: 118.6 | AD12: 119.4 | AE12: 119.8 | AF12: 120.7 | AG12: 123 | AH12: 123.4 | AI12: 123.9 | AJ12: 125.4 | AK12: 126.6 | AL12: 128.3 | AM12: 128.9 | AN12: 129.6 | AO12: 130.6 | AP12: 130.8 | AQ12: 131.4 | AR12: 132.2 | AS12: 133.1 | AT12: 134.3 | AU12: 134.9 | AV12: 135.8 | AW12: 136.3 | AX12: 136.8 | AY12: 137.5 | AZ12: 136.9 | BA12: 136 | BB12: 135.6 | BC12: 134.1 | BD12: 134 | BE12: 133.5 | BF12: 133.9 | BG12: 134.7 | BH12: 134.7 | BI12: 135.6 | BJ12: 136 | BK12: 135.8 | BL12: 136 | BM12: 135.6 | BN12: 136.3 | BO12: 137.2 | BP12: 137.4 | BQ12: 137.6 | BR12: 138.2 | BS12: 138.6 | BT12: 138.7 | BU12: 139.5 | BV12: 140.6 | BW12: 140.2 | BX12: 138.9 | BY12: 139.2 | BZ12: 138.9 | CA12: 139.3 | CB12: 140.4 | CC12: 141.7 | CD12: 142.7 | CE12: 144.2 | CF12: 145.5 | CG12: 147.3 | CH12: 149.1 | CI12: 151.6 | CJ12: 152.8 | CK12: 154 | CL12: 158.7 | CM12: NA | CN12: 159.8 | CO12: 159.8 | CP12: 160 | CQ12: 160 | CR12: 160.9 | CS12: 162 | CT12: 163.5 | CU12: 164.5 | CV12: 165 | CW12: 164 | CX12: 164.4 | CY12: 169.7 | CZ12: 170 | DA12: 169.7 | DB12: 169.8 | DC12: 170.1 | DD12: 170.6 | DE12: 170.8 | DF12: 171.7 | DG12: 173.3 | DH12: 175.4 | DI12: 178.7 | DJ12: 182.9 | DK12: 186.6 | DL12: 188.9 | DM12: 191.8 | DN12: 195.6 | DO12: 199.1 | DP12: 201.6 | DQ12: 204.8 | DR12: 207.5 | DS12: 210.5 | DT12: 212.1 | DU12: 212.1 | DV12: 215.5 | DW12: 221
A13: Rural | B13: =VLOOKUP(C13,'Broader Categories'!$A$1:$B$28,2,FALSE) -> Food | C13: Non-alcoholic beverages | D13: 104.8 | E13: 105.1 | F13: 105.6 | G13: 106.5 | H13: 107.4 | I13: 108.2 | J13: 109.1 | K13: 109.7 | L13: 110.4 | M13: 111.1 | N13: 111.8 | O13: 112.1 | P13: 112.4 | Q13: 112.9 | R13: 113 | S13: 113.5 | T13: 114.2 | U13: 114.9 | V13: 115.6 | W13: 115.8 | X13: 116.5 | Y13: 116.8 | Z13: 116.8 | AA13: 117.3 | AB13: 117.9 | AC13: 118.8 | AD13: 118.9 | AE13: 119.4 | AF13: 120.2 | AG13: 121.1 | AH13: 121 | AI13: 121.5 | AJ13: 121.9 | AK13: 122.3 | AL13: 123.1 | AM13: 123.3 | AN13: 124.3 | AO13: 124.8 | AP13: 124.9 | AQ13: 125.4 | AR13: 126.1 | AS13: 126.4 | AT13: 127.3 | AU13: 128.1 | AV13: 128.8 | AW13: 128.7 | AX13: 128.7 | AY13: 129.1 | AZ13: 129 | BA13: 129.4 | BB13: 129.8 | BC13: 130 | BD13: 130.3 | BE13: 130.4 | BF13: 131.4 | BG13: 131.6 | BH13: 131.7 | BI13: 131.3 | BJ13: 131.9 | BK13: 131.1 | BL13: 131.2 | BM13: 130.5 | BN13: 131.2 | BO13: 131.9 | BP13: 132.2 | BQ13: 132.8 | BR13: 132.8 | BS13: 133.8 | BT13: 133.1 | BU13: 134.6 | BV13: 137.5 | BW13: 137.8 | BX13: 137 | BY13: 137.4 | BZ13: 137.4 | CA13: 137.7 | CB13: 138 | CC13: 138.5 | CD13: 138.5 | CE13: 138.5 | CF13: 138.6 | CG13: 138.7 | CH13: 139.3 | CI13: 139.7 | CJ13: 140.1 | CK13: 140.1 | CL13: 139.2 | CM13: NA | CN13: 142.1 | CO13: 142.1 | CP13: 143.5 | CQ13: 145.4 | CR13: 147.4 | CS13: 150 | CT13: 153.4 | CU13: 156.1 | CV13: 160 | CW13: 160.6 | CX13: 161.9 | CY13: 164.6 | CZ13: 165.5 | DA13: 166.2 | DB13: 167.6 | DC13: 168.3 | DD13: 168.8 | DE13: 169.1 | DF13: 169.7 | DG13: 169.8 | DH13: 170.5 | DI13: 171.2 | DJ13: 172.4 | DK13: 173.2 | DL13: 174.2 | DM13: 174.5 | DN13: 174.8 | DO13: 175.4 | DP13: 175.8 | DQ13: 176.4 | DR13: 176.8 | DS13: 176.9 | DT13: 177.6 | DU13: 177.6 | DV13: 178.2 | DW13: 178.7
A14: Rural | B14: =VLOOKUP(C14,'Broader Categories'!$A$1:$B$28,2,FALSE) -> Food | C14: Prepared meals, snacks, sweets etc. | D14: 106.7 | E14: 107.7 | F14: 108.2 | G14: 108.8 | H14: 109.9 | I14: 111 | J14: 112.1 | K14: 112.6 | L14: 114 | M14: 114.9 | N14: 116 | O14: 116.8 | P14: 117.3 | Q14: 117.8 | R14: 118.3 | S14: 118.7 | T14: 119.2 | U14: 120.1 | V14: 120.9 | W14: 121.7 | X14: 122.6 | Y14: 123.2 | Z14: 124.5 | AA14: 124.8 | AB14: 125.6 | AC14: 126.8 | AD14: 127.7 | AE14: 128.7 | AF14: 129.8 | AG14: 131.2 | AH14: 131.7 | AI14: 132.5 | AJ14: 132.7 | AK14: 133.1 | AL14: 134.2 | AM14: 135.1 | AN14: 135.9 | AO14: 136.4 | AP14: 137 | AQ14: 137.4 | AR14: 138.3 | AS14: 139.2 | AT14: 139.9 | AU14: 140.7 | AV14: 141.5 | AW14: 142.4 | AX14: 143.1 | AY14: 143.6 | AZ14: 143.9 | BA14: 144.4 | BB14: 145.4 | BC14: 145.5 | BD14: 145.8 | BE14: 146.5 | BF14: 147.7 | BG14: 148.7 | BH14: 149.3 | BI14: 150.3 | BJ14: 151.4 | BK14: 151.4 | BL14: 151.8 | BM14: 151.7 | BN14: 152.8 | BO14: 153.8 | BP14: 154.3 | BQ14: 154.3 | BR14: 154.8 | BS14: 155.2 | BT14: 155.9 | BU14: 155.2 | BV14: 156.1 | BW14: 156 | BX14: 155.8 | BY14: 156.2 | BZ14: 156.4 | CA14: 156.4 | CB14: 156.6 | CC14: 156.7 | CD14: 156.9 | CE14: 157.2 | CF14: 157.4 | CG14: 157.7 | CH14: 158.3 | CI14: 158.7 | CJ14: 159.2 | CK14: 160 | CL14: NA | CM14: NA | CN14: 161.8 | CO14: 161.8 | CP14: 161.5 | CQ14: 161.6 | CR14: 161.9 | CS14: 162.7 | CT14: 163.6 | CU14: 164.3 | CV14: 165.8 | CW14: 166.4 | CX14: 166.8 | CY14: 169.8 | CZ14: 171.7 | DA14: 171 | DB14: 171.9 | DC14: 172.8 | DD14: 173.6 | DE14: 174.3 | DF14: 175.1 | DG14: 175.8 | DH14: 176.3 | DI14: 177.4 | DJ14: 178.9 | DK14: 180.4 | DL14: 181.9 | DM14: 183.1 | DN14: 184 | DO14: 184.8 | DP14: 185.6 | DQ14: 186.9 | DR14: 187.7 | DS14: 188.5 | DT14: 189.9 | DU14: 189.9 | DV14: 190.5 | DW14: 191.1
A15: Rural | B15: =VLOOKUP(C15,'Broader Categories'!$A$1:$B$28,2,FALSE) -> Food | C15: Food and beverages | D15: 105.5 | E15: 106.3 | F15: 106.6 | G15: 107.1 | H15: 108.1 | I15: 110.6 | J15: 113.1 | K15: 114.9 | L15: 117.8 | M15: 119.8 | N15: 122.5 | O15: 118.7 | P15: 116 | Q15: 115.3 | R15: 116.2 | S15: 117.2 | T15: 118.2 | U15: 119.5 | V15: 123.3 | W15: 125.3 | X15: 125.3 | Y15: 125.1 | Z15: 124.9 | AA15: 123.3 | AB15: 122.8 | AC15: 122.8 | AD15: 123.1 | AE15: 123.6 | AF15: 124.4 | AG15: 126.6 | AH15: 127.5 | AI15: 129.8 | AJ15: 131 | AK15: 131.8 | AL15: 132.4 | AM15: 131.4 | AN15: 131.4 | AO15: 130.3 | AP15: 130.4 | AQ15: 131.8 | AR15: 133.6 | AS15: 136 | AT15: 137.6 | AU15: 138 | AV15: 137.2 | AW15: 137.4 | AX15: 136.6 | AY15: 134.7 | AZ15: 133.7 | BA15: 133.6 | BB15: 133.4 | BC15: 133.5 | BD15: 133.8 | BE15: 134.9 | BF15: 138.5 | BG15: 140.6 | BH15: 139.6 | BI15: 140.4 | BJ15: 142.4 | BK15: 141.5 | BL15: 140.4 | BM15: 138.7 | BN15: 138.6 | BO15: 138.6 | BP15: 139.1 | BQ15: 140 | BR15: 142 | BS15: 142.7 | BT15: 141.3 | BU15: 140.2 | BV15: 140 | BW15: 138.5 | BX15: 137.4 | BY15: 137.2 | BZ15: 137.3 | CA15: 139.2 | CB15: 141 | CC15: 143 | CD15: 144 | CE15: 145.5 | CF15: 148.3 | CG15: 150.9 | CH15: 154.3 | CI15: 153 | CJ15: 149.8 | CK15: 148.2 | CL15: 150.1 | CM15: NA | CN15: 152.3 | CO15: 152.3 | CP15: 155.3 | CQ15: 156.1 | CR15: 159.6 | CS15: 163.4 | CT15: 164.5 | CU15: 159.6 | CV15: 154.7 | CW15: 154.5 | CX15: 155.6 | CY15: 158.7 | CZ15: 160.5 | DA15: 161.7 | DB15: 161.8 | DC15: 162.1 | DD15: 165.5 | DE15: 167.5 | DF15: 165.8 | DG15: 164.1 | DH15: 163.9 | DI15: 166.6 | DJ15: 168.6 | DK15: 170.8 | DL15: 172.4 | DM15: 172.5 | DN15: 173.9 | DO15: 175.5 | DP15: 177.4 | DQ15: 176.6 | DR15: 174.4 | DS15: 175 | DT15: 174.8 | DU15: 174.8 | DV15: 175.5 | DW15: 176.8
A16: Rural | B16: =VLOOKUP(C16,'Broader Categories'!$A$1:$B$28,2,FALSE) -> Food | C16: Pan, tobacco and intoxicants | D16: 105.1 | E16: 105.6 | F16: 106.5 | G16: 107.1 | H16: 108.1 | I16: 109 | J16: 109.8 | K16: 110.7 | L16: 111.7 | M16: 112.2 | N16: 112.8 | O16: 113.6 | P16: 114 | Q16: 114.2 | R16: 114.6 | S16: 115.4 | T16: 116.3 | U16: 117.3 | V16: 118 | W16: 118.8 | X16: 119.5 | Y16: 120 | Z16: 120.8 | AA16: 121.7 | AB16: 122.7 | AC16: 124.2 | AD16: 124.7 | AE16: 125.7 | AF16: 126.7 | AG16: 128.2 | AH16: 129.4 | AI16: 130.1 | AJ16: 131 | AK16: 131.5 | AL16: 132.2 | AM16: 133.1 | AN16: 133.6 | AO16: 134.4 | AP16: 135 | AQ16: 135.5 | AR16: 136 | AS16: 137.2 | AT16: 138 | AU16: 138.9 | AV16: 139.9 | AW16: 140.9 | AX16: 141.2 | AY16: 142.4 | AZ16: 143.1 | BA16: 143.7 | BB16: 144.2 | BC16: 144.4 | BD16: 145.5 | BE16: 145.8 | BF16: 147.4 | BG16: 149 | BH16: 149.8 | BI16: 150.5 | BJ16: 152.1 | BK16: 153.2 | BL16: 153.6 | BM16: 153.3 | BN16: 155.1 | BO16: 156.1 | BP16: 157 | BQ16: 157.3 | BR16: 156.1 | BS16: 156.4 | BT16: 157.7 | BU16: 159.6 | BV16: 161.9 | BW16: 162.4 | BX16: 162.7 | BY16: 162.8 | BZ16: 162.9 | CA16: 163.3 | CB16: 164.2 | CC16: 164.5 | CD16: 165.1 | CE16: 165.7 | CF16: 166.3 | CG16: 167.2 | CH16: 167.8 | CI16: 168.6 | CJ16: 169.4 | CK16: 170.5 | CL16: NA | CM16: NA | CN16: 182.4 | CO16: 182.4 | CP16: 180.9 | CQ16: 182.9 | CR16: 182.7 | CS16: 183.4 | CT16: 183.6 | CU16: 184.6 | CV16: 186.5 | CW16: 186.1 | CX16: 186.8 | CY16: 189.6 | CZ16: 189.1 | DA16: 189.7 | DB16: 190.2 | DC16: 190.5 | DD16: 191.2 | DE16: 191.4 | DF16: 190.8 | DG16: 190.7 | DH16: 191.5 | DI16: 192.3 | DJ16: 192.8 | DK16: 192.9 | DL16: 192.9 | DM16: 193.2 | DN16: 193.7 | DO16: 194.5 | DP16: 194.9 | DQ16: 195.5 | DR16: 195.9 | DS16: 196.9 | DT16: 198.3 | DU16: 198.4 | DV16: 199.5 | DW16: 199.9
A17: Rural | B17: =VLOOKUP(C17,'Broader Categories'!$A$1:$B$28,2,FALSE) -> Apparels | C17: Clothing | D17: 106.5 | E17: 107.1 | F17: 107.6 | G17: 108.1 | H17: 108.8 | I17: 109.7 | J17: 110.5 | K17: 111.3 | L17: 112.7 | M17: 113.6 | N17: 114.6 | O17: 115.8 | P17: 116.5 | Q17: 117.1 | R17: 117.5 | S17: 118.1 | T17: 118.7 | U17: 119.7 | V17: 120.7 | W17: 120.9 | X17: 121.7 | Y17: 122.7 | Z17: 123.3 | AA17: 123.8 | AB17: 124.4 | AC17: 125.4 | AD17: 126 | AE17: 126.4 | AF17: 127.3 | AG17: 128.4 | AH17: 128.8 | AI17: 129.5 | AJ17: 130.4 | AK17: 131.1 | AL17: 132.1 | AM17: 132.5 | AN17: 133.2 | AO17: 133.9 | AP17: 134.4 | AQ17: 135 | AR17: 135.4 | AS17: 136.3 | AT17: 137.2 | AU17: 137.8 | AV17: 138.5 | AW17: 139.6 | AX17: 139.9 | AY17: 140.4 | AZ17: 140.7 | BA17: 140.9 | BB17: 141.6 | BC17: 142.4 | BD17: 142.5 | BE17: 143.1 | BF17: 144.3 | BG17: 145.3 | BH17: 146.1 | BI17: 147.2 | BJ17: 148.2 | BK17: 148 | BL17: 148.3 | BM17: 148.7 | BN17: 149.2 | BO17: 150.1 | BP17: 150.8 | BQ17: 151.3 | BR17: 151.5 | BS17: 152.1 | BT17: 152.1 | BU17: 150.7 | BV17: 151.7 | BW17: 151.6 | BX17: 150.6 | BY17: 150.5 | BZ17: 150.8 | CA17: 151.3 | CB17: 151.4 | CC17: 151.6 | CD17: 151.8 | CE17: 151.7 | CF17: 151.7 | CG17: 152.3 | CH17: 152.6 | CI17: 152.8 | CJ17: 153 | CK17: 153.4 | CL17: NA | CM17: NA | CN17: 154.7 | CO17: 154.7 | CP17: 155.1 | CQ17: 155.4 | CR17: 155.7 | CS17: 156.3 | CT17: 157 | CU17: 157.5 | CV17: 159.1 | CW17: 159.6 | CX17: 160.7 | CY17: 165.3 | CZ17: 165.3 | DA17: 166 | DB17: 167 | DC17: 167.7 | DD17: 168.9 | DE17: 170.4 | DF17: 171.8 | DG17: 173.2 | DH17: 174.1 | DI17: 175.4 | DJ17: 177.5 | DK17: 179.3 | DL17: 180.7 | DM17: 182 | DN17: 183.2 | DO17: 184.7 | DP17: 186.1 | DQ17: 187.2 | DR17: 188.1 | DS17: 189 | DT17: 190 | DU17: 190 | DV17: 190.7 | DW17: 191.2
A18: Rural | B18: =VLOOKUP(C18,'Broader Categories'!$A$1:$B$28,2,FALSE) -> Apparels | C18: Footwear | D18: 105.8 | E18: 106.3 | F18: 106.8 | G18: 107.4 | H18: 107.9 | I18: 108.8 | J18: 109.5 | K18: 110.2 | L18: 111.4 | M18: 112.3 | N18: 113.1 | O18: 114 | P18: 114.5 | Q18: 114.5 | R18: 114.9 | S18: 116.1 | T18: 116.8 | U18: 117.3 | V18: 118.3 | W18: 118.8 | X18: 119.2 | Y18: 120.3 | Z18: 120.5 | AA18: 120.6 | AB18: 121.6 | AC18: 122.7 | AD18: 122.9 | AE18: 123.3 | AF18: 124.1 | AG18: 125.1 | AH18: 125.5 | AI18: 126.3 | AJ18: 126.8 | AK18: 127.3 | AL18: 128.2 | AM18: 128.5 | AN18: 128.9 | AO18: 129.8 | AP18: 130.2 | AQ18: 130.6 | AR18: 131.1 | AS18: 131.6 | AT18: 132.2 | AU18: 133 | AV18: 133.5 | AW18: 134.3 | AX18: 134.5 | AY18: 135.2 | AZ18: 135.8 | BA18: 135.8 | BB18: 136.2 | BC18: 136.8 | BD18: 137.3 | BE18: 137.7 | BF18: 138.1 | BG18: 139.2 | BH18: 139.7 | BI18: 140.6 | BJ18: 141.5 | BK18: 141.9 | BL18: 142.3 | BM18: 142.4 | BN18: 143 | BO18: 143.3 | BP18: 144.1 | BQ18: 144.7 | BR18: 145.1 | BS18: 145.8 | BT18: 146.1 | BU18: 144.5 | BV18: 145.5 | BW18: 145.9 | BX18: 145.1 | BY18: 146.1 | BZ18: 146.1 | CA18: 146.6 | CB18: 146.5 | CC18: 146.6 | CD18: 146.6 | CE18: 146.6 | CF18: 146.7 | CG18: 147 | CH18: 147.3 | CI18: 147.4 | CJ18: 147.5 | CK18: 147.6 | CL18: NA | CM18: NA | CN18: 150 | CO18: 150 | CP18: 149.3 | CQ18: 149.9 | CR18: 150.6 | CS18: 151 | CT18: 151.6 | CU18: 152.4 | CV18: 153.9 | CW18: 154.4 | CX18: 155.1 | CY18: 160.6 | CZ18: 159.9 | DA18: 161.1 | DB18: 162.6 | DC18: 163.6 | DD18: 164.8 | DE18: 166 | DF18: 167.3 | DG18: 169.3 | DH18: 171 | DI18: 173.2 | DJ18: 175.1 | DK18: 177.2 | DL18: 178.7 | DM18: 180.3 | DN18: 181.7 | DO18: 183.3 | DP18: 184.4 | DQ18: 185.2 | DR18: 185.9 | DS18: 186.3 | DT18: 187 | DU18: 187 | DV18: 187.3 | DW18: 187.9
A19: Rural | B19: =VLOOKUP(C19,'Broader Categories'!$A$1:$B$28,2,FALSE) -> Apparels | C19: Clothing and footwear | D19: 106.4 | E19: 107 | F19: 107.5 | G19: 108 | H19: 108.6 | I19: 109.5 | J19: 110.3 | K19: 111.1 | L19: 112.5 | M19: 113.4 | N19: 114.4 | O19: 115.5 | P19: 116.2 | Q19: 116.7 | R19: 117.2 | S19: 117.8 | T19: 118.5 | U19: 119.3 | V19: 120.3 | W19: 120.7 | X19: 121.3 | Y19: 122.3 | Z19: 122.9 | AA19: 123.3 | AB19: 124 | AC19: 125 | AD19: 125.5 | AE19: 126 | AF19: 126.8 | AG19: 128 | AH19: 128.3 | AI19: 129 | AJ19: 129.9 | AK19: 130.6 | AL19: 131.5 | AM19: 131.9 | AN19: 132.6 | AO19: 133.4 | AP19: 133.8 | AQ19: 134.4 | AR19: 134.8 | AS19: 135.6 | AT19: 136.5 | AU19: 137.1 | AV19: 137.8 | AW19: 138.8 | AX19: 139.2 | AY19: 139.7 | AZ19: 140 | BA19: 140.2 | BB19: 140.8 | BC19: 141.6 | BD19: 141.8 | BE19: 142.3 | BF19: 143.5 | BG19: 144.5 | BH19: 145.2 | BI19: 146.2 | BJ19: 147.3 | BK19: 147.2 | BL19: 147.5 | BM19: 147.8 | BN19: 148.3 | BO19: 149.1 | BP19: 149.8 | BQ19: 150.3 | BR19: 150.6 | BS19: 151.3 | BT19: 151.3 | BU19: 149.8 | BV19: 150.8 | BW19: 150.8 | BX19: 149.9 | BY19: 149.9 | BZ19: 150.1 | CA19: 150.7 | CB19: 150.7 | CC19: 150.9 | CD19: 151.1 | CE19: 151 | CF19: 151 | CG19: 151.5 | CH19: 151.9 | CI19: 152.1 | CJ19: 152.3 | CK19: 152.5 | CL19: NA | CM19: NA | CN19: 154.1 | CO19: 154.1 | CP19: 154.3 | CQ19: 154.6 | CR19: 155 | CS19: 155.5 | CT19: 156.3 | CU19: 156.8 | CV19: 158.4 | CW19: 158.9 | CX19: 159.9 | CY19: 164.5 | CZ19: 164.6 | DA19: 165.3 | DB19: 166.3 | DC19: 167.1 | DD19: 168.3 | DE19: 169.8 | DF19: 171.2 | DG19: 172.7 | DH19: 173.7 | DI19: 175.1 | DJ19: 177.1 | DK19: 179 | DL19: 180.4 | DM19: 181.7 | DN19: 183 | DO19: 184.5 | DP19: 185.9 | DQ19: 186.9 | DR19: 187.8 | DS19: 188.6 | DT19: 189.6 | DU19: 189.6 | DV19: 190.2 | DW19: 190.8
A20: Rural | B20: =VLOOKUP(C20,'Broader Categories'!$A$1:$B$28,2,FALSE) -> Home | C20: Housing | D20: NA | E20: NA | F20: NA | G20: NA | H20: NA | I20: NA | J20: NA | K20: NA | L20: NA | M20: NA | N20: NA | O20: NA | P20: NA | Q20: NA | R20: NA | S20: NA | T20: NA | U20: NA | V20: NA | W20: NA | X20: NA | Y20: NA | Z20: NA | AA20: NA | AB20: NA | AC20: NA | AD20: NA | AE20: NA | AF20: NA | AG20: NA | AH20: NA | AI20: NA | AJ20: NA | AK20: NA | AL20: NA | AM20: NA | AN20: NA | AO20: NA | AP20: NA | AQ20: NA | AR20: NA | AS20: NA | AT20: NA | AU20: NA | AV20: NA | AW20: NA | AX20: NA | AY20: NA | AZ20: NA | BA20: NA | BB20: NA | BC20: NA | BD20: NA | BE20: NA | BF20: NA | BG20: NA | BH20: NA | BI20: NA | BJ20: NA | BK20: NA | BL20: NA | BM20: NA | BN20: NA | BO20: NA | BP20: NA | BQ20: NA | BR20: NA | BS20: NA | BT20: NA | BU20: NA | BV20: NA | BW20: NA | BX20: NA | BY20: NA | BZ20: NA | CA20: NA | CB20: NA | CC20: NA | CD20: NA | CE20: NA | CF20: NA | CG20: NA | CH20: NA | CI20: NA | CJ20: NA | CK20: NA | CL20: NA | CM20: NA | CN20: NA | CO20: NA | CP20: NA | CQ20: NA | CR20: NA | CS20: NA | CT20: NA | CU20: NA | CV20: NA | CW20: - | CX20: - | CY20: NA | CZ20: NA | DA20: NA | DB20: NA | DC20: NA | DD20: NA | DE20: NA | DF20: NA | DG20: NA | DH20: NA | DI20: NA | DJ20: NA | DK20: NA | DL20: NA | DM20: NA | DN20: NA | DO20: NA | DP20: NA | DQ20: NA | DR20: NA | DS20: NA | DT20: NA | DU20: NA | DV20: - | DW20: -
A21: Rural | B21: =VLOOKUP(C21,'Broader Categories'!$A$1:$B$28,2,FALSE) -> Home | C21: Fuel and light | D21: 105.5 | E21: 106.2 | F21: 106.1 | G21: 106.5 | H21: 107.5 | I21: 108.5 | J21: 109.5 | K21: 109.9 | L21: 111.1 | M21: 111.6 | N21: 112.6 | O21: 112.8 | P21: 113 | Q21: 113.2 | R21: 113.4 | S21: 113.4 | T21: 113.4 | U21: 114.4 | V21: 115.3 | W21: 115.4 | X21: 115.8 | Y21: 116.4 | Z21: 117.3 | AA21: 117.4 | AB21: 118.4 | AC21: 120 | AD21: 120.6 | AE21: 121.2 | AF21: 121.9 | AG21: 122.6 | AH21: 123 | AI21: 123.8 | AJ21: 123.7 | AK21: 124.4 | AL21: 125.6 | AM21: 125.7 | AN21: 126.2 | AO21: 127.5 | AP21: 127 | AQ21: 127 | AR21: 127.4 | AS21: 128 | AT21: 128.2 | AU21: 129.1 | AV21: 129.7 | AW21: 129.8 | AX21: 130.3 | AY21: 132 | AZ21: 132.1 | BA21: 133.2 | BB21: 134.2 | BC21: 135 | BD21: 135 | BE21: 134.8 | BF21: 135.3 | BG21: 136.4 | BH21: 137.4 | BI21: 138.1 | BJ21: 141.1 | BK21: 142.6 | BL21: 142.3 | BM21: 142.4 | BN21: 142.6 | BO21: 143.8 | BP21: 144.3 | BQ21: 145.1 | BR21: 146.8 | BS21: 147.7 | BT21: 149 | BU21: 149.7 | BV21: 150.3 | BW21: 149 | BX21: 146.2 | BY21: 145.3 | BZ21: 146.4 | CA21: 146.9 | CB21: 147.8 | CC21: 146.8 | CD21: 146.4 | CE21: 146.9 | CF21: 147.7 | CG21: 148.4 | CH21: 149.9 | CI21: 150.4 | CJ21: 152.3 | CK21: 153.4 | CL21: 148.4 | CM21: NA | CN21: 144.9 | CO21: 144.9 | CP21: 145.8 | CQ21: 146.4 | CR21: 146.8 | CS21: 147.5 | CT21: 148.7 | CU21: 150.9 | CV21: 154.4 | CW21: 156 | CX21: 156 | CY21: 161.7 | CZ21: 162.1 | DA21: 162.5 | DB21: 163.1 | DC21: 163.7 | DD21: 165.5 | DE21: 165.3 | DF21: 165.6 | DG21: 165.8 | DH21: 167.4 | DI21: 168.9 | DJ21: 173.3 | DK21: 175.3 | DL21: 176.7 | DM21: 179.6 | DN21: 179.1 | DO21: 179.7 | DP21: 180.8 | DQ21: 181.9 | DR21: 182.8 | DS21: 183.2 | DT21: 181.6 | DU21: 181.4 | DV21: 181.5 | DW21: 182.5
A22: Rural | B22: =VLOOKUP(C22,'Broader Categories'!$A$1:$B$28,2,FALSE) -> Home | C22: Household goods and services | D22: 104.8 | E22: 105.2 | F22: 105.6 | G22: 106.1 | H22: 106.8 | I22: 107.5 | J22: 108.3 | K22: 108.7 | L22: 109.6 | M22: 110.4 | N22: 111.3 | O22: 112.1 | P22: 112.6 | Q22: 112.9 | R22: 113.4 | S22: 113.7 | T22: 114.1 | U22: 114.9 | V22: 115.4 | W22: 115.9 | X22: 116.7 | Y22: 117.5 | Z22: 118.1 | AA22: 118.2 | AB22: 118.9 | AC22: 119.6 | AD22: 120.2 | AE22: 120.9 | AF22: 121.5 | AG22: 122.8 | AH22: 123 | AI22: 123.7 | AJ22: 124.5 | AK22: 125.1 | AL22: 125.6 | AM22: 126 | AN22: 126.6 | AO22: 127.1 | AP22: 127.7 | AQ22: 128 | AR22: 128.5 | AS22: 129.3 | AT22: 130 | AU22: 130.6 | AV22: 131.1 | AW22: 131.8 | AX22: 132.1 | AY22: 132.9 | AZ22: 133.2 | BA22: 133.6 | BB22: 134.1 | BC22: 134.3 | BD22: 134.9 | BE22: 135.2 | BF22: 136.1 | BG22: 137.3 | BH22: 137.9 | BI22: 138.4 | BJ22: 139.4 | BK22: 139.5 | BL22: 139.8 | BM22: 139.9 | BN22: 139.9 | BO22: 140.9 | BP22: 141.8 | BQ22: 142.2 | BR22: 143.1 | BS22: 143.8 | BT22: 144 | BU22: 147.5 | BV22: 148 | BW22: 149.5 | BX22: 150.1 | BY22: 150.1 | BZ22: 150 | CA22: 149.5 | CB22: 149.6 | CC22: 150 | CD22: 150.2 | CE22: 150.3 | CF22: 150.6 | CG22: 150.9 | CH22: 151.2 | CI22: 151.7 | CJ22: 151.8 | CK22: 151.5 | CL22: NA | CM22: NA | CN22: 151.7 | CO22: 151.7 | CP22: 151.9 | CQ22: 151.6 | CR22: 152 | CS22: 152.8 | CT22: 153.4 | CU22: 153.9 | CV22: 154.8 | CW22: 154.8 | CX22: 155.5 | CY22: 158.8 | CZ22: 159.2 | DA22: 160.3 | DB22: 160.9 | DC22: 161.3 | DD22: 162 | DE22: 162.9 | DF22: 163.9 | DG22: 164.9 | DH22: 165.7 | DI22: 166.5 | DJ22: 167.7 | DK22: 168.9 | DL22: 170.3 | DM22: 171.3 | DN22: 172.3 | DO22: 173.6 | DP22: 174.4 | DQ22: 175.5 | DR22: 176.4 | DS22: 177.2 | DT22: 178.6 | DU22: 178.6 | DV22: 179.1 | DW22: 179.8
A23: Rural | B23: =VLOOKUP(C23,'Broader Categories'!$A$1:$B$28,2,FALSE) -> Health | C23: Health | D23: 104 | E23: 104.4 | F23: 104.7 | G23: 105.1 | H23: 105.7 | I23: 106.3 | J23: 106.9 | K23: 107.5 | L23: 108.3 | M23: 108.9 | N23: 109.7 | O23: 110.1 | P23: 110.6 | Q23: 110.9 | R23: 111.4 | S23: 111.8 | T23: 112.1 | U23: 112.8 | V23: 113.4 | W23: 114 | X23: 114.5 | Y23: 115.3 | Z23: 115.9 | AA23: 116.2 | AB23: 116.6 | AC23: 117.7 | AD23: 118.2 | AE23: 118.6 | AF23: 119.4 | AG23: 120.4 | AH23: 120.8 | AI23: 121.1 | AJ23: 121.4 | AK23: 122 | AL23: 122.6 | AM23: 123.1 | AN23: 123.7 | AO23: 124.3 | AP23: 124.8 | AQ23: 125.2 | AR23: 125.8 | AS23: 126.2 | AT23: 126.7 | AU23: 127 | AV23: 127.8 | AW23: 128.7 | AX23: 129.1 | AY23: 129.7 | AZ23: 129.9 | BA23: 130.1 | BB23: 130.6 | BC23: 131 | BD23: 131.4 | BE23: 131.3 | BF23: 132.1 | BG23: 133 | BH23: 133.4 | BI23: 134.2 | BJ23: 135.8 | BK23: 136.1 | BL23: 136 | BM23: 136.2 | BN23: 136.7 | BO23: 137.6 | BP23: 138.4 | BQ23: 138.4 | BR23: 139 | BS23: 139.4 | BT23: 140 | BU23: 144.8 | BV23: 145.4 | BW23: 149.6 | BX23: 149.6 | BY23: 149.9 | BZ23: 150.4 | CA23: 151.3 | CB23: 151.7 | CC23: 152.2 | CD23: 152.7 | CE23: 153.4 | CF23: 153.7 | CG23: 154.3 | CH23: 154.8 | CI23: 155.7 | CJ23: 156.2 | CK23: 156.7 | CL23: 154.3 | CM23: NA | CN23: 158.2 | CO23: 158.2 | CP23: 158.8 | CQ23: 159.1 | CR23: 159.5 | CS23: 160.4 | CT23: 161.6 | CU23: 162.5 | CV23: 164.3 | CW23: 164.6 | CX23: 165.3 | CY23: 169.1 | CZ23: 169.7 | DA23: 170.4 | DB23: 171.1 | DC23: 171.9 | DD23: 172.5 | DE23: 173.4 | DF23: 174 | DG23: 174.7 | DH23: 175.3 | DI23: 176 | DJ23: 177 | DK23: 177.7 | DL23: 178.2 | DM23: 178.8 | DN23: 179.4 | DO23: 180.2 | DP23: 181.2 | DQ23: 182.3 | DR23: 183.5 | DS23: 184.7 | DT23: 186.6 | DU23: 186.6 | DV23: 187.2 | DW23: 187.8
A24: Rural | B24: =VLOOKUP(C24,'Broader Categories'!$A$1:$B$28,2,FALSE) -> Transport | C24: Transport and communication | D24: 103.3 | E24: 103.9 | F24: 104.6 | G24: 104.4 | H24: 104.1 | I24: 105 | J24: 106.8 | K24: 107.8 | L24: 109.3 | M24: 109.3 | N24: 109.6 | O24: 109.9 | P24: 110.5 | Q24: 110.8 | R24: 111.2 | S24: 111.2 | T24: 111.4 | U24: 112.2 | V24: 113.2 | W24: 113.2 | X24: 112.8 | Y24: 112.6 | Z24: 112 | AA24: 111.5 | AB24: 111 | AC24: 110.9 | AD24: 111.6 | AE24: 111.9 | AF24: 113.3 | AG24: 114.2 | AH24: 114.1 | AI24: 113.6 | AJ24: 113.8 | AK24: 113.8 | AL24: 114 | AM24: 114 | AN24: 113.6 | AO24: 113.9 | AP24: 113.6 | AQ24: 114.4 | AR24: 115.1 | AS24: 116.3 | AT24: 116.4 | AU24: 116 | AV24: 117 | AW24: 117.8 | AX24: 118.2 | AY24: 118.6 | AZ24: 119.1 | BA24: 119.5 | BB24: 119.8 | BC24: 119.2 | BD24: 119.4 | BE24: 119.4 | BF24: 119.1 | BG24: 120.3 | BH24: 121.2 | BI24: 121 | BJ24: 121.6 | BK24: 122 | BL24: 122.7 | BM24: 123.3 | BN24: 124.6 | BO24: 125.3 | BP24: 126.4 | BQ24: 127.4 | BR24: 127.5 | BS24: 128.3 | BT24: 129.9 | BU24: 130.8 | BV24: 130.3 | BW24: 128.9 | BX24: 128.6 | BY24: 129.2 | BZ24: 129.9 | CA24: 130.2 | CB24: 130.2 | CC24: 131.2 | CD24: 131.4 | CE24: 131.6 | CF24: 131.7 | CG24: 132.1 | CH24: 135 | CI24: 136.3 | CJ24: 136 | CK24: 135.8 | CL24: NA | CM24: NA | CN24: 141.4 | CO24: 141.4 | CP24: 143.6 | CQ24: 144.6 | CR24: 146.4 | CS24: 146.1 | CT24: 146.4 | CU24: 147.5 | CV24: 150.2 | CW24: 151.3 | CX24: 151.7 | CY24: 153.2 | CZ24: 154.2 | DA24: 157.1 | DB24: 157.7 | DC24: 157.8 | DD24: 159.5 | DE24: 158.9 | DF24: 160.1 | DG24: 160.8 | DH24: 161.2 | DI24: 162 | DJ24: 166.2 | DK24: 167.1 | DL24: 165.5 | DM24: 166.3 | DN24: 166.6 | DO24: 166.9 | DP24: 167.4 | DQ24: 167.5 | DR24: 167.8 | DS24: 168.2 | DT24: 169 | DU24: 169 | DV24: 169.4 | DW24: 169.7
A25: Rural | B25: =VLOOKUP(C25,'Broader Categories'!$A$1:$B$28,2,FALSE) -> Recreation | C25: Recreation and amusement | D25: 103.4 | E25: 104 | F25: 104 | G25: 104.5 | H25: 105 | I25: 105.6 | J25: 106.4 | K25: 106.8 | L25: 107.7 | M25: 108.3 | N25: 108.7 | O25: 109.2 | P25: 109.6 | Q25: 109.9 | R25: 110.2 | S25: 110.5 | T25: 110.9 | U25: 111.4 | V25: 111.8 | W25: 112.2 | X25: 112.6 | Y25: 113 | Z25: 113.3 | AA25: 113.3 | AB25: 114 | AC25: 114.8 | AD25: 115.5 | AE25: 116.2 | AF25: 116.7 | AG25: 117.9 | AH25: 118 | AI25: 118.5 | AJ25: 119.6 | AK25: 120.1 | AL25: 120.9 | AM25: 121.6 | AN25: 121.4 | AO25: 122.3 | AP25: 122.5 | AQ25: 123.2 | AR25: 123.6 | AS25: 124.1 | AT25: 125.2 | AU25: 125.5 | AV25: 125.7 | AW25: 126.5 | AX25: 126.9 | AY25: 127.3 | AZ25: 127 | BA25: 127.7 | BB25: 128.3 | BC25: 128.3 | BD25: 129.4 | BE25: 129.8 | BF25: 130.6 | BG25: 131.5 | BH25: 132.3 | BI25: 133 | BJ25: 133.7 | BK25: 133.4 | BL25: 134.3 | BM25: 134.3 | BN25: 135.1 | BO25: 136 | BP25: 136.8 | BQ25: 137.8 | BR25: 138.4 | BS25: 138.6 | BT25: 140 | BU25: 140.1 | BV25: 143.1 | BW25: 143.3 | BX25: 142.9 | BY25: 143.4 | BZ25: 143.8 | CA25: 145.9 | CB25: 146.4 | CC25: 147.5 | CD25: 148 | CE25: 148.3 | CF25: 148.7 | CG25: 149.1 | CH25: 149.5 | CI25: 150.1 | CJ25: 150.4 | CK25: 151.2 | CL25: NA | CM25: NA | CN25: 153.2 | CO25: 153.2 | CP25: 152.2 | CQ25: 152.8 | CR25: 152.4 | CS25: 153.6 | CT25: 153.9 | CU25: 155.1 | CV25: 157 | CW25: 157.8 | CX25: 158.6 | CY25: 160 | CZ25: 160.4 | DA25: 160.7 | DB25: 161.1 | DC25: 162.7 | DD25: 163.2 | DE25: 163.8 | DF25: 164.5 | DG25: 164.9 | DH25: 165.5 | DI25: 166.6 | DJ25: 167.2 | DK25: 167.6 | DL25: 168 | DM25: 168.6 | DN25: 169.3 | DO25: 170 | DP25: 170.6 | DQ25: 170.8 | DR25: 171.2 | DS25: 171.8 | DT25: 172.8 | DU25: 172.8 | DV25: 173.2 | DW25: 173.8
A26: Rural | B26: =VLOOKUP(C26,'Broader Categories'!$A$1:$B$28,2,FALSE) -> Education | C26: Education | D26: 103.8 | E26: 104.1 | F26: 104.3 | G26: 104.8 | H26: 105.5 | I26: 106.5 | J26: 107.8 | K26: 108.7 | L26: 109.8 | M26: 110.2 | N26: 111 | O26: 111.6 | P26: 111.8 | Q26: 112 | R26: 112.4 | S26: 113 | T26: 113.1 | U26: 114.3 | V26: 115.5 | W26: 116.2 | X26: 116.6 | Y26: 116.9 | Z26: 117.2 | AA26: 117.7 | AB26: 118.2 | AC26: 118.7 | AD26: 119.4 | AE26: 119.9 | AF26: 120.5 | AG26: 122 | AH26: 122.9 | AI26: 123.6 | AJ26: 124.5 | AK26: 125.1 | AL26: 125.8 | AM26: 125.6 | AN26: 126.2 | AO26: 127.1 | AP26: 127.5 | AQ26: 127.9 | AR26: 129.1 | AS26: 130.2 | AT26: 130.8 | AU26: 131.9 | AV26: 132.2 | AW26: 133 | AX26: 133.7 | AY26: 134.2 | AZ26: 134.6 | BA26: 134.9 | BB26: 135.2 | BC26: 135.7 | BD26: 136.3 | BE26: 136.9 | BF26: 138.6 | BG26: 140.2 | BH26: 139.6 | BI26: 140.1 | BJ26: 141.5 | BK26: 141.1 | BL26: 141.6 | BM26: 141.5 | BN26: 142.7 | BO26: 143.7 | BP26: 144.4 | BQ26: 145.1 | BR26: 145.8 | BS26: 146.9 | BT26: 147.6 | BU26: 148 | BV26: 150.2 | BW26: 155.1 | BX26: 155.2 | BY26: 155.5 | BZ26: 155.5 | CA26: 156.7 | CB26: 157.7 | CC26: 159.1 | CD26: 159.7 | CE26: 160.2 | CF26: 160.7 | CG26: 160.8 | CH26: 161.1 | CI26: 161.7 | CJ26: 161.9 | CK26: 161.2 | CL26: NA | CM26: NA | CN26: 161.8 | CO26: 161.8 | CP26: 162.7 | CQ26: 161.1 | CR26: 162.5 | CS26: 161.6 | CT26: 162.9 | CU26: 163.5 | CV26: 163.6 | CW26: 163.8 | CX26: 164.1 | CY26: 167.6 | CZ26: 166.8 | DA26: 167.2 | DB26: 167.5 | DC26: 168.5 | DD26: 169 | DE26: 169.3 | DF26: 169.7 | DG26: 169.9 | DH26: 170.3 | DI26: 170.6 | DJ26: 170.9 | DK26: 171.8 | DL26: 172.6 | DM26: 174.7 | DN26: 175.7 | DO26: 176.2 | DP26: 176.5 | DQ26: 176.9 | DR26: 177.3 | DS26: 177.8 | DT26: 178.5 | DU26: 178.5 | DV26: 179.4 | DW26: 180.3
A27: Rural | B27: =VLOOKUP(C27,'Broader Categories'!$A$1:$B$28,2,FALSE) -> Health | C27: Personal care and effects | D27: 104.7 | E27: 104.6 | F27: 104.3 | G27: 102.7 | H27: 102.1 | I27: 102.5 | J27: 102.5 | K27: 105 | L27: 106.7 | M27: 107.5 | N27: 108.2 | O27: 108.1 | P27: 108.3 | Q27: 108.7 | R27: 108.9 | S27: 108.9 | T27: 108.9 | U27: 108 | V27: 108.8 | W27: 109.4 | X27: 109.1 | Y27: 109.3 | Z27: 108.8 | AA27: 109.4 | AB27: 110.2 | AC27: 110.8 | AD27: 110.8 | AE27: 111.6 | AF27: 112.3 | AG27: 113 | AH27: 112.7 | AI27: 112.5 | AJ27: 113.7 | AK27: 114.2 | AL27: 114.2 | AM27: 114.1 | AN27: 114.9 | AO27: 116.8 | AP27: 117.4 | AQ27: 118.4 | AR27: 119.7 | AS27: 119.9 | AT27: 120.9 | AU27: 122 | AV27: 122.8 | AW27: 123 | AX27: 123.5 | AY27: 121.9 | AZ27: 122.3 | BA27: 123.2 | BB27: 123.3 | BC27: 123.7 | BD27: 123.7 | BE27: 124.1 | BF27: 124.4 | BG27: 125.4 | BH27: 126.7 | BI27: 127.4 | BJ27: 128.1 | BK27: 127.8 | BL27: 128.6 | BM27: 128.8 | BN27: 129.3 | BO27: 130.4 | BP27: 131.2 | BQ27: 131.4 | BR27: 131.4 | BS27: 131.3 | BT27: 132 | BU27: 134.4 | BV27: 133.1 | BW27: 133.2 | BX27: 133.5 | BY27: 134.9 | BZ27: 134 | CA27: 133.9 | CB27: 134.8 | CC27: 136.1 | CD27: 138.8 | CE27: 140.2 | CF27: 140.3 | CG27: 140.6 | CH27: 140.6 | CI27: 142.5 | CJ27: 143.4 | CK27: 145.1 | CL27: NA | CM27: NA | CN27: 151.2 | CO27: 151.2 | CP27: 153.6 | CQ27: 157.4 | CR27: 156.2 | CS27: 156.2 | CT27: 156.6 | CU27: 156.2 | CV27: 155.2 | CW27: 153.1 | CX27: 154.6 | CY27: 159.3 | CZ27: 159.4 | DA27: 160.4 | DB27: 160.3 | DC27: 160.2 | DD27: 161.1 | DE27: 162.4 | DF27: 162.8 | DG27: 163.2 | DH27: 164.5 | DI27: 167.4 | DJ27: 169 | DK27: 168.5 | DL27: 169.5 | DM27: 169.7 | DN27: 171.1 | DO27: 170.8 | DP27: 172 | DQ27: 173.4 | DR27: 175.7 | DS27: 178.4 | DT27: 180.7 | DU27: 180.7 | DV27: 183.8 | DW27: 184.9
A28: Rural | B28: =VLOOKUP(C28,'Broader Categories'!$A$1:$B$28,2,FALSE) -> Misc | C28: Miscellaneous | D28: 104 | E28: 104.4 | F28: 104.6 | G28: 104.6 | H28: 104.8 | I28: 105.5 | J28: 106.5 | K28: 107.5 | L28: 108.7 | M28: 109.1 | N28: 109.8 | O28: 110.1 | P28: 110.6 | Q28: 110.9 | R28: 111.3 | S28: 111.5 | T28: 111.8 | U28: 112.3 | V28: 113.1 | W28: 113.5 | X28: 113.7 | Y28: 114 | Z28: 114.1 | AA28: 114.2 | AB28: 114.5 | AC28: 115 | AD28: 115.5 | AE28: 116 | AF28: 116.9 | AG28: 117.9 | AH28: 118.1 | AI28: 118.2 | AJ28: 118.8 | AK28: 119.2 | AL28: 119.6 | AM28: 119.8 | AN28: 120.1 | AO28: 120.9 | AP28: 121.1 | AQ28: 121.7 | AR28: 122.5 | AS28: 123.3 | AT28: 123.8 | AU28: 124.2 | AV28: 124.9 | AW28: 125.7 | AX28: 126.1 | AY28: 126.3 | AZ28: 126.6 | BA28: 127 | BB28: 127.4 | BC28: 127.5 | BD28: 127.9 | BE28: 128.1 | BF28: 128.6 | BG28: 129.7 | BH28: 130.3 | BI28: 130.7 | BJ28: 131.7 | BK28: 131.9 | BL28: 132.3 | BM28: 132.5 | BN28: 133.3 | BO28: 134.2 | BP28: 135.1 | BQ28: 135.6 | BR28: 136 | BS28: 136.6 | BT28: 137.4 | BU28: 139.8 | BV28: 140.1 | BW28: 141.6 | BX28: 141.7 | BY28: 142.2 | BZ28: 142.4 | CA28: 142.9 | CB28: 143.3 | CC28: 144.2 | CD28: 144.9 | CE28: 145.4 | CF28: 145.7 | CG28: 146.1 | CH28: 147.1 | CI28: 148.1 | CJ28: 148.4 | CK28: 148.6 | CL28: NA | CM28: NA | CN28: 151.7 | CO28: 151.7 | CP28: 153 | CQ28: 153.7 | CR28: 154.3 | CS28: 154.5 | CT28: 155.2 | CU28: 155.9 | CV28: 157.2 | CW28: 157.3 | CX28: 158 | CY28: 161.1 | CZ28: 161.5 | DA28: 162.8 | DB28: 163.3 | DC28: 163.8 | DD28: 164.7 | DE28: 165.2 | DF28: 166 | DG28: 166.6 | DH28: 167.3 | DI28: 168.3 | DJ28: 170.2 | DK28: 170.9 | DL28: 171 | DM28: 171.8 | DN28: 172.6 | DO28: 173.1 | DP28: 173.9 | DQ28: 174.6 | DR28: 175.5 | DS28: 176.5 | DT28: 177.9 | DU28: 177.9 | DV28: 178.9 | DW28: 179.5
A29: Rural | B29: =VLOOKUP(C29,'Broader Categories'!$A$1:$B$28,2,FALSE) -> Does not come under any category | C29: General index | D29: 105.1 | E29: 105.8 | F29: 106 | G29: 106.4 | H29: 107.2 | I29: 108.9 | J29: 110.7 | K29: 112.1 | L29: 114.2 | M29: 115.5 | N29: 117.4 | O29: 115.5 | P29: 114.2 | Q29: 114 | R29: 114.6 | S29: 115.4 | T29: 116 | U29: 117 | V29: 119.5 | W29: 120.7 | X29: 120.9 | Y29: 121 | Z29: 121.1 | AA29: 120.3 | AB29: 120.3 | AC29: 120.6 | AD29: 121.1 | AE29: 121.5 | AF29: 122.4 | AG29: 124.1 | AH29: 124.7 | AI29: 126.1 | AJ29: 127 | AK29: 127.7 | AL29: 128.3 | AM29: 127.9 | AN29: 128.1 | AO29: 127.9 | AP29: 128 | AQ29: 129 | AR29: 130.3 | AS29: 131.9 | AT29: 133 | AU29: 133.5 | AV29: 133.4 | AW29: 133.8 | AX29: 133.6 | AY29: 132.8 | AZ29: 132.4 | BA29: 132.6 | BB29: 132.8 | BC29: 132.9 | BD29: 133.3 | BE29: 133.9 | BF29: 136.2 | BG29: 137.8 | BH29: 137.6 | BI29: 138.3 | BJ29: 140 | BK29: 139.8 | BL29: 139.3 | BM29: 138.5 | BN29: 138.7 | BO29: 139.1 | BP29: 139.8 | BQ29: 140.5 | BR29: 141.8 | BS29: 142.5 | BT29: 142.1 | BU29: 142.2 | BV29: 142.4 | BW29: 141.9 | BX29: 141 | BY29: 141 | BZ29: 141.2 | CA29: 142.4 | CB29: 143.6 | CC29: 144.9 | CD29: 145.7 | CE29: 146.7 | CF29: 148.3 | CG29: 149.9 | CH29: 152.3 | CI29: 151.9 | CJ29: 150.4 | CK29: 149.8 | CL29: NA | CM29: NA | CN29: 152.7 | CO29: 152.7 | CP29: 154.7 | CQ29: 155.4 | CR29: 157.5 | CS29: 159.8 | CT29: 160.7 | CU29: 158.5 | CV29: 156.7 | CW29: 156.7 | CX29: 157.6 | CY29: 161.1 | CZ29: 162.1 | DA29: 163.2 | DB29: 163.6 | DC29: 164 | DD29: 166.3 | DE29: 167.6 | DF29: 167 | DG29: 166.4 | DH29: 166.7 | DI29: 168.7 | DJ29: 170.8 | DK29: 172.5 | DL29: 173.6 | DM29: 174.3 | DN29: 175.3 | DO29: 176.4 | DP29: 177.9 | DQ29: 177.8 | DR29: 177.1 | DS29: 177.8 | DT29: 178 | DU29: 178 | DV29: 178.8 | DW29: 179.8
A30: Urban | B30: =VLOOKUP(C30,'Broader Categories'!$A$1:$B$28,2,FALSE) -> Food | C30: Cereals and products | D30: 110.5 | E30: 112.9 | F30: 113.9 | G30: 114.6 | H30: 115.4 | I30: 117 | J30: 117.8 | K30: 118.3 | L30: 118.6 | M30: 118.9 | N30: 119.8 | O30: 120.5 | P30: 121.2 | Q30: 121.9 | R30: 122.1 | S30: 122.5 | T30: 122.7 | U30: 123.1 | V30: 123.8 | W30: 124.8 | X30: 124.2 | Y30: 124.6 | Z30: 124.5 | AA30: 124 | AB30: 124 | AC30: 124.3 | AD30: 124 | AE30: 123.8 | AF30: 123.8 | AG30: 123.6 | AH30: 123.2 | AI30: 123.1 | AJ30: 123.4 | AK30: 123.6 | AL30: 124 | AM30: 124.3 | AN30: 124.7 | AO30: 124.8 | AP30: 124.8 | AQ30: 124.9 | AR30: 125 | AS30: 125.9 | AT30: 126.8 | AU30: 127.6 | AV30: 128.1 | AW30: 128.7 | AX30: 130.2 | AY30: 131.6 | AZ30: 132.2 | BA30: 132.8 | BB30: 132.7 | BC30: 132.7 | BD30: 132.6 | BE30: 132.9 | BF30: 132.8 | BG30: 133.2 | BH30: 133.6 | BI30: 133.9 | BJ30: 134.3 | BK30: 134.4 | BL30: 134.6 | BM30: 134.8 | BN30: 135 | BO30: 135 | BP30: 135 | BQ30: 135.3 | BR30: 135.6 | BS30: 136.5 | BT30: 137 | BU30: 137.6 | BV30: 138.1 | BW30: 138.5 | BX30: 138.3 | BY30: 139.4 | BZ30: 139.7 | CA30: 140.4 | CB30: 140.7 | CC30: 141.4 | CD30: 142.1 | CE30: 142.7 | CF30: 143.5 | CG30: 144.1 | CH30: 144.9 | CI30: 145.6 | CJ30: 146.2 | CK30: 146.5 | CL30: 151.8 | CM30: NA | CN30: 152.7 | CO30: 152.7 | CP30: 151.6 | CQ30: 151.5 | CR30: 150.6 | CS30: 149.7 | CT30: 149 | CU30: 148 | CV30: 147.6 | CW30: 147.5 | CX30: 147.6 | CY30: 148.8 | CZ30: 149.2 | DA30: 149.1 | DB30: 149.3 | DC30: 149.3 | DD30: 150.1 | DE30: 151 | DF30: 151.6 | DG30: 152.2 | DH30: 152.5 | DI30: 153.7 | DJ30: 155.4 | DK30: 156.7 | DL30: 157.5 | DM30: 159.3 | DN30: 162.1 | DO30: 164.9 | DP30: 166.4 | DQ30: 168.4 | DR30: 170.2 | DS30: 173.3 | DT30: 174.7 | DU30: 174.7 | DV30: 174.8 | DW30: 174.7
A31: Urban | B31: =VLOOKUP(C31,'Broader Categories'!$A$1:$B$28,2,FALSE) -> Food | C31: Meat and fish | D31: 109.1 | E31: 112.9 | F31: 111.4 | G31: 113.4 | H31: 114.2 | I31: 120.1 | J31: 119.2 | K31: 120.4 | L31: 119.1 | M31: 118.1 | N31: 116.3 | O31: 118.1 | P31: 122 | Q31: 122 | R31: 121.4 | S31: 121.7 | T31: 124.1 | U31: 125.9 | V31: 126.4 | W31: 127.3 | X31: 125.4 | Y31: 126.1 | Z31: 125.6 | AA31: 124.7 | AB31: 125.5 | AC31: 126.5 | AD31: 126.7 | AE31: 128.2 | AF31: 129.7 | AG31: 134.4 | AH31: 134.3 | AI31: 131.7 | AJ31: 129 | AK31: 128.6 | AL31: 129.8 | AM31: 131.7 | AN31: 135.9 | AO31: 135.1 | AP31: 136.3 | AQ31: 139.3 | AR31: 142.1 | AS31: 143.9 | AT31: 144.2 | AU31: 140.3 | AV31: 137.7 | AW31: 138.4 | AX31: 138.5 | AY31: 138.2 | AZ31: 138.9 | BA31: 139.8 | BB31: 139.4 | BC31: 140.6 | BD31: 144.1 | BE31: 148.7 | BF31: 148.4 | BG31: 143.9 | BH31: 143 | BI31: 142.8 | BJ31: 142.1 | BK31: 142.6 | BL31: 143.7 | BM31: 143 | BN31: 143.1 | BO31: 144.3 | BP31: 148.2 | BQ31: 149.7 | BR31: 148.6 | BS31: 146.4 | BT31: 143.1 | BU31: 144.9 | BV31: 146.3 | BW31: 147.8 | BX31: 149.4 | BY31: 150.1 | BZ31: 151.1 | CA31: 156.7 | CB31: 159.6 | CC31: 160.2 | CD31: 158.3 | CE31: 158.7 | CF31: 159.8 | CG31: 162.4 | CH31: 164.5 | CI31: 167.6 | CJ31: 167.6 | CK31: 167.5 | CL31: NA | CM31: NA | CN31: 197 | CO31: 197 | CP31: 197.8 | CQ31: 193.1 | CR31: 193.7 | CS31: 195.5 | CT31: 195.7 | CU31: 194.8 | CV31: 191.2 | CW31: 197.5 | CX31: 202.5 | CY31: 204.3 | CZ31: 205.5 | DA31: 210.9 | DB31: 207.4 | DC31: 207.4 | DD31: 208.4 | DE31: 204.9 | DF31: 202.2 | DG31: 202.1 | DH31: 205.2 | DI31: 215.8 | DJ31: 215.8 | DK31: 221.2 | DL31: 223.4 | DM31: 217.1 | DN31: 210.9 | DO31: 213.7 | DP31: 214.9 | DQ31: 213.4 | DR31: 212.9 | DS31: 215.2 | DT31: 212.2 | DU31: 212.2 | DV31: 213.7 | DW31: 219.4
A32: Urban | B32: =VLOOKUP(C32,'Broader Categories'!$A$1:$B$28,2,FALSE) -> Food | C32: Egg | D32: 113 | E32: 116.9 | F32: 113.2 | G32: 106 | H32: 102.7 | I32: 112.5 | J32: 114 | K32: 112.7 | L32: 113.2 | M32: 114.5 | N32: 122.6 | O32: 128.5 | P32: 129.9 | Q32: 124.5 | R32: 121.5 | S32: 113.3 | T32: 114.2 | U32: 115.4 | V32: 118 | W32: 116.5 | X32: 116.4 | Y32: 117.8 | Z32: 122.7 | AA32: 126.3 | AB32: 126.6 | AC32: 119.5 | AD32: 113.5 | AE32: 110 | AF32: 111.3 | AG32: 120.9 | AH32: 119.5 | AI32: 118.1 | AJ32: 115.6 | AK32: 115.9 | AL32: 121.5 | AM32: 127.1 | AN32: 132 | AO32: 130.3 | AP32: 123.7 | AQ32: 119.9 | AR32: 127 | AS32: 130.9 | AT32: 136.6 | AU32: 133.7 | AV32: 130.6 | AW32: 130.3 | AX32: 134.1 | AY32: 134.9 | AZ32: 132.6 | BA32: 129.3 | BB32: 128.4 | BC32: 124.5 | BD32: 125.6 | BE32: 128.3 | BF32: 129.4 | BG32: 128.3 | BH32: 129.7 | BI32: 131.4 | BJ32: 146.7 | BK32: 145.9 | BL32: 143.6 | BM32: 139.9 | BN32: 135.5 | BO32: 130.8 | BP32: 130.5 | BQ32: 133.9 | BR32: 139.1 | BS32: 136.6 | BT32: 132.8 | BU32: 133.5 | BV32: 137.8 | BW32: 141.1 | BX32: 143.5 | BY32: 145.3 | BZ32: 142.9 | CA32: 138.3 | CB32: 140.4 | CC32: 142.5 | CD32: 140.8 | CE32: 141.6 | CF32: 144.7 | CG32: 148.4 | CH32: 153.7 | CI32: 157 | CJ32: 153.1 | CK32: 148.9 | CL32: 151.9 | CM32: NA | CN32: 154.6 | CO32: 154.6 | CP32: 154.5 | CQ32: 157.3 | CR32: 164.8 | CS32: 176.9 | CT32: 178.3 | CU32: 178.4 | CV32: 169.9 | CW32: 164.7 | CX32: 166.4 | CY32: 173 | CZ32: 182.8 | DA32: 185 | DB32: 174.1 | DC32: 174.1 | DD32: 173 | DE32: 175.4 | DF32: 180 | DG32: 180.1 | DH32: 176.4 | DI32: 167.7 | DJ32: 164.6 | DK32: 164.1 | DL32: 172.8 | DM32: 176.6 | DN32: 170.6 | DO32: 170.9 | DP32: 171.9 | DQ32: 183.2 | DR32: 191.9 | DS32: 197 | DT32: 177.2 | DU32: 177.2 | DV32: 172.4 | DW32: 176.7
A33: Urban | B33: =VLOOKUP(C33,'Broader Categories'!$A$1:$B$28,2,FALSE) -> Food | C33: Milk and products | D33: 103.6 | E33: 104 | F33: 104.3 | G33: 104.7 | H33: 105.5 | I33: 107.3 | J33: 108.3 | K33: 108.9 | L33: 109.6 | M33: 110.4 | N33: 112 | O33: 112.8 | P33: 113.6 | Q33: 115.2 | R33: 116.2 | S33: 117 | T33: 119.1 | U33: 120.4 | V33: 121.6 | W33: 122.2 | X33: 122.7 | Y33: 123.1 | Z33: 124.6 | AA33: 124.9 | AB33: 125.2 | AC33: 125.6 | AD33: 125.9 | AE33: 126.3 | AF33: 126.6 | AG33: 127.3 | AH33: 127.7 | AI33: 128 | AJ33: 128.3 | AK33: 128.5 | AL33: 128.6 | AM33: 128.6 | AN33: 129.2 | AO33: 129.6 | AP33: 129.7 | AQ33: 130.2 | AR33: 130.4 | AS33: 131 | AT33: 131.8 | AU33: 132.2 | AV33: 132.6 | AW33: 132.7 | AX33: 132.9 | AY33: 133.1 | AZ33: 133.1 | BA33: 133.5 | BB33: 134.9 | BC33: 136.3 | BD33: 136.8 | BE33: 137.3 | BF33: 137.7 | BG33: 138.3 | BH33: 138.7 | BI33: 139.1 | BJ33: 139.5 | BK33: 139.5 | BL33: 139.6 | BM33: 139.9 | BN33: 139.9 | BO33: 140.3 | BP33: 140.7 | BQ33: 140.8 | BR33: 141 | BS33: 141.2 | BT33: 141.5 | BU33: 141.5 | BV33: 141.6 | BW33: 141.6 | BX33: 141.7 | BY33: 141.7 | BZ33: 141.9 | CA33: 142.4 | CB33: 143.4 | CC33: 144.1 | CD33: 144.9 | CE33: 144.9 | CF33: 145.6 | CG33: 145.9 | CH33: 147.5 | CI33: 149.3 | CJ33: 150.7 | CK33: 151.1 | CL33: 155.5 | CM33: NA | CN33: 153.4 | CO33: 153.4 | CP33: 153.4 | CQ33: 153.9 | CR33: 153.7 | CS33: 153.9 | CT33: 154.2 | CU33: 154.4 | CV33: 155.1 | CW33: 155.6 | CX33: 156 | CY33: 156.5 | CZ33: 156.5 | DA33: 158.2 | DB33: 159.2 | DC33: 159.1 | DD33: 159.2 | DE33: 159.6 | DF33: 160 | DG33: 160.4 | DH33: 160.6 | DI33: 162.6 | DJ33: 164.2 | DK33: 165.4 | DL33: 166.4 | DM33: 167.1 | DN33: 168.4 | DO33: 170.1 | DP33: 171 | DQ33: 172.3 | DR33: 173.9 | DS33: 175.2 | DT33: 177.9 | DU33: 177.9 | DV33: 178.8 | DW33: 179.4
A34: Urban | B34: =VLOOKUP(C34,'Broader Categories'!$A$1:$B$28,2,FALSE) -> Food | C34: Oils and fats | D34: 103.4 | E34: 103.5 | F34: 102.7 | G34: 102.1 | H34: 101.5 | I34: 101.3 | J34: 101.1 | K34: 101.1 | L34: 101.7 | M34: 102.3 | N34: 103.2 | O34: 103.4 | P34: 102.9 | Q34: 102.5 | R34: 102.8 | S34: 103.1 | T34: 103.5 | U34: 103.4 | V34: 103.5 | W34: 103.6 | X34: 103.5 | Y34: 103.5 | Z34: 103.2 | AA34: 103 | AB34: 104.3 | AC34: 104.9 | AD34: 104.8 | AE34: 104.5 | AF34: 105.2 | AG34: 106 | AH34: 106.3 | AI34: 106.8 | AJ34: 107 | AK34: 109 | AL34: 110 | AM34: 110 | AN34: 109.7 | AO34: 108.4 | AP34: 107.9 | AQ34: 108.9 | AR34: 109.6 | AS34: 110.2 | AT34: 111 | AU34: 111.8 | AV34: 111.9 | AW34: 112.5 | AX34: 112.6 | AY34: 113.5 | AZ34: 114 | BA34: 114.3 | BB34: 114 | BC34: 113.5 | BD34: 113.4 | BE34: 113.5 | BF34: 113.4 | BG34: 114.1 | BH34: 114.5 | BI34: 114.9 | BJ34: 115.2 | BK34: 115.9 | BL34: 116.4 | BM34: 116.2 | BN34: 116.5 | BO34: 116.6 | BP34: 116.4 | BQ34: 116.6 | BR34: 116.7 | BS34: 117.4 | BT34: 117.8 | BU34: 118 | BV34: 118.1 | BW34: 118.1 | BX34: 118.1 | BY34: 118.4 | BZ34: 118.4 | CA34: 118.6 | CB34: 118.6 | CC34: 119.3 | CD34: 119.9 | CE34: 120.8 | CF34: 121.1 | CG34: 121.5 | CH34: 122.7 | CI34: 126.3 | CJ34: 127.4 | CK34: 127.5 | CL34: 131.6 | CM34: NA | CN34: 132.9 | CO34: 132.9 | CP34: 133.4 | CQ34: 134.4 | CR34: 135.7 | CS34: 138 | CT34: 140.7 | CU34: 144.1 | CV34: 151.4 | CW34: 156.4 | CX34: 161.4 | CY34: 168.8 | CZ34: 172.2 | DA34: 170.6 | DB34: 175 | DC34: 175 | DD34: 176.6 | DE34: 175.8 | DF34: 173.5 | DG34: 171 | DH34: 171.5 | DI34: 180 | DJ34: 186 | DK34: 189.5 | DL34: 188.6 | DM34: 184.8 | DN34: 182.5 | DO34: 179.3 | DP34: 177.7 | DQ34: 180 | DR34: 179.1 | DS34: 178 | DT34: 172.2 | DU34: 172.2 | DV34: 168.7 | DW34: 164.4
A35: Urban | B35: =VLOOKUP(C35,'Broader Categories'!$A$1:$B$28,2,FALSE) -> Food | C35: Fruits | D35: 102.3 | E35: 103.1 | F35: 104.9 | G35: 109.5 | H35: 110.6 | I35: 112.4 | J35: 113.2 | K35: 108.7 | L35: 103.2 | M35: 106.2 | N35: 110 | O35: 110.7 | P35: 112.1 | Q35: 114.1 | R35: 117.7 | S35: 126.7 | T35: 129.2 | U35: 131.2 | V35: 133.7 | W35: 132.7 | X35: 124.5 | Y35: 123.5 | Z35: 122.2 | AA35: 122.3 | AB35: 121.3 | AC35: 121.6 | AD35: 123.8 | AE35: 130.6 | AF35: 130.8 | AG35: 132.3 | AH35: 132.8 | AI35: 130.1 | AJ35: 124 | AK35: 124.1 | AL35: 123.7 | AM35: 120.8 | AN35: 119 | AO35: 118.6 | AP35: 119.9 | AQ35: 131.1 | AR35: 133.5 | AS35: 135.5 | AT35: 137 | AU35: 135.8 | AV35: 132.5 | AW35: 130.4 | AX35: 130.8 | AY35: 129.3 | AZ35: 129.6 | BA35: 131.4 | BB35: 136.8 | BC35: 137.7 | BD35: 135.2 | BE35: 137.2 | BF35: 139.4 | BG35: 142.7 | BH35: 137.5 | BI35: 135.6 | BJ35: 136.4 | BK35: 135 | BL35: 133.8 | BM35: 135.5 | BN35: 138.5 | BO35: 150.1 | BP35: 151.3 | BQ35: 152.2 | BR35: 149.7 | BS35: 146.3 | BT35: 140 | BU35: 139.5 | BV35: 141.5 | BW35: 138.5 | BX35: 135.2 | BY35: 137 | BZ35: 139.4 | CA35: 149.7 | CB35: 150.9 | CC35: 154.7 | CD35: 153.9 | CE35: 149.8 | CF35: 150.6 | CG35: 148.8 | CH35: 147.2 | CI35: 144.4 | CJ35: 143.1 | CK35: 143.3 | CL35: 152.9 | CM35: NA | CN35: 151.8 | CO35: 151.8 | CP35: 154.5 | CQ35: 155.4 | CR35: 155.7 | CS35: 150.5 | CT35: 149.7 | CU35: 152.6 | CV35: 154 | CW35: 157.3 | CX35: 168.8 | CY35: 172.5 | CZ35: 171.5 | DA35: 170.9 | DB35: 161.3 | DC35: 161.2 | DD35: 159.3 | DE35: 160.3 | DF35: 158.3 | DG35: 156.5 | DH35: 156.4 | DI35: 159.6 | DJ35: 175.9 | DK35: 174.5 | DL35: 174.1 | DM35: 179.5 | DN35: 177.1 | DO35: 167.5 | DP35: 165.7 | DQ35: 162.6 | DR35: 159.5 | DS35: 160.5 | DT35: 172.1 | DU35: 172.1 | DV35: 179.2 | DW35: 175.8
A36: Urban | B36: =VLOOKUP(C36,'Broader Categories'!$A$1:$B$28,2,FALSE) -> Food | C36: Vegetables | D36: 102.9 | E36: 104.9 | F36: 103.8 | G36: 109.7 | H36: 123.7 | I36: 143.6 | J36: 160.9 | K36: 177 | L36: 174.3 | M36: 183.5 | N36: 192.8 | O36: 144.8 | P36: 118.9 | Q36: 111.5 | R36: 113.3 | S36: 121.2 | T36: 127 | U36: 137.5 | V36: 172.4 | W36: 181.9 | X36: 168.6 | Y36: 159.6 | Z36: 153.2 | AA36: 141 | AB36: 134.4 | AC36: 131.8 | AD36: 131.4 | AE36: 130.8 | AF36: 135.6 | AG36: 146.7 | AH36: 153.5 | AI36: 165.5 | AJ36: 168.5 | AK36: 165.8 | AL36: 164.6 | AM36: 149 | AN36: 144.1 | AO36: 129.2 | AP36: 128.1 | AQ36: 136.8 | AR36: 151.4 | AS36: 173.7 | AT36: 179.5 | AU36: 163.5 | AV36: 152.9 | AW36: 155.1 | AX36: 142 | AY36: 121.1 | AZ36: 118.7 | BA36: 120.2 | BB36: 122.2 | BC36: 127.1 | BD36: 129.2 | BE36: 142.2 | BF36: 175.1 | BG36: 179.8 | BH36: 160.7 | BI36: 173.2 | BJ36: 185.2 | BK36: 163.2 | BL36: 150.5 | BM36: 136.9 | BN36: 128 | BO36: 127.6 | BP36: 131.4 | BQ36: 144 | BR36: 159.2 | BS36: 157.3 | BT36: 151.3 | BU36: 153 | BV36: 145.2 | BW36: 132.4 | BX36: 130.5 | BY36: 131.6 | BZ36: 141.2 | CA36: 161.6 | CB36: 169.8 | CC36: 180.1 | CD36: 189.1 | CE36: 192.4 | CF36: 207.2 | CG36: 215.7 | CH36: 231.5 | CI36: 207.8 | CJ36: 181.7 | CK36: 167 | CL36: 180 | CM36: NA | CN36: 171.2 | CO36: 171.2 | CP36: 191.9 | CQ36: 202 | CR36: 226 | CS36: 245.3 | CT36: 240.9 | CU36: 206.8 | CV36: 180.2 | CW36: 166.1 | CX36: 161.6 | CY36: 166.5 | CZ36: 176.2 | DA36: 186.4 | DB36: 183.3 | DC36: 183.5 | DD36: 214.4 | DE36: 229.1 | DF36: 219.5 | DG36: 203.6 | DH36: 198 | DI36: 188.4 | DJ36: 190.7 | DK36: 203.2 | DL36: 211.5 | DM36: 208.5 | DN36: 213.1 | DO36: 220.8 | DP36: 228.6 | DQ36: 205.5 | DR36: 178.7 | DS36: 175.3 | DT36: 175.8 | DU36: 175.9 | DV36: 179.9 | DW36: 185
A37: Urban | B37: =VLOOKUP(C37,'Broader Categories'!$A$1:$B$28,2,FALSE) -> Food | C37: Pulses and products | D37: 105.8 | E37: 104.1 | F37: 103.5 | G37: 104.6 | H37: 105.2 | I37: 105.4 | J37: 105.1 | K37: 104.7 | L37: 105.1 | M37: 105.3 | N37: 106.3 | O37: 107.1 | P37: 107.5 | Q37: 108.2 | R37: 108.9 | S37: 111 | T37: 112.6 | U37: 112.8 | V37: 113.1 | W37: 115.2 | X37: 116.9 | Y37: 117.4 | Z37: 119.3 | AA37: 120.1 | AB37: 122.9 | AC37: 125.1 | AD37: 127.2 | AE37: 131.3 | AF37: 142.6 | AG37: 148.1 | AH37: 149.5 | AI37: 156 | AJ37: 165.4 | AK37: 187.2 | AL37: 191.6 | AM37: 190.1 | AN37: 184.2 | AO37: 176.4 | AP37: 170.3 | AQ37: 176.9 | AR37: 182.8 | AS37: 184.4 | AT37: 188.4 | AU37: 182.3 | AV37: 173.6 | AW37: 175.7 | AX37: 174.9 | AY37: 170.3 | AZ37: 155.1 | BA37: 143.1 | BB37: 135.8 | BC37: 133.8 | BD37: 131.5 | BE37: 128.2 | BF37: 124.7 | BG37: 123.5 | BH37: 124.5 | BI37: 124.1 | BJ37: 122.2 | BK37: 119.8 | BL37: 118.4 | BM37: 117 | BN37: 115.5 | BO37: 114 | BP37: 112.8 | BQ37: 112.3 | BR37: 112.6 | BS37: 113.6 | BT37: 113.5 | BU37: 113.2 | BV37: 115.3 | BW37: 117.5 | BX37: 118.2 | BY37: 119.9 | BZ37: 120.7 | CA37: 124.4 | CB37: 127.4 | CC37: 128.9 | CD37: 129.8 | CE37: 130.3 | CF37: 131.2 | CG37: 134.6 | CH37: 137.2 | CI37: 139.1 | CJ37: 139.6 | CK37: 139.7 | CL37: 150.8 | CM37: NA | CN37: 152 | CO37: 152 | CP37: 151.3 | CQ37: 150.8 | CR37: 152.2 | CS37: 158.7 | CT37: 161.5 | CU37: 162.1 | CV37: 159.8 | CW37: 161.1 | CX37: 162.8 | CY37: 165.9 | CZ37: 166.9 | DA37: 164.7 | DB37: 164.5 | DC37: 164.5 | DD37: 165.3 | DE37: 165.1 | DF37: 164.2 | DG37: 163.8 | DH37: 163.2 | DI37: 163.4 | DJ37: 164 | DK37: 164.1 | DL37: 163.6 | DM37: 164 | DN37: 167.3 | DO37: 169.2 | DP37: 169.9 | DQ37: 171 | DR37: 171.3 | DS37: 171.2 | DT37: 172.2 | DU37: 172.2 | DV37: 174.7 | DW37: 176.9
A38: Urban | B38: =VLOOKUP(C38,'Broader Categories'!$A$1:$B$28,2,FALSE) -> Food | C38: Sugar and Confectionery | D38: 105.1 | E38: 103.8 | F38: 102.6 | G38: 102 | H38: 101.9 | I38: 101.4 | J38: 101.3 | K38: 101 | L38: 100.8 | M38: 100.2 | N38: 99.5 | O38: 98.6 | P38: 96.9 | Q38: 95.4 | R38: 96.3 | S38: 100.3 | T38: 101.3 | U38: 101.4 | V38: 102.7 | W38: 102.7 | X38: 101.9 | Y38: 101.2 | Z38: 99.8 | AA38: 97.8 | AB38: 96.1 | AC38: 95 | AD38: 93.2 | AE38: 91.6 | AF38: 90.8 | AG38: 89.8 | AH38: 85.7 | AI38: 85.3 | AJ38: 86.3 | AK38: 89.4 | AL38: 90.8 | AM38: 92.7 | AN38: 96.7 | AO38: 99.1 | AP38: 101.8 | AQ38: 109.1 | AR38: 111.1 | AS38: 112 | AT38: 113.3 | AU38: 114.6 | AV38: 115.1 | AW38: 115.4 | AX38: 115.6 | AY38: 115.5 | AZ38: 117.3 | BA38: 119.5 | BB38: 120.3 | BC38: 120.8 | BD38: 121 | BE38: 120.9 | BF38: 121.5 | BG38: 122.1 | BH38: 122.4 | BI38: 122.6 | BJ38: 123.9 | BK38: 120.7 | BL38: 117.3 | BM38: 115.4 | BN38: 114.2 | BO38: 110.6 | BP38: 105.3 | BQ38: 108.4 | BR38: 111.8 | BS38: 113.3 | BT38: 112.3 | BU38: 112.8 | BV38: 112.5 | BW38: 111 | BX38: 110.4 | BY38: 110.4 | BZ38: 110.4 | CA38: 111.2 | CB38: 111.8 | CC38: 111.8 | CD38: 112.7 | CE38: 114 | CF38: 114.8 | CG38: 115 | CH38: 114.7 | CI38: 114.8 | CJ38: 114.6 | CK38: 114.4 | CL38: 121.2 | CM38: NA | CN38: 116.3 | CO38: 116.3 | CP38: 116.8 | CQ38: 118.9 | CR38: 118.1 | CS38: 117.2 | CT38: 117.1 | CU38: 116.3 | CV38: 114.9 | CW38: 114.3 | CX38: 114.8 | CY38: 115.9 | CZ38: 116.1 | DA38: 115.7 | DB38: 120.4 | DC38: 120.4 | DD38: 122.5 | DE38: 123.1 | DF38: 121.9 | DG38: 121.3 | DH38: 120.6 | DI38: 120.3 | DJ38: 120.5 | DK38: 121.2 | DL38: 121.4 | DM38: 121.5 | DN38: 122.2 | DO38: 123.1 | DP38: 123.4 | DQ38: 123.4 | DR38: 123.1 | DS38: 122.7 | DT38: 121.9 | DU38: 121.9 | DV38: 123.1 | DW38: 124.2
A39: Urban | B39: =VLOOKUP(C39,'Broader Categories'!$A$1:$B$28,2,FALSE) -> Food | C39: Spices | D39: 101.8 | E39: 102.3 | F39: 102.4 | G39: 103.5 | H39: 105 | I39: 106.4 | J39: 107.5 | K39: 108.5 | L39: 109.1 | M39: 109.6 | N39: 110.3 | O39: 111.9 | P39: 112.7 | Q39: 113.5 | R39: 114.1 | S39: 115.3 | T39: 117 | U39: 118.3 | V39: 120 | W39: 122.1 | X39: 122.9 | Y39: 123.8 | Z39: 124.6 | AA39: 125.4 | AB39: 126.6 | AC39: 127.7 | AD39: 127.4 | AE39: 127.7 | AF39: 128.8 | AG39: 130.5 | AH39: 131.5 | AI39: 132.7 | AJ39: 134.4 | AK39: 135.8 | AL39: 137.1 | AM39: 138.6 | AN39: 139.5 | AO39: 139.7 | AP39: 140.1 | AQ39: 140.4 | AR39: 141.5 | AS39: 142.8 | AT39: 143.9 | AU39: 144.6 | AV39: 144.8 | AW39: 145.3 | AX39: 145.4 | AY39: 145.5 | AZ39: 144.9 | BA39: 144 | BB39: 142.6 | BC39: 141.3 | BD39: 139.9 | BE39: 138.8 | BF39: 137.8 | BG39: 137.5 | BH39: 137.3 | BI39: 137.8 | BJ39: 138.3 | BK39: 139.7 | BL39: 140.5 | BM39: 140.7 | BN39: 140.7 | BO39: 140.2 | BP39: 139.6 | BQ39: 140 | BR39: 140.3 | BS39: 141.1 | BT39: 141.2 | BU39: 141.1 | BV39: 141.4 | BW39: 141.5 | BX39: 140.4 | BY39: 140.8 | BZ39: 140.7 | CA39: 141 | CB39: 141 | CC39: 141.6 | CD39: 142.5 | CE39: 143.8 | CF39: 145.2 | CG39: 146.3 | CH39: 148 | CI39: 149.5 | CJ39: 150.4 | CK39: 151.5 | CL39: 154 | CM39: NA | CN39: 158.8 | CO39: 158.8 | CP39: 160 | CQ39: 160.9 | CR39: 161.3 | CS39: 161.4 | CT39: 161.9 | CU39: 163 | CV39: 162.5 | CW39: 162.6 | CX39: 162.8 | CY39: 165.2 | CZ39: 165.5 | DA39: 165.5 | DB39: 166.2 | DC39: 166.2 | DD39: 166.8 | DE39: 167.2 | DF39: 168.2 | DG39: 169.8 | DH39: 172.2 | DI39: 174.7 | DJ39: 178 | DK39: 181.4 | DL39: 183.5 | DM39: 186.3 | DN39: 189.7 | DO39: 193.6 | DP39: 196.4 | DQ39: 198.8 | DR39: 200.5 | DS39: 204.3 | DT39: 204.8 | DU39: 204.8 | DV39: 207.8 | DW39: 211.9
A40: Urban | B40: =VLOOKUP(C40,'Broader Categories'!$A$1:$B$28,2,FALSE) -> Food | C40: Non-alcoholic beverages | D40: 105.1 | E40: 106 | F40: 107 | G40: 108.2 | H40: 109.1 | I40: 110 | J40: 110.4 | K40: 110.9 | L40: 111.1 | M40: 111.4 | N40: 111.8 | O40: 112.1 | P40: 112.1 | Q40: 112.1 | R40: 112.2 | S40: 112.7 | T40: 112.9 | U40: 113.2 | V40: 113.8 | W40: 114.4 | X40: 114.8 | Y40: 115.2 | Z40: 115.8 | AA40: 116.1 | AB40: 116.5 | AC40: 116.8 | AD40: 117 | AE40: 117.2 | AF40: 117.7 | AG40: 118 | AH40: 118.3 | AI40: 118.8 | AJ40: 119.1 | AK40: 119.4 | AL40: 119.8 | AM40: 120.2 | AN40: 120.5 | AO40: 120.6 | AP40: 120.7 | AQ40: 121.1 | AR40: 121.5 | AS40: 121.6 | AT40: 121.7 | AU40: 121.9 | AV40: 122.1 | AW40: 122.5 | AX40: 122.7 | AY40: 123.1 | AZ40: 123.2 | BA40: 123.4 | BB40: 123.6 | BC40: 123.8 | BD40: 123.8 | BE40: 124.2 | BF40: 124.4 | BG40: 124.6 | BH40: 124.8 | BI40: 125.1 | BJ40: 125.4 | BK40: 125.7 | BL40: 125.9 | BM40: 125.9 | BN40: 126.2 | BO40: 126.5 | BP40: 126.6 | BQ40: 126.7 | BR40: 126.8 | BS40: 127.4 | BT40: 127.7 | BU40: 127.6 | BV40: 128 | BW40: 128.1 | BX40: 128.1 | BY40: 128.3 | BZ40: 128.5 | CA40: 128.9 | CB40: 129 | CC40: 129.5 | CD40: 129.8 | CE40: 130 | CF40: 130.2 | CG40: 130.5 | CH40: 130.8 | CI40: 131.1 | CJ40: 131.5 | CK40: 131.9 | CL40: 133.5 | CM40: NA | CN40: 135.6 | CO40: 135.6 | CP40: 136.5 | CQ40: 137.7 | CR40: 139.2 | CS40: 141.5 | CT40: 143.3 | CU40: 145.9 | CV40: 149.2 | CW40: 150.7 | CX40: 151.5 | CY40: 152 | CZ40: 152.3 | DA40: 153.4 | DB40: 154.8 | DC40: 154.8 | DD40: 155.4 | DE40: 156.1 | DF40: 156.5 | DG40: 156.6 | DH40: 156.7 | DI40: 157.1 | DJ40: 157.5 | DK40: 158.5 | DL40: 159.1 | DM40: 159.8 | DN40: 160.5 | DO40: 161.1 | DP40: 161.6 | DQ40: 162.1 | DR40: 162.8 | DS40: 163.7 | DT40: 164.9 | DU40: 164.9 | DV40: 165.5 | DW40: 165.9
A41: Urban | B41: =VLOOKUP(C41,'Broader Categories'!$A$1:$B$28,2,FALSE) -> Food | C41: Prepared meals, snacks, sweets etc. | D41: 107.9 | E41: 109 | F41: 109.8 | G41: 110.6 | H41: 111.3 | I41: 112.2 | J41: 113.1 | K41: 114.3 | L41: 115.4 | M41: 116 | N41: 117.1 | O41: 118.1 | P41: 119 | Q41: 119.9 | R41: 120.5 | S41: 121 | T41: 121.7 | U41: 122.4 | V41: 123.4 | W41: 124.7 | X41: 125.2 | Y41: 125.9 | Z41: 126.9 | AA41: 127.6 | AB41: 128 | AC41: 128.6 | AD41: 129.2 | AE41: 129.5 | AF41: 129.9 | AG41: 130.5 | AH41: 131.1 | AI41: 131.7 | AJ41: 132.3 | AK41: 132.9 | AL41: 133.7 | AM41: 134.2 | AN41: 134.7 | AO41: 135.2 | AP41: 135.4 | AQ41: 135.9 | AR41: 136.3 | AS41: 136.9 | AT41: 137.5 | AU41: 138.1 | AV41: 138.8 | AW41: 139.6 | AX41: 140.3 | AY41: 140.9 | AZ41: 141.6 | BA41: 141.9 | BB41: 142.4 | BC41: 142.6 | BD41: 142.9 | BE41: 143.1 | BF41: 143.7 | BG41: 144.5 | BH41: 145 | BI41: 145.5 | BJ41: 146 | BK41: 146.3 | BL41: 146.8 | BM41: 147.1 | BN41: 147.6 | BO41: 148.3 | BP41: 148.7 | BQ41: 149 | BR41: 149.4 | BS41: 150.4 | BT41: 151.3 | BU41: 152 | BV41: 152.6 | BW41: 152.9 | BX41: 153.2 | BY41: 153.5 | BZ41: 153.9 | CA41: 154.5 | CB41: 155.1 | CC41: 155.6 | CD41: 156.2 | CE41: 156.4 | CF41: 156.8 | CG41: 157.2 | CH41: 157.7 | CI41: 158.5 | CJ41: 159 | CK41: 159.1 | CL41: NA | CM41: NA | CN41: 161.7 | CO41: 161.7 | CP41: 163.3 | CQ41: 164.4 | CR41: 164.8 | CS41: 165.1 | CT41: 166.1 | CU41: 167.2 | CV41: 169.4 | CW41: 170.3 | CX41: 171.4 | CY41: 171.1 | CZ41: 173.3 | DA41: 173.5 | DB41: 175.1 | DC41: 175.1 | DD41: 175.9 | DE41: 176.8 | DF41: 178.2 | DG41: 179 | DH41: 180 | DI41: 181.5 | DJ41: 183.3 | DK41: 184.9 | DL41: 186.3 | DM41: 187.7 | DN41: 188.9 | DO41: 190.4 | DP41: 191.5 | DQ41: 192.4 | DR41: 193.3 | DS41: 194.3 | DT41: 196.6 | DU41: 196.6 | DV41: 197 | DW41: 197.7
A42: Urban | B42: =VLOOKUP(C42,'Broader Categories'!$A$1:$B$28,2,FALSE) -> Food | C42: Food and beverages | D42: 105.9 | E42: 107.2 | F42: 107.3 | G42: 108.8 | H42: 111.1 | I42: 115 | J42: 117.5 | K42: 119.6 | L42: 119.2 | M42: 120.8 | N42: 122.9 | O42: 117.8 | P42: 115.5 | Q42: 115.2 | R42: 116 | S42: 118.2 | T42: 120 | U42: 122 | V42: 127.1 | W42: 128.9 | X42: 126.7 | Y42: 125.8 | Z42: 125.4 | AA42: 124 | AB42: 123.5 | AC42: 123.7 | AD42: 123.9 | AE42: 124.6 | AF42: 126.1 | AG42: 128.5 | AH42: 129.5 | AI42: 131.1 | AJ42: 131.5 | AK42: 132.6 | AL42: 133.3 | AM42: 131.5 | AN42: 131.2 | AO42: 129.1 | AP42: 128.9 | AQ42: 131.8 | AR42: 134.6 | AS42: 138.2 | AT42: 139.8 | AU42: 137.6 | AV42: 135.7 | AW42: 136.3 | AX42: 135.2 | AY42: 132.8 | AZ42: 132 | BA42: 132.1 | BB42: 132.6 | BC42: 133.4 | BD42: 133.6 | BE42: 135.7 | BF42: 139.8 | BG42: 140.5 | BH42: 138 | BI42: 139.7 | BJ42: 141.5 | BK42: 138.8 | BL42: 137.2 | BM42: 135.6 | BN42: 134.8 | BO42: 135.7 | BP42: 136.4 | BQ42: 138.4 | BR42: 140.3 | BS42: 140.1 | BT42: 138.9 | BU42: 139.4 | BV42: 139.1 | BW42: 137.6 | BX42: 137.3 | BY42: 138 | BZ42: 139.6 | CA42: 143.8 | CB42: 145.6 | CC42: 147.7 | CD42: 149.1 | CE42: 149.5 | CF42: 151.9 | CG42: 153.6 | CH42: 156.3 | CI42: 154.4 | CJ42: 151.7 | CK42: 150.1 | CL42: 153.5 | CM42: NA | CN42: 157 | CO42: 157 | CP42: 159.9 | CQ42: 161.3 | CR42: 164.4 | CS42: 167 | CT42: 167 | CU42: 163.4 | CV42: 160.8 | CW42: 160.4 | CX42: 162 | CY42: 164.2 | CZ42: 166.2 | DA42: 167.9 | DB42: 167.3 | DC42: 167.3 | DD42: 171.5 | DE42: 173.5 | DF42: 172.2 | DG42: 170.3 | DH42: 170.2 | DI42: 171.5 | DJ42: 174.5 | DK42: 177.5 | DL42: 179.3 | DM42: 179.4 | DN42: 180.4 | DO42: 181.8 | DP42: 183.3 | DQ42: 181.3 | DR42: 178.6 | DS42: 179.5 | DT42: 180.7 | DU42: 180.8 | DV42: 182.1 | DW42: 183.1
A43: Urban | B43: =VLOOKUP(C43,'Broader Categories'!$A$1:$B$28,2,FALSE) -> Food | C43: Pan, tobacco and intoxicants | D43: 105.2 | E43: 106 | F43: 106.8 | G43: 108.5 | H43: 109.8 | I43: 110.9 | J43: 111.7 | K43: 112.4 | L43: 112.9 | M43: 113.5 | N43: 114.1 | O43: 115 | P43: 115.7 | Q43: 116.2 | R43: 116.7 | S43: 117.6 | T43: 118.3 | U43: 119 | V43: 121 | W43: 123 | X43: 124.3 | Y43: 124.3 | Z43: 125.8 | AA43: 126.4 | AB43: 127.4 | AC43: 128.1 | AD43: 128.8 | AE43: 130.1 | AF43: 131.3 | AG43: 132.1 | AH43: 133.1 | AI43: 134.2 | AJ43: 134.7 | AK43: 135.3 | AL43: 137.6 | AM43: 138.2 | AN43: 139.5 | AO43: 140 | AP43: 140.6 | AQ43: 141.5 | AR43: 142.2 | AS43: 142.7 | AT43: 142.9 | AU43: 143.6 | AV43: 143.9 | AW43: 144.3 | AX43: 144.3 | AY43: 145 | AZ43: 145.6 | BA43: 146.3 | BB43: 147.5 | BC43: 148 | BD43: 148.3 | BE43: 148.6 | BF43: 150.5 | BG43: 152.1 | BH43: 153.6 | BI43: 154.6 | BJ43: 156.2 | BK43: 157 | BL43: 157.7 | BM43: 159.3 | BN43: 159.7 | BO43: 159.2 | BP43: 160.3 | BQ43: 161 | BR43: 161.4 | BS43: 162.1 | BT43: 163.3 | BU43: 164 | BV43: 164.4 | BW43: 164.6 | BX43: 164.7 | BY43: 164.9 | BZ43: 165.3 | CA43: 166.2 | CB43: 166.7 | CC43: 167.2 | CD43: 167.9 | CE43: 168.6 | CF43: 169.3 | CG43: 169.9 | CH43: 170.4 | CI43: 170.8 | CJ43: 172 | CK43: 173.3 | CL43: NA | CM43: NA | CN43: 186.7 | CO43: 186.7 | CP43: 187.2 | CQ43: 188.7 | CR43: 188.7 | CS43: 188.8 | CT43: 190.2 | CU43: 191.8 | CV43: 193.3 | CW43: 193.5 | CX43: 194.4 | CY43: 198.2 | CZ43: 195.6 | DA43: 195.5 | DB43: 196.5 | DC43: 196.5 | DD43: 197 | DE43: 197 | DF43: 196.8 | DG43: 196.4 | DH43: 196.5 | DI43: 197.5 | DJ43: 197.1 | DK43: 197.5 | DL43: 198.3 | DM43: 198.6 | DN43: 198.7 | DO43: 199.7 | DP43: 200.1 | DQ43: 200.6 | DR43: 201.1 | DS43: 201.6 | DT43: 202.7 | DU43: 202.7 | DV43: 203.5 | DW43: 204.2
A44: Urban | B44: =VLOOKUP(C44,'Broader Categories'!$A$1:$B$28,2,FALSE) -> Apparels | C44: Clothing | D44: 105.9 | E44: 106.6 | F44: 107.2 | G44: 107.9 | H44: 108.5 | I44: 109.2 | J44: 109.8 | K44: 110.6 | L44: 111.4 | M44: 112.5 | N44: 113.5 | O44: 114.2 | P44: 114.8 | Q44: 115.3 | R44: 115.8 | S44: 116.3 | T44: 116.8 | U44: 117.4 | V44: 118 | W44: 118.6 | X44: 119.2 | Y44: 119.6 | Z44: 120.3 | AA44: 120.7 | AB44: 121 | AC44: 121.3 | AD44: 121.7 | AE44: 122.1 | AF44: 122.4 | AG44: 123.2 | AH44: 123.5 | AI44: 123.7 | AJ44: 124 | AK44: 124.4 | AL44: 125 | AM44: 125.4 | AN44: 125.8 | AO44: 126.2 | AP44: 126.4 | AQ44: 126.8 | AR44: 127.2 | AS44: 127.6 | AT44: 127.9 | AU44: 128.3 | AV44: 128.7 | AW44: 129.1 | AX44: 129.6 | AY44: 130 | AZ44: 130.2 | BA44: 130.5 | BB44: 130.8 | BC44: 131.2 | BD44: 131.5 | BE44: 131.5 | BF44: 131.6 | BG44: 132.7 | BH44: 133.3 | BI44: 134 | BJ44: 135 | BK44: 135.6 | BL44: 136 | BM44: 136.3 | BN44: 136.7 | BO44: 137.8 | BP44: 138.6 | BQ44: 138.9 | BR44: 139.6 | BS44: 140 | BT44: 140.8 | BU44: 141.5 | BV44: 142.4 | BW44: 142.7 | BX44: 143 | BY44: 143.3 | BZ44: 143.5 | CA44: 144 | CB44: 144.3 | CC44: 144.7 | CD44: 145 | CE44: 145.3 | CF44: 145.9 | CG44: 146.3 | CH44: 146.8 | CI44: 147 | CJ44: 147.3 | CK44: 147.7 | CL44: NA | CM44: NA | CN44: 149.1 | CO44: 149.1 | CP44: 150 | CQ44: 150.2 | CR44: 150.5 | CS44: 151.1 | CT44: 151.9 | CU44: 152.5 | CV44: 154.2 | CW44: 155.1 | CX44: 155.9 | CY44: 156.5 | CZ44: 157.3 | DA44: 157.9 | DB44: 159.8 | DC44: 159.8 | DD44: 160.8 | DE44: 162.3 | DF44: 163.3 | DG44: 164.7 | DH44: 165.7 | DI44: 167.1 | DJ44: 168.4 | DK44: 170 | DL44: 171.6 | DM44: 172.7 | DN44: 173.7 | DO44: 175 | DP44: 175.5 | DQ44: 176.7 | DR44: 177.7 | DS44: 178.7 | DT44: 180.3 | DU44: 180.2 | DV44: 181 | DW44: 181.3
A45: Urban | B45: =VLOOKUP(C45,'Broader Categories'!$A$1:$B$28,2,FALSE) -> Apparels | C45: Footwear | D45: 105 | E45: 105.5 | F45: 106 | G45: 106.4 | H45: 106.7 | I45: 107.2 | J45: 107.8 | K45: 108.3 | L45: 109 | M45: 109.7 | N45: 110.3 | O45: 110.9 | P45: 111.3 | Q45: 111.7 | R45: 112.1 | S45: 112.5 | T45: 112.9 | U45: 113.2 | V45: 113.6 | W45: 114.1 | X45: 114.5 | Y45: 114.9 | Z45: 115.4 | AA45: 115.8 | AB45: 116.1 | AC45: 116.5 | AD45: 116.9 | AE45: 117.2 | AF45: 117.4 | AG45: 117.6 | AH45: 117.9 | AI45: 118.2 | AJ45: 118.6 | AK45: 118.8 | AL45: 119.3 | AM45: 119.5 | AN45: 119.8 | AO45: 120.1 | AP45: 120.3 | AQ45: 120.5 | AR45: 120.7 | AS45: 121.1 | AT45: 121.1 | AU45: 121.4 | AV45: 121.6 | AW45: 121.9 | AX45: 122.1 | AY45: 122.2 | AZ45: 122.3 | BA45: 122.5 | BB45: 122.8 | BC45: 123 | BD45: 123.2 | BE45: 123.2 | BF45: 123.7 | BG45: 124.3 | BH45: 124.6 | BI45: 124.9 | BJ45: 125.4 | BK45: 125.6 | BL45: 125.9 | BM45: 126.1 | BN45: 126.7 | BO45: 127.4 | BP45: 127.9 | BQ45: 128.7 | BR45: 128.9 | BS45: 129 | BT45: 129.3 | BU45: 129.8 | BV45: 130.2 | BW45: 130.3 | BX45: 130.4 | BY45: 130.8 | BZ45: 131.2 | CA45: 131.7 | CB45: 131.7 | CC45: 131.9 | CD45: 132.2 | CE45: 132.2 | CF45: 132.4 | CG45: 132.6 | CH45: 132.8 | CI45: 133.2 | CJ45: 133.5 | CK45: 133.8 | CL45: NA | CM45: NA | CN45: 136.6 | CO45: 136.6 | CP45: 135.2 | CQ45: 136.3 | CR45: 136.1 | CS45: 136.4 | CT45: 136.7 | CU45: 137.3 | CV45: 138.2 | CW45: 138.7 | CX45: 139.3 | CY45: 140.2 | CZ45: 140.5 | DA45: 141.9 | DB45: 143.6 | DC45: 143.6 | DD45: 144.4 | DE45: 145.3 | DF45: 146.7 | DG45: 148.5 | DH45: 150.4 | DI45: 152.6 | DJ45: 154.5 | DK45: 155.9 | DL45: 157.4 | DM45: 158.7 | DN45: 160 | DO45: 161.7 | DP45: 162.6 | DQ45: 163.5 | DR45: 164.5 | DS45: 165.3 | DT45: 167 | DU45: 167 | DV45: 167.7 | DW45: 168.1
A46: Urban | B46: =VLOOKUP(C46,'Broader Categories'!$A$1:$B$28,2,FALSE) -> Apparels | C46: Clothing and footwear | D46: 105.8 | E46: 106.4 | F46: 107 | G46: 107.7 | H46: 108.3 | I46: 108.9 | J46: 109.5 | K46: 110.2 | L46: 111.1 | M46: 112 | N46: 113 | O46: 113.7 | P46: 114.3 | Q46: 114.7 | R46: 115.2 | S46: 115.7 | T46: 116.2 | U46: 116.7 | V46: 117.4 | W46: 117.9 | X46: 118.4 | Y46: 118.9 | Z46: 119.5 | AA46: 120 | AB46: 120.2 | AC46: 120.6 | AD46: 120.9 | AE46: 121.3 | AF46: 121.6 | AG46: 122.3 | AH46: 122.7 | AI46: 122.9 | AJ46: 123.2 | AK46: 123.6 | AL46: 124.2 | AM46: 124.5 | AN46: 124.9 | AO46: 125.3 | AP46: 125.5 | AQ46: 125.8 | AR46: 126.2 | AS46: 126.6 | AT46: 126.9 | AU46: 127.3 | AV46: 127.7 | AW46: 128 | AX46: 128.5 | AY46: 128.8 | AZ46: 129 | BA46: 129.3 | BB46: 129.6 | BC46: 130 | BD46: 130.2 | BE46: 130.2 | BF46: 130.4 | BG46: 131.4 | BH46: 132 | BI46: 132.6 | BJ46: 133.5 | BK46: 134 | BL46: 134.4 | BM46: 134.7 | BN46: 135.2 | BO46: 136.2 | BP46: 137 | BQ46: 137.4 | BR46: 137.9 | BS46: 138.3 | BT46: 139.1 | BU46: 139.7 | BV46: 140.5 | BW46: 140.8 | BX46: 141.1 | BY46: 141.4 | BZ46: 141.6 | CA46: 142.2 | CB46: 142.4 | CC46: 142.7 | CD46: 143 | CE46: 143.3 | CF46: 143.9 | CG46: 144.2 | CH46: 144.6 | CI46: 144.9 | CJ46: 145.2 | CK46: 145.6 | CL46: NA | CM46: NA | CN46: 147.2 | CO46: 147.2 | CP46: 147.8 | CQ46: 148.1 | CR46: 148.3 | CS46: 148.8 | CT46: 149.6 | CU46: 150.2 | CV46: 151.8 | CW46: 152.6 | CX46: 153.4 | CY46: 154.1 | CZ46: 154.8 | DA46: 155.5 | DB46: 157.3 | DC46: 157.4 | DD46: 158.3 | DE46: 159.7 | DF46: 160.7 | DG46: 162.2 | DH46: 163.4 | DI46: 164.9 | DJ46: 166.3 | DK46: 167.8 | DL46: 169.4 | DM46: 170.6 | DN46: 171.6 | DO46: 173 | DP46: 173.6 | DQ46: 174.7 | DR46: 175.7 | DS46: 176.6 | DT46: 178.2 | DU46: 178.2 | DV46: 178.9 | DW46: 179.3
A47: Urban | B47: =VLOOKUP(C47,'Broader Categories'!$A$1:$B$28,2,FALSE) -> Home | C47: Housing | D47: 100.3 | E47: 100.4 | F47: 100.4 | G47: 100.5 | H47: 100.5 | I47: 106.6 | J47: 107.7 | K47: 108.9 | L47: 109.7 | M47: 110.5 | N47: 111.1 | O47: 110.7 | P47: 111.6 | Q47: 112.5 | R47: 113.2 | S47: 113.9 | T47: 114.3 | U47: 113.9 | V47: 114.8 | W47: 115.5 | X47: 116.1 | Y47: 116.7 | Z47: 117.1 | AA47: 116.5 | AB47: 117.3 | AC47: 118.1 | AD47: 118.6 | AE47: 119.2 | AF47: 119.6 | AG47: 119 | AH47: 119.9 | AI47: 120.9 | AJ47: 121.6 | AK47: 122.4 | AL47: 122.9 | AM47: 122.4 | AN47: 123.4 | AO47: 124.4 | AP47: 124.9 | AQ47: 125.6 | AR47: 126 | AS47: 125.5 | AT47: 126.4 | AU47: 127.3 | AV47: 127.9 | AW47: 128.7 | AX47: 129.1 | AY47: 128.5 | AZ47: 129.6 | BA47: 130.5 | BB47: 131.1 | BC47: 131.7 | BD47: 132.1 | BE47: 131.4 | BF47: 132.6 | BG47: 134.4 | BH47: 135.7 | BI47: 137.3 | BJ47: 138.6 | BK47: 139.1 | BL47: 140.4 | BM47: 141.3 | BN47: 142 | BO47: 142.9 | BP47: 143.2 | BQ47: 142.5 | BR47: 143.6 | BS47: 144.6 | BT47: 145.3 | BU47: 146.3 | BV47: 146.9 | BW47: 146.5 | BX47: 147.7 | BY47: 148.5 | BZ47: 149 | CA47: 150.1 | CB47: 149.4 | CC47: 150.6 | CD47: 151.6 | CE47: 152.2 | CF47: 153 | CG47: 153.5 | CH47: 152.8 | CI47: 153.9 | CJ47: 154.8 | CK47: 154.5 | CL47: 155.6 | CM47: NA | CN47: 154.7 | CO47: 154.7 | CP47: 155.5 | CQ47: 156.3 | CR47: 156.5 | CS47: 158 | CT47: 158.4 | CU47: 157.7 | CV47: 159.8 | CW47: 159.9 | CX47: 161.4 | CY47: 161.6 | CZ47: 160.5 | DA47: 161.5 | DB47: 162.1 | DC47: 162.1 | DD47: 163.6 | DE47: 164.2 | DF47: 163.4 | DG47: 164.5 | DH47: 165.5 | DI47: 165.3 | DJ47: 167 | DK47: 167.5 | DL47: 166.8 | DM47: 167.8 | DN47: 169 | DO47: 169.5 | DP47: 171.2 | DQ47: 171.8 | DR47: 170.7 | DS47: 172.1 | DT47: 173.5 | DU47: 173.5 | DV47: 175.2 | DW47: 175.6
A48: Urban | B48: =VLOOKUP(C48,'Broader Categories'!$A$1:$B$28,2,FALSE) -> Home | C48: Fuel and light | D48: 105.4 | E48: 105.7 | F48: 106 | G48: 106.4 | H48: 107.2 | I48: 108 | J48: 108.6 | K48: 109.3 | L48: 109.5 | M48: 109.7 | N48: 110 | O48: 110.4 | P48: 111 | Q48: 111.1 | R48: 110.9 | S48: 110.9 | T48: 111.1 | U48: 111.2 | V48: 111.6 | W48: 111.8 | X48: 111.8 | Y48: 112 | Z48: 112.6 | AA48: 113 | AB48: 113.4 | AC48: 114 | AD48: 114.4 | AE48: 114.7 | AF48: 114.9 | AG48: 115.1 | AH48: 115.3 | AI48: 115.3 | AJ48: 115.1 | AK48: 114.9 | AL48: 115.1 | AM48: 116 | AN48: 116.9 | AO48: 116 | AP48: 114.8 | AQ48: 114.6 | AR48: 115 | AS48: 115.5 | AT48: 115.5 | AU48: 114.7 | AV48: 114.8 | AW48: 115.2 | AX48: 116.2 | AY48: 117.8 | AZ48: 118 | BA48: 119.2 | BB48: 120.8 | BC48: 121.4 | BD48: 120.1 | BE48: 119 | BF48: 119.7 | BG48: 118.9 | BH48: 120.6 | BI48: 122.6 | BJ48: 125.7 | BK48: 126.8 | BL48: 127.3 | BM48: 127.3 | BN48: 126.4 | BO48: 124.6 | BP48: 124.7 | BQ48: 126.5 | BR48: 128.1 | BS48: 129.8 | BT48: 131.2 | BU48: 133.4 | BV48: 136.7 | BW48: 132.4 | BX48: 128.6 | BY48: 127.1 | BZ48: 128.8 | CA48: 129.4 | CB48: 130.5 | CC48: 127 | CD48: 125.5 | CE48: 126.6 | CF48: 128.9 | CG48: 132.2 | CH48: 133.6 | CI48: 135.1 | CJ48: 138.9 | CK48: 141.4 | CL48: 137.1 | CM48: NA | CN48: 137.1 | CO48: 137.1 | CP48: 138.3 | CQ48: 137.2 | CR48: 137.1 | CS48: 137.3 | CT48: 137.9 | CU48: 142.9 | CV48: 149.1 | CW48: 154.8 | CX48: 154.9 | CY48: 155.5 | CZ48: 156.1 | DA48: 157.7 | DB48: 160.7 | DC48: 160.8 | DD48: 162.2 | DE48: 161.6 | DF48: 161.7 | DG48: 161.6 | DH48: 163 | DI48: 164.5 | DJ48: 170.5 | DK48: 173.5 | DL48: 174.9 | DM48: 179.5 | DN48: 178.4 | DO48: 179.2 | DP48: 180 | DQ48: 180.3 | DR48: 180.6 | DS48: 180.1 | DT48: 182.8 | DU48: 182.6 | DV48: 182.1 | DW48: 183.4
A49: Urban | B49: =VLOOKUP(C49,'Broader Categories'!$A$1:$B$28,2,FALSE) -> Home | C49: Household goods and services | D49: 104.8 | E49: 105.2 | F49: 105.7 | G49: 106.5 | H49: 107.1 | I49: 107.7 | J49: 108.1 | K49: 108.7 | L49: 109.6 | M49: 110.2 | N49: 110.9 | O49: 111.3 | P49: 111.9 | Q49: 112.6 | R49: 113 | S49: 113.4 | T49: 114.1 | U49: 114.3 | V49: 114.9 | W49: 115.3 | X49: 115.5 | Y49: 115.8 | Z49: 116.4 | AA49: 116.8 | AB49: 117.2 | AC49: 117.7 | AD49: 118 | AE49: 118.4 | AF49: 118.7 | AG49: 119.2 | AH49: 119.5 | AI49: 120 | AJ49: 120.4 | AK49: 120.7 | AL49: 121 | AM49: 121 | AN49: 121.6 | AO49: 121.8 | AP49: 122.3 | AQ49: 122.8 | AR49: 123.2 | AS49: 123.2 | AT49: 123.5 | AU49: 123.9 | AV49: 124.3 | AW49: 124.5 | AX49: 124.7 | AY49: 125 | AZ49: 125.1 | BA49: 125.3 | BB49: 125.6 | BC49: 126 | BD49: 126.5 | BE49: 126.8 | BF49: 127.2 | BG49: 127.7 | BH49: 128.1 | BI49: 128.3 | BJ49: 128.8 | BK49: 129.3 | BL49: 129.5 | BM49: 129.9 | BN49: 130.8 | BO49: 131.8 | BP49: 132.5 | BQ49: 133.1 | BR49: 133.6 | BS49: 134.4 | BT49: 134.9 | BU49: 135.1 | BV49: 135.8 | BW49: 136.2 | BX49: 136.3 | BY49: 136.6 | BZ49: 136.8 | CA49: 137.2 | CB49: 137.4 | CC49: 137.7 | CD49: 138.1 | CE49: 138.3 | CF49: 138.7 | CG49: 139.1 | CH49: 139.8 | CI49: 140.1 | CJ49: 140.4 | CK49: 140.8 | CL49: NA | CM49: NA | CN49: 140.4 | CO49: 140.4 | CP49: 144.5 | CQ49: 145.4 | CR49: 145.1 | CS49: 145.1 | CT49: 145.5 | CU49: 145.7 | CV49: 146.5 | CW49: 147.2 | CX49: 147.6 | CY49: 150.1 | CZ49: 149.8 | DA49: 150.7 | DB49: 153.2 | DC49: 153.3 | DD49: 154.3 | DE49: 155.2 | DF49: 156 | DG49: 156.8 | DH49: 157.4 | DI49: 158.6 | DJ49: 159.8 | DK49: 161.1 | DL49: 162.1 | DM49: 163.1 | DN49: 164.2 | DO49: 165 | DP49: 166 | DQ49: 166.9 | DR49: 167.3 | DS49: 168 | DT49: 169.2 | DU49: 169.2 | DV49: 169.6 | DW49: 170.1
A50: Urban | B50: =VLOOKUP(C50,'Broader Categories'!$A$1:$B$28,2,FALSE) -> Health | C50: Health | D50: 104.1 | E50: 104.7 | F50: 105.2 | G50: 105.7 | H50: 106.2 | I50: 106.5 | J50: 107.1 | K50: 107.6 | L50: 107.9 | M50: 108.2 | N50: 108.6 | O50: 109 | P50: 109.7 | Q50: 110.4 | R50: 110.8 | S50: 111 | T50: 111.2 | U50: 111.4 | V50: 111.5 | W50: 112.2 | X50: 112.3 | Y50: 112.6 | Z50: 113 | AA50: 113.2 | AB50: 113.7 | AC50: 114.1 | AD50: 114.3 | AE50: 114.6 | AF50: 114.9 | AG50: 115.4 | AH50: 116 | AI50: 116.6 | AJ50: 117.1 | AK50: 117.7 | AL50: 118.1 | AM50: 118.6 | AN50: 119.1 | AO50: 119.5 | AP50: 119.7 | AQ50: 120 | AR50: 120.3 | AS50: 120.6 | AT50: 120.9 | AU50: 121.2 | AV50: 121.4 | AW50: 121.8 | AX50: 122.1 | AY50: 122.3 | AZ50: 122.6 | BA50: 122.9 | BB50: 123.1 | BC50: 123.4 | BD50: 123.6 | BE50: 123.8 | BF50: 125 | BG50: 125.7 | BH50: 126.1 | BI50: 126.6 | BJ50: 127.4 | BK50: 128.2 | BL50: 129 | BM50: 129.8 | BN50: 130.5 | BO50: 131.3 | BP50: 132 | BQ50: 132.6 | BR50: 133.6 | BS50: 134.9 | BT50: 135.7 | BU50: 136.2 | BV50: 136.8 | BW50: 137.3 | BX50: 137.8 | BY50: 138.5 | BZ50: 139.2 | CA50: 139.8 | CB50: 140.3 | CC50: 140.8 | CD50: 141.5 | CE50: 141.9 | CF50: 142.4 | CG50: 142.8 | CH50: 143.2 | CI50: 143.8 | CJ50: 144.4 | CK50: 145 | CL50: 144.8 | CM50: NA | CN50: 148.1 | CO50: 148.1 | CP50: 148.7 | CQ50: 150 | CR50: 151 | CS50: 152 | CT50: 152.9 | CU50: 154.1 | CV50: 156.3 | CW50: 156.9 | CX50: 157.5 | CY50: 160.4 | CZ50: 160.8 | DA50: 161.5 | DB50: 162.8 | DC50: 162.8 | DD50: 163.5 | DE50: 164.2 | DF50: 165.1 | DG50: 166.1 | DH50: 167.2 | DI50: 168.2 | DJ50: 169 | DK50: 170.1 | DL50: 170.9 | DM50: 171.7 | DN50: 172.6 | DO50: 173.8 | DP50: 174.7 | DQ50: 175.8 | DR50: 177.2 | DS50: 178.5 | DT50: 180.8 | DU50: 180.8 | DV50: 181.5 | DW50: 182.2
A51: Urban | B51: =VLOOKUP(C51,'Broader Categories'!$A$1:$B$28,2,FALSE) -> Transport | C51: Transport and communication | D51: 103.2 | E51: 104.4 | F51: 105.5 | G51: 105 | H51: 103.9 | I51: 105.2 | J51: 107.3 | K51: 108.1 | L51: 110.4 | M51: 109.7 | N51: 109.5 | O51: 109.7 | P51: 110.8 | Q51: 111.3 | R51: 111.6 | S51: 111.2 | T51: 111.3 | U51: 111.5 | V51: 113 | W51: 112.5 | X51: 111.2 | Y51: 111 | Z51: 109.7 | AA51: 108.8 | AB51: 107.9 | AC51: 106.8 | AD51: 108.4 | AE51: 108.4 | AF51: 110.8 | AG51: 111.7 | AH51: 111.5 | AI51: 109.9 | AJ51: 109.1 | AK51: 109.3 | AL51: 109.3 | AM51: 109.3 | AN51: 108.9 | AO51: 109.1 | AP51: 108.5 | AQ51: 110 | AR51: 110.7 | AS51: 112.3 | AT51: 111.7 | AU51: 110.4 | AV51: 111.8 | AW51: 112.8 | AX51: 113.4 | AY51: 113.7 | AZ51: 115.2 | BA51: 115.5 | BB51: 115.6 | BC51: 114.3 | BD51: 114.3 | BE51: 113.9 | BF51: 113.2 | BG51: 114.6 | BH51: 115.7 | BI51: 115 | BJ51: 115.3 | BK51: 115.3 | BL51: 116.3 | BM51: 117.4 | BN51: 117.8 | BO51: 118.9 | BP51: 119.8 | BQ51: 120.4 | BR51: 120.1 | BS51: 120.7 | BT51: 122.5 | BU51: 123.3 | BV51: 121.2 | BW51: 118.8 | BX51: 118.6 | BY51: 119.2 | BZ51: 119.9 | CA51: 120.1 | CB51: 119.6 | CC51: 120.6 | CD51: 120.8 | CE51: 121.2 | CF51: 121.5 | CG51: 121.7 | CH51: 125.2 | CI51: 126.1 | CJ51: 125.2 | CK51: 124.6 | CL51: NA | CM51: NA | CN51: 129.3 | CO51: 129.3 | CP51: 133.9 | CQ51: 135.1 | CR51: 135.4 | CS51: 135.2 | CT51: 135.5 | CU51: 136.9 | CV51: 140.5 | CW51: 141.7 | CX51: 142.1 | CY51: 145 | CZ51: 147.5 | DA51: 149.5 | DB51: 150.4 | DC51: 150.5 | DD51: 152.2 | DE51: 151.2 | DF51: 151.8 | DG51: 152.7 | DH51: 153.1 | DI51: 154.2 | DJ51: 159.3 | DK51: 159.4 | DL51: 157.2 | DM51: 157.4 | DN51: 157.7 | DO51: 158.2 | DP51: 158.8 | DQ51: 158.9 | DR51: 159.4 | DS51: 159.5 | DT51: 159.8 | DU51: 159.8 | DV51: 160.1 | DW51: 160.4
A52: Urban | B52: =VLOOKUP(C52,'Broader Categories'!$A$1:$B$28,2,FALSE) -> Recreation | C52: Recreation and amusement | D52: 102.9 | E52: 103.3 | F52: 103.5 | G52: 104 | H52: 104.6 | I52: 105.2 | J52: 105.9 | K52: 106.5 | L52: 107.4 | M52: 108 | N52: 108.5 | O52: 108.9 | P52: 109.8 | Q52: 110.3 | R52: 110.9 | S52: 111.2 | T52: 111.5 | U52: 111.8 | V52: 112.4 | W52: 112.9 | X52: 113.4 | Y52: 113.6 | Z52: 114 | AA52: 114.3 | AB52: 114.6 | AC52: 114.9 | AD52: 115.4 | AE52: 115.6 | AF52: 116 | AG52: 116.2 | AH52: 116.6 | AI52: 117.2 | AJ52: 117.3 | AK52: 117.7 | AL52: 117.9 | AM52: 118.1 | AN52: 118.5 | AO52: 118.8 | AP52: 119.1 | AQ52: 119.5 | AR52: 119.8 | AS52: 119.9 | AT52: 120.3 | AU52: 120.6 | AV52: 120.8 | AW52: 121.2 | AX52: 121.7 | AY52: 121.8 | AZ52: 122 | BA52: 122.2 | BB52: 122.4 | BC52: 122.6 | BD52: 122.8 | BE52: 122.9 | BF52: 123.5 | BG52: 124.1 | BH52: 124.5 | BI52: 124.8 | BJ52: 125.1 | BK52: 125.6 | BL52: 126.2 | BM52: 126.5 | BN52: 126.8 | BO52: 127.6 | BP52: 128 | BQ52: 128.5 | BR52: 129 | BS52: 129.8 | BT52: 130.2 | BU52: 130.7 | BV52: 131.3 | BW52: 131.7 | BX52: 131.9 | BY52: 132.2 | BZ52: 133 | CA52: 134 | CB52: 134.3 | CC52: 135 | CD52: 135.4 | CE52: 135.9 | CF52: 136.2 | CG52: 136.7 | CH52: 136.8 | CI52: 137.2 | CJ52: 137.7 | CK52: 137.9 | CL52: NA | CM52: NA | CN52: 144.5 | CO52: 144.5 | CP52: 141.2 | CQ52: 141.8 | CR52: 142 | CS52: 144.4 | CT52: 144.3 | CU52: 145.4 | CV52: 147.3 | CW52: 148.6 | CX52: 149.1 | CY52: 152.6 | CZ52: 150.7 | DA52: 151.2 | DB52: 153.7 | DC52: 153.9 | DD52: 155.1 | DE52: 156.7 | DF52: 157.6 | DG52: 158.4 | DH52: 159.5 | DI52: 160.8 | DJ52: 162.2 | DK52: 163.2 | DL52: 164.1 | DM52: 164.6 | DN52: 165.1 | DO52: 165.8 | DP52: 166.3 | DQ52: 166.7 | DR52: 167.1 | DS52: 167.8 | DT52: 168.4 | DU52: 168.4 | DV52: 168.8 | DW52: 169.2
A53: Urban | B53: =VLOOKUP(C53,'Broader Categories'!$A$1:$B$28,2,FALSE) -> Education | C53: Education | D53: 103.5 | E53: 103.7 | F53: 103.8 | G53: 105.2 | H53: 105.7 | I53: 108.1 | J53: 110.1 | K53: 110.8 | L53: 111.2 | M53: 111.3 | N53: 111.3 | O53: 111.4 | P53: 111.5 | Q53: 111.6 | R53: 111.8 | S53: 112.5 | T53: 112.9 | U53: 115.1 | V53: 117.8 | W53: 119.2 | X53: 120 | Y53: 120.2 | Z53: 120.3 | AA53: 120.7 | AB53: 120.8 | AC53: 120.4 | AD53: 120.6 | AE53: 121.7 | AF53: 122 | AG53: 123.8 | AH53: 125.4 | AI53: 126.2 | AJ53: 126.5 | AK53: 126.5 | AL53: 126.6 | AM53: 126.6 | AN53: 126.4 | AO53: 126.3 | AP53: 126.4 | AQ53: 127.6 | AR53: 128 | AS53: 129.3 | AT53: 130.8 | AU53: 131.5 | AV53: 131.6 | AW53: 131.9 | AX53: 132.1 | AY53: 132.3 | AZ53: 132.4 | BA53: 132.4 | BB53: 132.8 | BC53: 133.6 | BD53: 133.8 | BE53: 134.3 | BF53: 135.5 | BG53: 135.7 | BH53: 135.9 | BI53: 136.3 | BJ53: 136.6 | BK53: 136.7 | BL53: 137.1 | BM53: 137.2 | BN53: 137.8 | BO53: 139.7 | BP53: 140.4 | BQ53: 141.2 | BR53: 144 | BS53: 145.3 | BT53: 145.2 | BU53: 145.5 | BV53: 146.1 | BW53: 146.5 | BX53: 146.6 | BY53: 146.6 | BZ53: 146.7 | CA53: 148 | CB53: 148.9 | CC53: 150.4 | CD53: 151.5 | CE53: 151.6 | CF53: 151.7 | CG53: 151.8 | CH53: 151.9 | CI53: 152.1 | CJ53: 152.2 | CK53: 152.5 | CL53: NA | CM53: NA | CN53: 152.5 | CO53: 152.5 | CP53: 155.5 | CQ53: 154.9 | CR53: 155.7 | CS53: 156.4 | CT53: 156.9 | CU53: 156.1 | CV53: 156.6 | CW53: 157.6 | CX53: 157.6 | CY53: 156.6 | CZ53: 158.1 | DA53: 160.3 | DB53: 160.4 | DC53: 160.3 | DD53: 160.3 | DE53: 160.8 | DF53: 160.6 | DG53: 161 | DH53: 162 | DI53: 162.7 | DJ53: 164 | DK53: 165.2 | DL53: 166.5 | DM53: 169.1 | DN53: 169.9 | DO53: 170.9 | DP53: 171.2 | DQ53: 171.5 | DR53: 171.8 | DS53: 171.8 | DT53: 172.5 | DU53: 172.5 | DV53: 174.2 | DW53: 174.8
A54: Urban | B54: =VLOOKUP(C54,'Broader Categories'!$A$1:$B$28,2,FALSE) -> Health | C54: Personal care and effects | D54: 104.3 | E54: 104.3 | F54: 104.2 | G54: 103.2 | H54: 102.6 | I54: 103.3 | J54: 103.2 | K54: 106 | L54: 106.9 | M54: 107.3 | N54: 107.9 | O54: 107.7 | P54: 108 | Q54: 108.7 | R54: 109.2 | S54: 109.1 | T54: 109.3 | U54: 108.7 | V54: 109.7 | W54: 110.5 | X54: 110 | Y54: 110.1 | Z54: 109.6 | AA54: 110.4 | AB54: 111.4 | AC54: 111.7 | AD54: 111.3 | AE54: 111.8 | AF54: 112.4 | AG54: 112.5 | AH54: 111.7 | AI54: 112 | AJ54: 112.9 | AK54: 113.5 | AL54: 113.3 | AM54: 113.2 | AN54: 114 | AO54: 116.2 | AP54: 117.1 | AQ54: 117.6 | AR54: 118.5 | AS54: 118.8 | AT54: 120 | AU54: 120.9 | AV54: 121.2 | AW54: 120.8 | AX54: 121.3 | AY54: 119.9 | AZ54: 120.9 | BA54: 121.7 | BB54: 121.7 | BC54: 122.2 | BD54: 122 | BE54: 122.5 | BF54: 122.4 | BG54: 123.3 | BH54: 124.4 | BI54: 124.6 | BJ54: 124.9 | BK54: 124.6 | BL54: 125.5 | BM54: 126.2 | BN54: 126.7 | BO54: 127.6 | BP54: 128.1 | BQ54: 128.2 | BR54: 128.2 | BS54: 128.3 | BT54: 129.3 | BU54: 130.4 | BV54: 130.5 | BW54: 130.8 | BX54: 131.7 | BY54: 133 | BZ54: 132.5 | CA54: 132.6 | CB54: 133.7 | CC54: 135.1 | CD54: 137.8 | CE54: 139 | CF54: 139.5 | CG54: 139.8 | CH54: 140.2 | CI54: 142.1 | CJ54: 143.5 | CK54: 145.3 | CL54: NA | CM54: NA | CN54: 152.2 | CO54: 152.2 | CP54: 155.2 | CQ54: 159.8 | CR54: 158.1 | CS54: 157.9 | CT54: 157.9 | CU54: 157.7 | CV54: 156.7 | CW54: 154.9 | CX54: 156.6 | CY54: 157.5 | CZ54: 158 | DA54: 159.6 | DB54: 159.6 | DC54: 159.6 | DD54: 160.3 | DE54: 161.8 | DF54: 162.4 | DG54: 162.8 | DH54: 164.2 | DI54: 166.8 | DJ54: 168.4 | DK54: 168.2 | DL54: 169.2 | DM54: 169.8 | DN54: 171.4 | DO54: 171.1 | DP54: 172.3 | DQ54: 173.8 | DR54: 176 | DS54: 178.8 | DT54: 181.4 | DU54: 181.5 | DV54: 184.4 | DW54: 185.6
